Workbook
Name AddLoans: '1-StartingPoint'!$D$36
Name Advertising: '1-StartingPoint'!$C$26
Name Annual_Interest_Rate: #REF!
Name Beg_Bal: #REF!
Name Buildings: '1-StartingPoint'!$C$10
Name Category1: '3a-SalesForecastYear1'!$B$9
Name Category1_Annual_Sales: '3a-SalesForecastYear1'!$O$19
Name Category1_SalesPrice: '3a-SalesForecastYear1'!#REF!
Name Category2: '3a-SalesForecastYear1'!$B$10
Name Category2_Annual_Sales: '3a-SalesForecastYear1'!$O$25
Name Category2_SalesPrice: '3a-SalesForecastYear1'!#REF!
Name Category3: '3a-SalesForecastYear1'!$B$11
Name Category3_Annual_Sales: '3a-SalesForecastYear1'!$O$31
Name Category3_SalesPrice: '3a-SalesForecastYear1'!#REF!
Name Category4: '3a-SalesForecastYear1'!$B$12
Name Category4_Annual_Sales: '3a-SalesForecastYear1'!$O$37
Name Category4_SalesPrice: '3a-SalesForecastYear1'!#REF!
Name Category5: '3a-SalesForecastYear1'!$B$13
Name Category5_Annual_Sales: '3a-SalesForecastYear1'!$O$43
Name Category5_SalesPrice: '3a-SalesForecastYear1'!#REF!
Name Category6: '3a-SalesForecastYear1'!$B$14
Name Category6_Annual_Sales: '3a-SalesForecastYear1'!$O$49
Name Category6_SalesPrice: '3a-SalesForecastYear1'!#REF!
Name Catergory6: '3a-SalesForecastYear1'!$B$14
Name CCDebt: '1-StartingPoint'!$D$39
Name COGS_Annual_Total: '3a-SalesForecastYear1'!$O$54
Name CommLoan: '1-StartingPoint'!$D$37
Name CommMortgage: '1-StartingPoint'!$D$38
Name ContingencyCash: '1-StartingPoint'!#REF!
Name Equipment: '1-StartingPoint'!$C$12
Name Extra_Pay: #REF!
Name Furniture: '1-StartingPoint'!$C$13
Name Growth_Rate_Yr2: '3b-SalesForecastYrs1-3'!$C$7
Name Growth_Rate_Yr3: '3b-SalesForecastYrs1-3'!$C$8
Name Info_Entered: #REF!
Name Int: #REF!
Name InterestRate_ShortTerm: #REF!
Name Inventory: '1-StartingPoint'!$C$21
Name Land: '1-StartingPoint'!$C$9
Name Last_Row: IF(Values_Entered,Header_Row+Number_of_Payments,Header_Row)
Name LeaseImprovements: '1-StartingPoint'!$C$11
Name LegalAcctFees: '1-StartingPoint'!$C$22
Name Licenses: '1-StartingPoint'!$C$27
Name Loan_Amount: #REF!
Name Loan_Term_Years: #REF!
Name LoanAmount_ShortTerm: #REF!
Name LoanTermYears_ShortTerm: #REF!
Name Margin_Annual_Total: '3a-SalesForecastYear1'!$O$55
Name Misc_Expenses: '5a-OpExYear1'!$O$19
Name Monthly_Payment_LongTerm: #REF!
Name NetIncomeY1: '7b-IncomeStatementYrs1-3'!$C$59
Name NetIncomeY2: '7b-IncomeStatementYrs1-3'!$E$59
Name NetIncomeY3: '7b-IncomeStatementYrs1-3'!$G$59
Name Number_of_Payments: MATCH(0.01,End_Bal,-1)+1
Name OfficeSupplies_Expenses: '5a-OpExYear1'!$O$20
Name Other_Expenses: '5a-OpExYear1'!$O$21
Name OtherBankDebt: '1-StartingPoint'!$D$41
Name OtherFixedAssets: '1-StartingPoint'!$C$15
Name OtherStartUp: '1-StartingPoint'!$C$28
Name OutsideInvest: '1-StartingPoint'!$D$35

Sheet Directions
B7: Step 1 - Enter info about your company in yellow shaded boxes below.
C9: Preparer Name | D9: Company Name | E9: Starting Month | F9: Starting Year
B12: Step 2 - Read the following instructions
C36: =IF(ISBLANK(E10),-10000,MONTH(DATEVALUE(E10&" 1"))) -> -10000
B38: =IF(Directions!$C$36>0,CHOOSE(Directions!$C$36,"January","February","March","April","May","June","July","August","September","October","November","December"),"Month 1") -> Month 1 | C38: =IF(Directions!$C$36+1>12,CHOOSE(Directions!$C$36+1-12,"January","February","March","April","May","June","July","August","September","October","November","December"),IF(Directions!$C$36<0,"Month 2",(CHOOSE(Directions!$C$36+1,"January","February","March","April","May","June","July","August","September","October","November","December")))) -> Month 2 | D38: =IF(Directions!$C$36+2>12,CHOOSE(Directions!$C$36+2-12,"January","February","March","April","May","June","July","August","September","October","November","December"),IF(Directions!$C$36<0,"Month 3",CHOOSE(Directions!$C$36+2,"January","February","March","April","May","June","July","August","September","October","November","December"))) -> Month 3 | E38: =IF(Directions!$C$36+3>12,CHOOSE(Directions!$C$36+3-12,"January","February","March","April","May","June","July","August","September","October","November","December"),IF(Directions!$C$36<0,"Month 4",CHOOSE(Directions!$C$36+3,"January","February","March","April","May","June","July","August","September","October","November","December"))) -> Month 4 | F38: =IF(Directions!$C$36+4>12,CHOOSE(Directions!$C$36+4-12,"January","February","March","April","May","June","July","August","September","October","November","December"),IF(Directions!$C$36<0,"Month 5",CHOOSE(Directions!$C$36+4,"January","February","March","April","May","June","July","August","September","October","November","December"))) -> Month 5 | G38: =IF(Directions!$C$36+5>12,CHOOSE(Directions!$C$36+5-12,"January","February","March","April","May","June","July","August","September","October","November","December"),IF(Directions!$C$36<0,"Month 6",CHOOSE(Directions!$C$36+5,"January","February","March","April","May","June","July","August","September","October","November","December"))) -> Month 6 | H38: =IF(Directions!$C$36+6>12,CHOOSE(Directions!$C$36+6-12,"January","February","March","April","May","June","July","August","September","October","November","December"),IF(Directions!$C$36<0,"Month 7",CHOOSE(Directions!$C$36+6,"January","February","March","April","May","June","July","August","September","October","November","December"))) -> Month 7 | I38: =IF(Directions!$C$36+7>12,CHOOSE(Directions!$C$36+7-12,"January","February","March","April","May","June","July","August","September","October","November","December"),IF(Directions!$C$36<0,"Month 8",CHOOSE(Directions!$C$36+7,"January","February","March","April","May","June","July","August","September","October","November","December"))) -> Month 8 | J38: =IF(Directions!$C$36+8>12,CHOOSE(Directions!$C$36+8-12,"January","February","March","April","May","June","July","August","September","October","November","December"),IF(Directions!$C$36<0,"Month 9",CHOOSE(Directions!$C$36+8,"January","February","March","April","May","June","July","August","September","October","November","December"))) -> Month 9 | K38: =IF(Directions!$C$36+9>12,CHOOSE(Directions!$C$36+9-12,"January","February","March","April","May","June","July","August","September","October","November","December"),IF(Directions!$C$36<0,"Month 10",CHOOSE(Directions!$C$36+9,"January","February","March","April","May","June","July","August","September","October","November","December"))) -> Month 10 | L38: =IF(Directions!$C$36+10>12,CHOOSE(Directions!$C$36+10-12,"January","February","March","April","May","June","July","August","September","October","November","December"),IF(Directions!$C$36<0,"Month 11",CHOOSE(Directions!$C$36+10,"January","February","March","April","May","June","July","August","September","October","November","December"))) -> Month 11 | M38: =IF(Directions!$C$36+11>12,CHOOSE(Directions!$C$36+11-12,"January","February","March","April","May","June","July","August","September","October","November","December"),IF(Directions!$C$36<0,"Month 12",CHOOSE(Directions!$C$36+11,"January","February","March","April","May","June","July","August","September","October","November","December"))) -> Month 12

Sheet 1-StartingPoint
B2: Start-up Expenses Year 1 (Starting Balance Sheet)
B4: Prepared By: | C4: Company Name:
B5: =IF(ISBLANK(Directions!C10),"Owner",Directions!C10) -> Owner | C5: =IF(ISBLANK(Directions!D10),"Company 1",Directions!D10) -> Company 1
B7: Fixed Assets | C7: Amount | D7: Depreciation (years) | E7: Notes
B9: Real Estate-Land | D9: Not Depreciated
B10: Real Estate-Buildings | D10: 20
B11: Leasehold Improvements | D11: 7
B12: Equipment | D12: 7
B13: Furniture and Fixtures | D13: 5
B14: Vehicles | D14: 5
B15: Other | D15: 5
B16: Total Fixed Assets | C16: =SUM(C9:C15) -> 0
B18: Operating Capital | C18: Amount | D18: Notes
B19: Pre-Opening Salaries and Wages
B20: Prepaid Insurance Premiums
B21: Inventory
B22: Legal and Accounting Fees
B23: Rent Deposits
B24: Utility Deposits
B25: Supplies
B26: Advertising and Promotions
B27: Licenses
B28: Other Initial Start-Up Costs
B29: Working Capital (Cash On Hand)
B30: Total Operating Capital | C30: =SUM(C19:C29) -> 0
B31: Total Required Funds | C31: =C16+C30 -> 0
B33: Sources of Funding | C33: Percentage | D33: Totals | E33: Loan Rate | F33: Term in Months | G33: Monthly Payments | H33: Notes
B34: Owner's Equity | C34: =IF($C$31=0,0,D34/$C$31) -> 0
B35: Outside Investors | C35: =IF($C$31=0,0,D35/$C$31) -> 0
B36: Additional Loans or Debt
B37: Commercial Loan | C37: =IF($C$31=0,0,D37/$C$31) -> 0 | E37: 0.09 | F37: 84 | G37: =PMT(E37/12,F37,-D37) -> 0
B38: Commercial Mortgage | C38: =IF($C$31=0,0,D38/$C$31) -> 0 | E38: 0.09 | F38: 240 | G38: =PMT(E38/12,F38,-D38) -> 0 | J38: See Loan Amortization & Depreciation Schedule
B39: Credit Card Debt | C39: =IF($C$31=0,0,D39/$C$31) -> 0 | E39: 0.07 | F39: 60 | G39: =PMT(E39/12,F39,-D39) -> 0
B40: Vehicle Loans | C40: =IF($C$31=0,0,D40/$C$31) -> 0 | E40: 0.06 | F40: 48 | G40: =PMT(E40/12,F40,-D40) -> 0
B41: Other Bank Debt | C41: =IF($C$31=0,0,D41/$C$31) -> 0 | E41: 0.05 | F41: 36 | G41: =PMT(E41/12,F41,-D41) -> 0
B42: Total Sources of Funding | C42: =IF($C$31=0,0,D42/$C$31) -> 0 | D42: =SUM(D34:D41) -> 0 | E42: Cell D 42 must equal cell C31 | G42: =SUM(G37:G41) -> 0
B43: Total Funding Needed | D43: =C31-D42 -> 0 | E43: =IF(D43>0,"You require more funding (Not Balanced)",IF(D43<0,"Your funding exceeds your needs (Not Balanced)","You are fully funded (Balanced)")) -> You are fully funded (Balanced)
B46: Existing Businesses ONLY -- Calculating Cash on Hand
B47: Cash | C47: 0
B48: + Accounts Receivable | C48: 0
B49: + Prepaid Expenses | C49: 0
B50: - Accounts Payable | C50: 0
B51: - Accrued Expenses | C51: 0
B52: Total Cash on Hand | C52: =(C47+C48+C49-C50-C51) -> 0

Sheet 2a-PayrollYear1
B2: Payroll Year 1
B4: Prepared By: | C4: Company Name:
B5: =IF(ISBLANK(Directions!C10),"Owner",Directions!C10) -> Owner | C5: =IF(ISBLANK(Directions!D10),"Company 1",Directions!D10) -> Company 1
A7: Employee Types | B7: Number of Owners /Employees | C7: Average Hourly Pay (to 2 decimal places, ex. $15.23) | D7: Estimated Hrs./Week (per person) | E7: Estimated Pay/Month (Total) | F7: =Directions!B38 -> Month 1 | G7: =Directions!C38 -> Month 2 | H7: =Directions!D38 -> Month 3 | I7: =Directions!E38 -> Month 4 | J7: =Directions!F38 -> Month 5 | K7: =Directions!G38 -> Month 6 | L7: =Directions!H38 -> Month 7 | M7: =Directions!I38 -> Month 8 | ... Q7: =Directions!M38 -> Month 12 | R7: Annual Totals
A8: Founder (You) | B8: 1 | C8: 38.46 | D8: 40 | E8: =(C8*D8*B8)*52/12 -> 6666.4 | F8: 0 | G8: 0 | H8: 0 | I8: 3000 | J8: 4000 | K8: 5000 | L8: 6000 | M8: 6000 | N8: 6667 | O8: 6667 | P8: 6667 | Q8: 6667 | R8: =SUM(F8:Q8) -> 50668
A9: Sales Representatives | B9: 0 | C9: 25 | D9: 40 | E9: =(C9*D9*B9)*52/12 -> 0 | F9: =E9 -> 0 | G9: =F9 -> 0 | H9: =G9 -> 0 | I9: =H9 -> 0 | J9: =I9 -> 0 | K9: =J9 -> 0 | L9: =K9 -> 0 | M9: =L9 -> 0 | ... Q9: =P9 -> 0 | R9: =SUM(F9:Q9) -> 0
A10: Account Executives | B10: 0 | C10: 28.85 | D10: 40 | E10: =(C10*D10*B10)*52/12 -> 0 | F10: =E10 -> 0 | G10: =F10 -> 0 | H10: =G10 -> 0 | I10: =H10 -> 0 | J10: =I10 -> 0 | K10: =J10 -> 0 | L10: =K10 -> 0 | M10: =L10 -> 0 | ... Q10: =P10 -> 0 | R10: =SUM(F10:Q10) -> 0
A11: Independent Contractors | B11: 0 | E11: =(C11*D11*B11)*52/12 -> 0 | F11: =E11 -> 0 | G11: =F11 -> 0 | H11: =G11 -> 0 | I11: =H11 -> 0 | J11: =I11 -> 0 | K11: =J11 -> 0 | L11: =K11 -> 0 | M11: =L11 -> 0 | ... Q11: =P11 -> 0 | R11: =SUM(F11:Q11) -> 0
A12: Total Salaries and Wages | B12: =SUM(B8:B11) -> 1 | C12: =SUM(C8:C11) -> 92.31 | D12: =SUM(D8:D11) -> 120 | E12: =SUM(E8:E11) -> 6666.4 | F12: =SUM(F8:F11) -> 0 | G12: =SUM(G8:G11) -> 0 | H12: =SUM(H8:H11) -> 0 | I12: =SUM(I8:I11) -> 3000 | ... R12: =SUM(R8:R11) -> 50668
A14: Payroll Taxes and Benefits | B14: Wage Base Limit | C14: Percentage of Salary/Wage | E14: Estimated Taxes & Benefits/Month (Total) | F14: ='3a-SalesForecastYear1'!C16 -> Month 1 | G14: ='3a-SalesForecastYear1'!D16 -> Month 2 | H14: ='3a-SalesForecastYear1'!E16 -> Month 3 | I14: ='3a-SalesForecastYear1'!F16 -> Month 4 | J14: ='3a-SalesForecastYear1'!G16 -> Month 5 | K14: ='3a-SalesForecastYear1'!H16 -> Month 6 | L14: ='3a-SalesForecastYear1'!I16 -> Month 7 | M14: ='3a-SalesForecastYear1'!J16 -> Month 8 | ... R14: ='3a-SalesForecastYear1'!O16 -> Annual Totals
A15: Social Security | B15: 137700 | C15: 0.062 | E15: =(E$8+E$9+E$10)*$C$15 -> 413.3168 | F15: =(F$8+F$9+F$10)*$C$15 -> 0 | G15: =(G$8+G$9+G$10)*$C$15 -> 0 | H15: =(H$8+H$9+H$10)*$C$15 -> 0 | I15: =(I$8+I$9+I$10)*$C$15 -> 186 | J15: =(J$8+J$9+J$10)*$C$15 -> 248 | K15: =(K$8+K$9+K$10)*$C$15 -> 310 | L15: =(L$8+L$9+L$10)*$C$15 -> 372 | ... Q15: =(Q$8+Q$9+Q$10)*$C$15 -> 413.354 | R15: =SUM(F15:Q15) -> 3141.416
A16: Medicare | B16: -- | C16: 0.0145 | E16: =(E$8+E$9+E$10)*$C$16 -> 96.6628 | F16: =(F$8+F$9+F$10)*$C$16 -> 0 | G16: =(G$8+G$9+G$10)*$C$16 -> 0 | H16: =(H$8+H$9+H$10)*$C$16 -> 0 | I16: =(I$8+I$9+I$10)*$C$16 -> 43.5 | J16: =(J$8+J$9+J$10)*$C$16 -> 58 | K16: =(K$8+K$9+K$10)*$C$16 -> 72.5 | L16: =(L$8+L$9+L$10)*$C$16 -> 87 | ... Q16: =(Q$8+Q$9+Q$10)*$C$16 -> 96.6715 | R16: =SUM(F16:Q16) -> 734.686
A17: Federal Unemployment Tax (FUTA) | B17: 7000 | C17: 0.006 | E17: =+$B$12*B17*C17/12 -> 3.5 | F17: =E17 -> 3.5 | G17: =F17 -> 3.5 | H17: =G17 -> 3.5 | I17: =H17 -> 3.5 | J17: =I17 -> 3.5 | K17: =J17 -> 3.5 | L17: =K17 -> 3.5 | M17: =L17 -> 3.5 | ... Q17: =P17 -> 3.5 | R17: =SUM(F17:Q17) -> 42
A18: State Unemployment Tax (SUTA) | B18: 7000 | C18: 0.0345 | E18: =+$B$12*B18*C18/12 -> 20.125 | F18: =E18 -> 20.125 | G18: =F18 -> 20.125 | H18: =G18 -> 20.125 | I18: =H18 -> 20.125 | J18: =I18 -> 20.125 | K18: =J18 -> 20.125 | L18: =K18 -> 20.125 | M18: =L18 -> 20.125 | ... Q18: =P18 -> 20.125 | R18: =SUM(F18:Q18) -> 241.5
A19: Employee Pension Programs | B19: -- | C19: 0 | D19: ed | E19: =($E$8+$E$9+$E$10)*C19 -> 0 | F19: =E19 -> 0 | G19: =F19 -> 0 | H19: =G19 -> 0 | I19: =H19 -> 0 | J19: =I19 -> 0 | K19: =J19 -> 0 | L19: =K19 -> 0 | M19: =L19 -> 0 | ... Q19: =P19 -> 0 | R19: =SUM(F19:Q19) -> 0
A20: Worker's Compensation | B20: -- | C20: 0 | E20: =($E$8+$E$9+$E$10)*C20 -> 0 | F20: =E20 -> 0 | G20: =F20 -> 0 | H20: =G20 -> 0 | I20: =H20 -> 0 | J20: =I20 -> 0 | K20: =J20 -> 0 | L20: =K20 -> 0 | M20: =L20 -> 0 | ... Q20: =P20 -> 0 | R20: =SUM(F20:Q20) -> 0
A21: Employee Health Insurance | B21: -- | C21: 0 | E21: =($E$8+$E$9+$E$10)*C21 -> 0 | F21: =E21 -> 0 | G21: =F21 -> 0 | H21: =G21 -> 0 | I21: =H21 -> 0 | J21: =I21 -> 0 | K21: =J21 -> 0 | L21: =K21 -> 0 | M21: =L21 -> 0 | ... Q21: =P21 -> 0 | R21: =SUM(F21:Q21) -> 0
A22: Other Employee Benefit Programs | B22: -- | C22: 0 | E22: =($E$8+$E$9+$E$10)*C22 -> 0 | F22: =E22 -> 0 | G22: =F22 -> 0 | H22: =G22 -> 0 | I22: =H22 -> 0 | J22: =I22 -> 0 | K22: =J22 -> 0 | L22: =K22 -> 0 | M22: =L22 -> 0 | ... Q22: =P22 -> 0 | R22: =SUM(F22:Q22) -> 0
A23: Total Payroll Taxes and Benefits | C23: =SUM(C15:C22) -> 0.117 | E23: =SUM(E15:E22) -> 533.6046 | F23: =SUM(F15:F22) -> 23.625 | G23: =SUM(G15:G22) -> 23.625 | H23: =SUM(H15:H22) -> 23.625 | I23: =SUM(I15:I22) -> 253.125 | J23: =SUM(J15:J22) -> 329.625 | K23: =SUM(K15:K22) -> 406.125 | L23: =SUM(L15:L22) -> 482.625 | ... R23: =SUM(R15:R22) -> 4159.602
A25: Total Salaries and Related Expenses | E25: =E12+E23 -> 7200.0046 | F25: =F12+F23 -> 23.625 | G25: =G12+G23 -> 23.625 | H25: =H12+H23 -> 23.625 | I25: =I12+I23 -> 3253.125 | J25: =J12+J23 -> 4329.625 | K25: =K12+K23 -> 5406.125 | L25: =L12+L23 -> 6482.625 | ... R25: =R12+R23 -> 54827.602

Sheet 2b-PayrollYrs1-3
B2: Payroll Years 1-3
B4: Prepared By: | C4: Company Name:
B5: =IF(ISBLANK(Directions!C10),"Owner",Directions!C10) -> Owner | C5: =IF(ISBLANK(Directions!D10),"Company 1",Directions!D10) -> Company 1
B8: Employee Types | C8: Year 1 Totals | D8: Growth Rate 1 to 2 | E8: =IF(Directions!G7>0,Directions!G7+1,"Second Year") -> Second Year | F8: Growth Rate 2 to 3 | G8: =IF(Directions!G7>0,Directions!G7+2,"Third Year") -> Third Year
B9: Owner(s) | C9: ='2a-PayrollYear1'!R8 -> 50668 | D9: 0.2 | E9: =C9*D9+C9 -> 60801.6 | F9: 0.3 | G9: =E9*F9+E9 -> 79042.08
B10: Full-Time Employees | C10: ='2a-PayrollYear1'!R9 -> 0 | D10: 0.2 | E10: =C10*D10+C10 -> 0 | F10: 0.3 | G10: =E10*F10+E10 -> 0
B11: Part-Time Employees | C11: ='2a-PayrollYear1'!R10 -> 0 | D11: 0.1 | E11: =C11*D11+C11 -> 0 | F11: 0.3 | G11: =E11*F11+E11 -> 0
B12: Independent Contractors | C12: ='2a-PayrollYear1'!R11 -> 0 | D12: 0.03 | E12: =C12*D12+C12 -> 0 | F12: 0.03 | G12: =E12*F12+E12 -> 0
B13: Total Salaries and Wages | C13: =SUM(C9:C12) -> 50668 | E13: =SUM(E9:E12) -> 60801.6 | G13: =SUM(G9:G12) -> 79042.08
B15: Payroll Taxes and Benefits
B16: Social Security | C16: ='2a-PayrollYear1'!R15 -> 3141.416 | D16: 0.2 | E16: =C16*D16+C16 -> 3769.6992 | F16: 0.3 | G16: =E16*F16+E16 -> 4900.609
B17: Medicare | C17: ='2a-PayrollYear1'!R16 -> 734.686 | D17: 0.2 | E17: =C17*D17+C17 -> 881.6232 | F17: 0.3 | G17: =E17*F17+E17 -> 1146.1102
B18: Federal Unemployment Tax (FUTA) | C18: ='2a-PayrollYear1'!R17 -> 42 | D18: 0.2 | E18: =C18*D18+C18 -> 50.4 | F18: 0.3 | G18: =E18*F18+E18 -> 65.52
B19: State Unemployment Tax (SUTA) | C19: ='2a-PayrollYear1'!R18 -> 241.5 | D19: 0.2 | E19: =C19*D19+C19 -> 289.8 | F19: 0.3 | G19: =E19*F19+E19 -> 376.74
B20: Employee Pension Programs | C20: ='2a-PayrollYear1'!R19 -> 0 | D20: 0 | E20: =C20*D20+C20 -> 0 | F20: 0 | G20: =E20*F20+E20 -> 0
B21: Worker's Compensation | C21: ='2a-PayrollYear1'!R20 -> 0 | D21: 0.03 | E21: =C21*D21+C21 -> 0 | F21: 0.03 | G21: =E21*F21+E21 -> 0
B22: Employee Health Insurance | C22: ='2a-PayrollYear1'!R21 -> 0 | D22: 0.03 | E22: =C22*D22+C22 -> 0 | F22: 0.03 | G22: =E22*F22+E22 -> 0
B23: Other Employee Benefit Programs | C23: ='2a-PayrollYear1'!R22 -> 0 | D23: 0.1 | E23: =C23*D23+C23 -> 0 | F23: 0.1 | G23: =E23*F23+E23 -> 0
B24: Total Payroll Taxes and Benefits | C24: =SUM(C16:C23) -> 4159.602 | E24: =SUM(E16:E23) -> 4991.5224 | G24: =SUM(G16:G23) -> 6488.9791
B26: Total Salaries and Related Expenses | C26: =SUM(C13+C24) -> 54827.602 | E26: =SUM(E13+E24) -> 65793.122 | G26: =SUM(G13+G24) -> 85531.059

Sheet 3a-SalesForecastYear1
B2: Sales Forecast Year 1 Q1 | D2: Q2 | E2: Q3 | F2: Q4
B3: Monthly Growth Rate by Qtr Yr1 | C3: 1 | D3: 0.5 | E3: 0.5 | F3: 0.5
B4: Prepared By: | C4: Company Name:
B5: =IF(ISBLANK(Directions!C10),"Owner",Directions!C10) -> Owner | C5: =IF(ISBLANK(Directions!D10),"Company 1",Directions!D10) -> Company 1
B7: Complete This Chart First:
B8: Product Lines | C8: Units | D8: Sales Price Per Unit | E8: COGS Per Unit | F8: Margin Per Unit
B9: Number of Contractors | C9: 1 | D9: {='4-AdditionalInputs'!C56} -> 540 | E9: {='4-AdditionalInputs'!C65} -> 180 | F9: =D9-E9 -> 360
B10: Immediate Revenue (70%) | C10: 1 | D10: ='4-AdditionalInputs'!C56*'4-AdditionalInputs'!C59 -> 378 | E10: {='4-AdditionalInputs'!C65} -> 180 | F10: =D10-E10 -> 198
B11: Deferred Revenue - 1 Month (20%) | C11: 1 | D11: ='4-AdditionalInputs'!C56*'4-AdditionalInputs'!C60 -> 108 | E11: 0 | F11: =D11-E11 -> 108
B12: Deferred Revenue - 6 Months (10%) | C12: 1 | D12: ='4-AdditionalInputs'!C56*'4-AdditionalInputs'!C61 -> 54 | E12: 0 | F12: =D12-E12 -> 54
F13: =D13-E13 -> 0
F14: =D14-E14 -> 0
B16: Product Lines | C16: ='2a-PayrollYear1'!F7 -> Month 1 | D16: ='2a-PayrollYear1'!G7 -> Month 2 | E16: ='2a-PayrollYear1'!H7 -> Month 3 | F16: ='2a-PayrollYear1'!I7 -> Month 4 | G16: ='2a-PayrollYear1'!J7 -> Month 5 | H16: ='2a-PayrollYear1'!K7 -> Month 6 | I16: ='2a-PayrollYear1'!L7 -> Month 7 | J16: ='2a-PayrollYear1'!M7 -> Month 8 | ... N16: ='2a-PayrollYear1'!Q7 -> Month 12 | O16: Annual Totals | P16: Category Breakdown | Q16: Category / Total
B17: =IF(ISBLANK(B9),"Product 1",B9) -> Number of Contractors
B18: =IF(ISBLANK(C9),"Units Sold",Unit1&" Sold") -> 1 Sold | C18: 18 | D18: 18 | E18: 18 | F18: 35 | G18: 35 | H18: 35 | I18: 53 | J18: 53 | K18: 70 | L18: 70 | M18: 88 | N18: 106 | O18: =SUM(C18:N18) -> 599 | Q18: =IF($O$52=0,0,O18/$O$52) -> 0.32378378
B19: Total Sales | C19: =$D$9*C18 -> 9720 | D19: =$D$9*D18 -> 9720 | E19: =$D$9*E18 -> 9720 | F19: =$D$9*F18 -> 18900 | G19: =$D$9*G18 -> 18900 | H19: =$D$9*H18 -> 18900 | I19: =$D$9*I18 -> 28620 | J19: =$D$9*J18 -> 28620 | ... N19: =$D$9*N18 -> 57240 | O19: =SUM(C19:N19) -> 323460 | P19: =(P20+P21) -> 1 | Q19: =IF($O$53=0,0,O19/$O$53) -> 0.52877825
B20: Total COGS | C20: =$E$9*C18 -> 3240 | D20: =$E$9*D18 -> 3240 | E20: =$E$9*E18 -> 3240 | F20: =$E$9*F18 -> 6300 | G20: =$E$9*G18 -> 6300 | H20: =$E$9*H18 -> 6300 | I20: =$E$9*I18 -> 9540 | J20: =$E$9*J18 -> 9540 | ... N20: =$E$9*N18 -> 19080 | O20: =SUM(C20:N20) -> 107820 | P20: =IF(O19=0,0,O20/O19) -> 0.33333333 | Q20: =IF($O$54=0,0,O20/$O$54) -> 0.5
B21: Total Margin | C21: =C19-C20 -> 6480 | D21: =D19-D20 -> 6480 | E21: =E19-E20 -> 6480 | F21: =F19-F20 -> 12600 | G21: =G19-G20 -> 12600 | H21: =H19-H20 -> 12600 | I21: =I19-I20 -> 19080 | J21: =J19-J20 -> 19080 | ... N21: =N19-N20 -> 38160 | O21: =SUM(C21:N21) -> 215640 | P21: =IF(O19=0,0,O21/O19) -> 0.66666667 | Q21: =IF($O$55=0,0,O21/$O$55) -> 0.54444646
B23: =IF(ISBLANK(B10),"Product 2",B10) -> Immediate Revenue (70%)
B24: =IF(ISBLANK(C10),"Units Sold",Unit2&" Sold") -> 1 Sold | C24: {=C18} -> 18 | D24: {=D18} -> 18 | E24: {=E18} -> 18 | F24: {=F18} -> 35 | G24: {=G18} -> 35 | H24: {=H18} -> 35 | I24: {=I18} -> 53 | J24: {=J18} -> 53 | ... N24: {=N18} -> 106 | O24: =SUM(C24:N24) -> 599 | Q24: =IF($O$52=0,0,O24/$O$52) -> 0.32378378
B25: Total Sales | C25: =$D$10*C24 -> 6804 | D25: =$D$10*D24 -> 6804 | E25: =$D$10*E24 -> 6804 | F25: =$D$10*F24 -> 13230 | G25: =$D$10*G24 -> 13230 | H25: =$D$10*H24 -> 13230 | I25: =$D$10*I24 -> 20034 | J25: =$D$10*J24 -> 20034 | ... N25: =$D$10*N24 -> 40068 | O25: =SUM(C25:N25) -> 226422 | P25: =(P26+P27) -> 1 | Q25: =IF($O$53=0,0,O25/$O$53) -> 0.37014477
B26: Total COGS | C26: =$E$10*C24 -> 3240 | D26: =$E$10*D24 -> 3240 | E26: =$E$10*E24 -> 3240 | F26: =$E$10*F24 -> 6300 | G26: =$E$10*G24 -> 6300 | H26: =$E$10*H24 -> 6300 | I26: =$E$10*I24 -> 9540 | J26: =$E$10*J24 -> 9540 | ... N26: =$E$10*N24 -> 19080 | O26: =SUM(C26:N26) -> 107820 | P26: =IF(O25=0,0,O26/O25) -> 0.47619048 | Q26: =IF($O$54=0,0,O26/$O$54) -> 0.5
B27: Margin | C27: =C25-C26 -> 3564 | D27: =D25-D26 -> 3564 | E27: =E25-E26 -> 3564 | F27: =F25-F26 -> 6930 | G27: =G25-G26 -> 6930 | H27: =H25-H26 -> 6930 | I27: =I25-I26 -> 10494 | J27: =J25-J26 -> 10494 | ... N27: =N25-N26 -> 20988 | O27: =SUM(C27:N27) -> 118602 | P27: =IF(O25=0,0,O27/O25) -> 0.52380952 | Q27: =IF($O$55=0,0,O27/$O$55) -> 0.29944556
B29: =IF(ISBLANK(B11),"Product 3",B11) -> Deferred Revenue - 1 Month (20%)
B30: =IF(ISBLANK(C11),"Units Sold",Unit3&" Sold") -> 1 Sold | C30: 0 | D30: {=C18} -> 18 | E30: {=D18} -> 18 | F30: {=E18} -> 18 | G30: {=F18} -> 35 | H30: {=G18} -> 35 | I30: {=H18} -> 35 | J30: {=I18} -> 53 | K30: {=J18} -> 53 | ... N30: {=M18} -> 88 | O30: =SUM(C30:N30) -> 493 | Q30: =IF($O$52=0,0,O30/$O$52) -> 0.26648649
B31: Total Sales | C31: =$D$11*C30 -> 0 | D31: =$D$11*D30 -> 1944 | E31: =$D$11*E30 -> 1944 | F31: =$D$11*F30 -> 1944 | G31: =$D$11*G30 -> 3780 | H31: =$D$11*H30 -> 3780 | I31: =$D$11*I30 -> 3780 | J31: =$D$11*J30 -> 5724 | ... N31: =$D$11*N30 -> 9504 | O31: =SUM(C31:N31) -> 53244 | P31: =(P32+P33) -> 1 | Q31: =IF($O$53=0,0,O31/$O$53) -> 0.08704096
B32: Total COGS | C32: =$E$11*C30 -> 0 | D32: =$E$11*D30 -> 0 | E32: =$E$11*E30 -> 0 | F32: =$E$11*F30 -> 0 | G32: =$E$11*G30 -> 0 | H32: =$E$11*H30 -> 0 | I32: =$E$11*I30 -> 0 | J32: =$E$11*J30 -> 0 | ... N32: =$E$11*N30 -> 0 | O32: =SUM(C32:N32) -> 0 | P32: =IF(O31=0,0,O32/O31) -> 0 | Q32: =IF($O$54=0,0,O32/$O$54) -> 0
B33: Margin | C33: =C31-C32 -> 0 | D33: =D31-D32 -> 1944 | E33: =E31-E32 -> 1944 | F33: =F31-F32 -> 1944 | G33: =G31-G32 -> 3780 | H33: =H31-H32 -> 3780 | I33: =I31-I32 -> 3780 | J33: =J31-J32 -> 5724 | ... N33: =N31-N32 -> 9504 | O33: =SUM(C33:N33) -> 53244 | P33: =IF(O31=0,0,O33/O31) -> 1 | Q33: =IF($O$55=0,0,O33/$O$55) -> 0.1344301
B35: =IF(ISBLANK(B12),"Product 4",B12) -> Deferred Revenue - 6 Months (10%)
B36: =IF(ISBLANK(C12),"Units Sold",Unit4&" Sold") -> 1 Sold | C36: 0 | D36: 0 | E36: 0 | F36: 0 | G36: 0 | H36: 0 | I36: {=C18} -> 18 | J36: {=D18} -> 18 | K36: {=E18} -> 18 | L36: {=F18} -> 35 | M36: {=G18} -> 35 | N36: {=H18} -> 35 | O36: =SUM(C36:N36) -> 159 | Q36: =IF($O$52=0,0,O36/$O$52) -> 0.085945946
B37: Total Sales | C37: =$D$12*C36 -> 0 | D37: =$D$12*D36 -> 0 | E37: =$D$12*E36 -> 0 | F37: =$D$12*F36 -> 0 | G37: =$D$12*G36 -> 0 | H37: =$D$12*H36 -> 0 | I37: =$D$12*I36 -> 972 | J37: =$D$12*J36 -> 972 | ... N37: =$D$12*N36 -> 1890 | O37: =SUM(C37:N37) -> 8586 | P37: =(P38+P39) -> 1 | Q37: =IF($O$53=0,0,O37/$O$53) -> 0.014036017
B38: Total COGS | C38: =$E$12*C36 -> 0 | D38: =$E$12*D36 -> 0 | E38: =$E$12*E36 -> 0 | F38: =$E$12*F36 -> 0 | G38: =$E$12*G36 -> 0 | H38: =$E$12*H36 -> 0 | I38: =$E$12*I36 -> 0 | J38: =$E$12*J36 -> 0 | ... N38: =$E$12*N36 -> 0 | O38: =SUM(C38:N38) -> 0 | P38: =IF(O37=0,0,O38/O37) -> 0 | Q38: =IF($O$54=0,0,O38/$O$54) -> 0
B39: Margin | C39: =C37-C38 -> 0 | D39: =D37-D38 -> 0 | E39: =E37-E38 -> 0 | F39: =F37-F38 -> 0 | G39: =G37-G38 -> 0 | H39: =H37-H38 -> 0 | I39: =I37-I38 -> 972 | J39: =J37-J38 -> 972 | ... N39: =N37-N38 -> 1890 | O39: =SUM(C39:N39) -> 8586 | P39: =IF(O37=0,0,O39/O37) -> 1 | Q39: =IF($O$55=0,0,O39/$O$55) -> 0.021677877
B41: =IF(ISBLANK(B13),"Product 5",B13) -> Product 5
B42: =IF(ISBLANK(C13),"Units Sold",Unit5&" Sold") -> Units Sold | D42: =C42+C42*$C$3 -> 0 | E42: =D42+D42*$C$3 -> 0 | F42: =E42+E42*$D$3 -> 0 | G42: =F42+F42*$D$3 -> 0 | H42: =G42+G42*$D$3 -> 0 | I42: =H42+H42*$E$3 -> 0 | J42: =I42+I42*$E$3 -> 0 | K42: =J42+J42*$E$3 -> 0 | L42: =K42+K42*$F$3 -> 0 | M42: =L42+L42*$F$3 -> 0 | N42: =M42+M42*$F$3 -> 0 | O42: =SUM(C42:N42) -> 0 | Q42: =IF($O$52=0,0,O42/$O$52) -> 0
B43: Total Sales | C43: =$D$13*C42 -> 0 | D43: =$D$13*D42 -> 0 | E43: =$D$13*E42 -> 0 | F43: =$D$13*F42 -> 0 | G43: =$D$13*G42 -> 0 | H43: =$D$13*H42 -> 0 | I43: =$D$13*I42 -> 0 | J43: =$D$13*J42 -> 0 | ... N43: =$D$13*N42 -> 0 | O43: =SUM(C43:N43) -> 0 | P43: =(P44+P45) -> 0 | Q43: =IF($O$53=0,0,O43/$O$53) -> 0
B44: Total COGS | C44: =$E$13*C42 -> 0 | D44: =$E$13*D42 -> 0 | E44: =$E$13*E42 -> 0 | F44: =$E$13*F42 -> 0 | G44: =$E$13*G42 -> 0 | H44: =$E$13*H42 -> 0 | I44: =$E$13*I42 -> 0 | J44: =$E$13*J42 -> 0 | ... N44: =$E$13*N42 -> 0 | O44: =SUM(C44:N44) -> 0 | P44: =IF(O43=0,0,O44/O43) -> 0 | Q44: =IF($O$54=0,0,O44/$O$54) -> 0
B45: Margin | C45: =C43-C44 -> 0 | D45: =D43-D44 -> 0 | E45: =E43-E44 -> 0 | F45: =F43-F44 -> 0 | G45: =G43-G44 -> 0 | H45: =H43-H44 -> 0 | I45: =I43-I44 -> 0 | J45: =J43-J44 -> 0 | ... N45: =N43-N44 -> 0 | O45: =SUM(C45:N45) -> 0 | P45: =IF(O43=0,0,O45/O43) -> 0 | Q45: =IF($O$55=0,0,O45/$O$55) -> 0
B47: =IF(ISBLANK(B14),"Product 6",B14) -> Product 6
B48: =IF(ISBLANK(C14),"Units Sold",Unit6&" Sold") -> Units Sold | D48: =C48+C48*$C$3 -> 0 | E48: =D48+D48*$C$3 -> 0 | F48: =E48+E48*$D$3 -> 0 | G48: =F48+F48*$D$3 -> 0 | H48: =G48+G48*$D$3 -> 0 | I48: =H48+H48*$E$3 -> 0 | J48: =I48+I48*$E$3 -> 0 | K48: =J48+J48*$E$3 -> 0 | L48: =K48+K48*$F$3 -> 0 | M48: =L48+L48*$F$3 -> 0 | N48: =M48+M48*$F$3 -> 0 | O48: =SUM(C48:N48) -> 0 | Q48: =IF($O$52=0,0,O48/$O$52) -> 0
B49: Total Sales | C49: =$D$14*C48 -> 0 | D49: =$D$14*D48 -> 0 | E49: =$D$14*E48 -> 0 | F49: =$D$14*F48 -> 0 | G49: =$D$14*G48 -> 0 | H49: =$D$14*H48 -> 0 | I49: =$D$14*I48 -> 0 | J49: =$D$14*J48 -> 0 | ... N49: =$D$14*N48 -> 0 | O49: =SUM(C49:N49) -> 0 | P49: =(P50+P51) -> 0 | Q49: =IF($O$53=0,0,O49/$O$53) -> 0
B50: Total COGS | C50: =$E$14*C48 -> 0 | D50: =$E$14*D48 -> 0 | E50: =$E$14*E48 -> 0 | F50: =$E$14*F48 -> 0 | G50: =$E$14*G48 -> 0 | H50: =$E$14*H48 -> 0 | I50: =$E$14*I48 -> 0 | J50: =$E$14*J48 -> 0 | ... N50: =$E$14*N48 -> 0 | O50: =SUM(C50:N50) -> 0 | P50: =IF(O49=0,0,O50/O49) -> 0 | Q50: =IF($O$54=0,0,O50/$O$54) -> 0
B51: Margin | C51: =C49-C50 -> 0 | D51: =D49-D50 -> 0 | E51: =E49-E50 -> 0 | F51: =F49-F50 -> 0 | G51: =G49-G50 -> 0 | H51: =H49-H50 -> 0 | I51: =I49-I50 -> 0 | J51: =J49-J50 -> 0 | ... N51: =N49-N50 -> 0 | O51: =SUM(C51:N51) -> 0 | P51: =IF(O49=0,0,O51/O49) -> 0 | Q51: =IF($O$55=0,0,O51/$O$55) -> 0
B52: Total Units Sold | C52: =C18+C24+C30+C36+C42+C48 -> 36 | D52: =D18+D24+D30+D36+D42+D48 -> 54 | E52: =E18+E24+E30+E36+E42+E48 -> 54 | F52: =F18+F24+F30+F36+F42+F48 -> 88 | G52: =G18+G24+G30+G36+G42+G48 -> 105 | H52: =H18+H24+H30+H36+H42+H48 -> 105 | I52: =I18+I24+I30+I36+I42+I48 -> 159 | J52: =J18+J24+J30+J36+J42+J48 -> 177 | ... N52: =N18+N24+N30+N36+N42+N48 -> 335 | O52: =SUM(C52:N52) -> 1850
B53: Total Sales | C53: =C19+C25+C31+C37+C43+C49 -> 16524 | D53: =D19+D25+D31+D37+D43+D49 -> 18468 | E53: =E19+E25+E31+E37+E43+E49 -> 18468 | F53: =F19+F25+F31+F37+F43+F49 -> 34074 | G53: =G19+G25+G31+G37+G43+G49 -> 35910 | H53: =H19+H25+H31+H37+H43+H49 -> 35910 | I53: =I19+I25+I31+I37+I43+I49 -> 53406 | J53: =J19+J25+J31+J37+J43+J49 -> 55350 | ... N53: =N19+N25+N31+N37+N43+N49 -> 108702 | O53: =SUM(C53:N53) -> 611712
B54: Total Cost of Goods Sold | C54: =C20+C26+C32+C38+C44+C50 -> 6480 | D54: =D20+D26+D32+D38+D44+D50 -> 6480 | E54: =E20+E26+E32+E38+E44+E50 -> 6480 | F54: =F20+F26+F32+F38+F44+F50 -> 12600 | G54: =G20+G26+G32+G38+G44+G50 -> 12600 | H54: =H20+H26+H32+H38+H44+H50 -> 12600 | I54: =I20+I26+I32+I38+I44+I50 -> 19080 | J54: =J20+J26+J32+J38+J44+J50 -> 19080 | ... N54: =N20+N26+N32+N38+N44+N50 -> 38160 | O54: =SUM(C54:N54) -> 215640
B55: Total Margin | C55: =C53-C54 -> 10044 | D55: =D53-D54 -> 11988 | E55: =E53-E54 -> 11988 | F55: =F53-F54 -> 21474 | G55: =G53-G54 -> 23310 | H55: =H53-H54 -> 23310 | I55: =I53-I54 -> 34326 | J55: =J53-J54 -> 36270 | ... N55: =N53-N54 -> 70542 | O55: =O21+O27+O33+O39+O45+O51 -> 396072

Sheet 3b-SalesForecastYrs1-3
B2: Sales Forecast Year 1-3
B4: Prepared by: | C4: Company Name:
B5: =IF(ISBLANK(Directions!C10),"Owner",Directions!C10) -> Owner | C5: =IF(ISBLANK(Directions!D10),"Company 1",Directions!D10) -> Company 1
B7: Monthly Growth Rate Year 2 | C7: 0.03
B8: Monthly Growth Rate Year 3 | C8: 0.02
A10: Product Lines | B10: Year 1 Totals | C10: ='2a-PayrollYear1'!F7 -> Month 1 | D10: ='2a-PayrollYear1'!G7 -> Month 2 | E10: ='2a-PayrollYear1'!H7 -> Month 3 | F10: ='2a-PayrollYear1'!I7 -> Month 4 | G10: ='2a-PayrollYear1'!J7 -> Month 5 | H10: ='2a-PayrollYear1'!K7 -> Month 6 | I10: ='2a-PayrollYear1'!L7 -> Month 7 | J10: ='2a-PayrollYear1'!M7 -> Month 8 | ... N10: ='2a-PayrollYear1'!Q7 -> Month 12 | O10: Year 2 Totals | P10: Category Breakdown | Q10: Category / Total | R10: ='2a-PayrollYear1'!F7 -> Month 1 | S10: ='2a-PayrollYear1'!G7 -> Month 2 | T10: ='2a-PayrollYear1'!H7 -> Month 3 | U10: ='2a-PayrollYear1'!I7 -> Month 4 | V10: ='2a-PayrollYear1'!J7 -> Month 5 | W10: ='2a-PayrollYear1'!K7 -> Month 6 | X10: ='2a-PayrollYear1'!L7 -> Month 7 | Y10: ='2a-PayrollYear1'!M7 -> Month 8 | ... AC10: ='2a-PayrollYear1'!Q7 -> Month 12 | AD10: Year 3 Totals | AE10: Category Breakdown | AF10: Category / Total
A11: ='3a-SalesForecastYear1'!B17 -> Number of Contractors
A12: =Unit1&" Sold" -> 1 Sold | B12: =Unit1_Annual -> 599 | C12: ='3a-SalesForecastYear1'!N18 -> 106 | D12: =C12+C12*$C$7 -> 109.18 | E12: =D12+D12*$C$7 -> 112.4554 | F12: =E12+E12*$C$7 -> 115.82906 | G12: =F12+F12*$C$7 -> 119.30393 | H12: =G12+G12*$C$7 -> 122.88305 | I12: =H12+H12*$C$7 -> 126.56954 | J12: =I12+I12*$C$7 -> 130.36663 | K12: =J12+J12*$C$7 -> 134.27763 | ... N12: =M12+M12*$C$7 -> 146.72879 | O12: =SUM(C12:N12) -> 1504.3551 | Q12: =IF($O$46=0,0,O12/$O$46) -> 0.31641791 | R12: =N12 -> 146.72879 | S12: =R12+R12*$C$8 -> 149.66337 | T12: =S12+S12*$C$8 -> 152.65663 | U12: =T12+T12*$C$8 -> 155.70977 | V12: =U12+U12*$C$8 -> 158.82396 | W12: =V12+V12*$C$8 -> 162.00044 | X12: =W12+W12*$C$8 -> 165.24045 | Y12: =X12+X12*$C$8 -> 168.54526 | Z12: =Y12+Y12*$C$8 -> 171.91616 | ... AC12: =AB12+AB12*$C$8 -> 182.43881 | AD12: =SUM(R12:AC12) -> 1967.9397 | AF12: =IF($AD$46=0,0,AD12/$AD$46) -> 0.31641791
A13: Total Sales | B13: =Category1_Annual_Sales -> 323460 | C13: =+C12*'3a-SalesForecastYear1'!$D$9 -> 57240 | D13: =+D12*'3a-SalesForecastYear1'!$D$9 -> 58957.2 | E13: =+E12*'3a-SalesForecastYear1'!$D$9 -> 60725.916 | F13: =+F12*'3a-SalesForecastYear1'!$D$9 -> 62547.693 | G13: =+G12*'3a-SalesForecastYear1'!$D$9 -> 64424.124 | H13: =+H12*'3a-SalesForecastYear1'!$D$9 -> 66356.848 | I13: =+I12*'3a-SalesForecastYear1'!$D$9 -> 68347.553 | J13: =+J12*'3a-SalesForecastYear1'!$D$9 -> 70397.98 | ... N13: =+N12*'3a-SalesForecastYear1'!$D$9 -> 79233.547 | O13: =SUM(C13:N13) -> 812351.77 | P13: =(P14+P15) -> 1 | Q13: =IF($O$47=0,0,O13/$O$47) -> 0.52657725 | R13: =+R12*'3a-SalesForecastYear1'!$D$9 -> 79233.547 | S13: =+S12*'3a-SalesForecastYear1'!$D$9 -> 80818.218 | T13: =+T12*'3a-SalesForecastYear1'!$D$9 -> 82434.582 | U13: =+U12*'3a-SalesForecastYear1'!$D$9 -> 84083.274 | V13: =+V12*'3a-SalesForecastYear1'!$D$9 -> 85764.939 | W13: =+W12*'3a-SalesForecastYear1'!$D$9 -> 87480.238 | X13: =+X12*'3a-SalesForecastYear1'!$D$9 -> 89229.843 | Y13: =+Y12*'3a-SalesForecastYear1'!$D$9 -> 91014.44 | ... AC13: =+AC12*'3a-SalesForecastYear1'!$D$9 -> 98516.956 | AD13: =SUM(R13:AC13) -> 1062687.4 | AE13: =(AE14+AE15) -> 1 | AF13: =IF($AD$47=0,0,AD13/$AD$47) -> 0.52657725
A14: Total COGS | B14: ='3a-SalesForecastYear1'!O20 -> 107820 | C14: =+C12*'3a-SalesForecastYear1'!$E$9 -> 19080 | D14: =+D12*'3a-SalesForecastYear1'!$E$9 -> 19652.4 | E14: =+E12*'3a-SalesForecastYear1'!$E$9 -> 20241.972 | F14: =+F12*'3a-SalesForecastYear1'!$E$9 -> 20849.231 | G14: =+G12*'3a-SalesForecastYear1'!$E$9 -> 21474.708 | H14: =+H12*'3a-SalesForecastYear1'!$E$9 -> 22118.949 | I14: =+I12*'3a-SalesForecastYear1'!$E$9 -> 22782.518 | J14: =+J12*'3a-SalesForecastYear1'!$E$9 -> 23465.993 | ... N14: =+N12*'3a-SalesForecastYear1'!$E$9 -> 26411.182 | O14: =SUM(C14:N14) -> 270783.92 | P14: =IF(O13=0,0,O14/O13) -> 0.33333333 | Q14: =IF($O$48=0,0,O14/$O$48) -> 0.5 | R14: =+R12*'3a-SalesForecastYear1'!$E$9 -> 26411.182 | S14: =+S12*'3a-SalesForecastYear1'!$E$9 -> 26939.406 | T14: =+T12*'3a-SalesForecastYear1'!$E$9 -> 27478.194 | U14: =+U12*'3a-SalesForecastYear1'!$E$9 -> 28027.758 | V14: =+V12*'3a-SalesForecastYear1'!$E$9 -> 28588.313 | W14: =+W12*'3a-SalesForecastYear1'!$E$9 -> 29160.079 | X14: =+X12*'3a-SalesForecastYear1'!$E$9 -> 29743.281 | Y14: =+Y12*'3a-SalesForecastYear1'!$E$9 -> 30338.147 | ... AC14: =+AC12*'3a-SalesForecastYear1'!$E$9 -> 32838.985 | AD14: =SUM(R14:AC14) -> 354229.15 | AE14: =IF(AD13=0,0,AD14/AD13) -> 0.33333333 | AF14: =IF($AD$48=0,0,AD14/$AD$48) -> 0.5
A15: Total Margin | B15: ='3a-SalesForecastYear1'!O21 -> 215640 | C15: =C13-C14 -> 38160 | D15: =D13-D14 -> 39304.8 | E15: =E13-E14 -> 40483.944 | F15: =F13-F14 -> 41698.462 | G15: =G13-G14 -> 42949.416 | H15: =H13-H14 -> 44237.899 | I15: =I13-I14 -> 45565.036 | J15: =J13-J14 -> 46931.987 | ... N15: =N13-N14 -> 52822.365 | O15: =SUM(C15:N15) -> 541567.85 | P15: =IF(O13=0,0,O15/O13) -> 0.66666667 | Q15: =IF($O$49=0,0,O15/$O$49) -> 0.54095433 | R15: =R13-R14 -> 52822.365 | S15: =S13-S14 -> 53878.812 | T15: =T13-T14 -> 54956.388 | U15: =U13-U14 -> 56055.516 | V15: =V13-V14 -> 57176.626 | W15: =W13-W14 -> 58320.159 | X15: =X13-X14 -> 59486.562 | Y15: =Y13-Y14 -> 60676.293 | ... AC15: =AC13-AC14 -> 65677.971 | AD15: =SUM(R15:AC15) -> 708458.29 | AE15: =IF(AD13=0,0,AD15/AD13) -> 0.66666667 | AF15: =IF($AD$49=0,0,AD15/$AD$49) -> 0.54095433
A17: ='3a-SalesForecastYear1'!B23 -> Immediate Revenue (70%)
A18: =Unit2&" Sold" -> 1 Sold | B18: =Unit2_Annual -> 599 | C18: ='3a-SalesForecastYear1'!N24 -> 106 | D18: =C18+C18*$C$7 -> 109.18 | E18: =D18+D18*$C$7 -> 112.4554 | F18: =E18+E18*$C$7 -> 115.82906 | G18: =F18+F18*$C$7 -> 119.30393 | H18: =G18+G18*$C$7 -> 122.88305 | I18: =H18+H18*$C$7 -> 126.56954 | J18: =I18+I18*$C$7 -> 130.36663 | K18: =J18+J18*$C$7 -> 134.27763 | ... N18: =M18+M18*$C$7 -> 146.72879 | O18: =SUM(C18:N18) -> 1504.3551 | Q18: =IF($O$46=0,0,O18/$O$46) -> 0.31641791 | R18: =N18 -> 146.72879 | S18: =R18+R18*$C$8 -> 149.66337 | T18: =S18+S18*$C$8 -> 152.65663 | U18: =T18+T18*$C$8 -> 155.70977 | V18: =U18+U18*$C$8 -> 158.82396 | W18: =V18+V18*$C$8 -> 162.00044 | X18: =W18+W18*$C$8 -> 165.24045 | Y18: =X18+X18*$C$8 -> 168.54526 | Z18: =Y18+Y18*$C$8 -> 171.91616 | ... AC18: =AB18+AB18*$C$8 -> 182.43881 | AD18: =SUM(R18:AC18) -> 1967.9397 | AF18: =IF($AD$46=0,0,AD18/$AD$46) -> 0.31641791
A19: Total Sales | B19: =Category2_Annual_Sales -> 226422 | C19: =+C18*'3a-SalesForecastYear1'!$D$10 -> 40068 | D19: =+D18*'3a-SalesForecastYear1'!$D$10 -> 41270.04 | E19: =+E18*'3a-SalesForecastYear1'!$D$10 -> 42508.141 | F19: =+F18*'3a-SalesForecastYear1'!$D$10 -> 43783.385 | G19: =+G18*'3a-SalesForecastYear1'!$D$10 -> 45096.887 | H19: =+H18*'3a-SalesForecastYear1'!$D$10 -> 46449.794 | I19: =+I18*'3a-SalesForecastYear1'!$D$10 -> 47843.287 | J19: =+J18*'3a-SalesForecastYear1'!$D$10 -> 49278.586 | ... N19: =+N18*'3a-SalesForecastYear1'!$D$10 -> 55463.483 | O19: =SUM(C19:N19) -> 568646.24 | P19: =(P20+P21) -> 1 | Q19: =IF($O$47=0,0,O19/$O$47) -> 0.36860407 | R19: =+R18*'3a-SalesForecastYear1'!$D$10 -> 55463.483 | S19: =+S18*'3a-SalesForecastYear1'!$D$10 -> 56572.752 | T19: =+T18*'3a-SalesForecastYear1'!$D$10 -> 57704.207 | U19: =+U18*'3a-SalesForecastYear1'!$D$10 -> 58858.292 | V19: =+V18*'3a-SalesForecastYear1'!$D$10 -> 60035.457 | W19: =+W18*'3a-SalesForecastYear1'!$D$10 -> 61236.167 | X19: =+X18*'3a-SalesForecastYear1'!$D$10 -> 62460.89 | Y19: =+Y18*'3a-SalesForecastYear1'!$D$10 -> 63710.108 | ... AC19: =+AC18*'3a-SalesForecastYear1'!$D$10 -> 68961.869 | AD19: =SUM(R19:AC19) -> 743881.21 | AE19: =(AE20+AE21) -> 1 | AF19: =IF($AD$47=0,0,AD19/$AD$47) -> 0.36860407
A20: Total COGS | B20: ='3a-SalesForecastYear1'!O26 -> 107820 | C20: =+C18*'3a-SalesForecastYear1'!$E$10 -> 19080 | D20: =+D18*'3a-SalesForecastYear1'!$E$10 -> 19652.4 | E20: =+E18*'3a-SalesForecastYear1'!$E$10 -> 20241.972 | F20: =+F18*'3a-SalesForecastYear1'!$E$10 -> 20849.231 | G20: =+G18*'3a-SalesForecastYear1'!$E$10 -> 21474.708 | H20: =+H18*'3a-SalesForecastYear1'!$E$10 -> 22118.949 | I20: =+I18*'3a-SalesForecastYear1'!$E$10 -> 22782.518 | J20: =+J18*'3a-SalesForecastYear1'!$E$10 -> 23465.993 | ... N20: =+N18*'3a-SalesForecastYear1'!$E$10 -> 26411.182 | O20: =SUM(C20:N20) -> 270783.92 | P20: =IF(O19=0,0,O20/O19) -> 0.47619048 | Q20: =IF($O$48=0,0,O20/$O$48) -> 0.5 | R20: =+R18*'3a-SalesForecastYear1'!$E$10 -> 26411.182 | S20: =+S18*'3a-SalesForecastYear1'!$E$10 -> 26939.406 | T20: =+T18*'3a-SalesForecastYear1'!$E$10 -> 27478.194 | U20: =+U18*'3a-SalesForecastYear1'!$E$10 -> 28027.758 | V20: =+V18*'3a-SalesForecastYear1'!$E$10 -> 28588.313 | W20: =+W18*'3a-SalesForecastYear1'!$E$10 -> 29160.079 | X20: =+X18*'3a-SalesForecastYear1'!$E$10 -> 29743.281 | Y20: =+Y18*'3a-SalesForecastYear1'!$E$10 -> 30338.147 | ... AC20: =+AC18*'3a-SalesForecastYear1'!$E$10 -> 32838.985 | AD20: =SUM(R20:AC20) -> 354229.15 | AE20: =IF(AD19=0,0,AD20/AD19) -> 0.47619048 | AF20: =IF($AD$48=0,0,AD20/$AD$48) -> 0.5
A21: Margin | B21: ='3a-SalesForecastYear1'!O27 -> 118602 | C21: =C19-C20 -> 20988 | D21: =D19-D20 -> 21617.64 | E21: =E19-E20 -> 22266.169 | F21: =F19-F20 -> 22934.154 | G21: =G19-G20 -> 23622.179 | H21: =H19-H20 -> 24330.844 | I21: =I19-I20 -> 25060.77 | J21: =J19-J20 -> 25812.593 | ... N21: =N19-N20 -> 29052.3 | O21: =SUM(C21:N21) -> 297862.32 | P21: =IF(O19=0,0,O21/O19) -> 0.52380952 | Q21: =IF($O$49=0,0,O21/$O$49) -> 0.29752488 | R21: =R19-R20 -> 29052.3 | S21: =S19-S20 -> 29633.346 | T21: =T19-T20 -> 30226.013 | U21: =U19-U20 -> 30830.534 | V21: =V19-V20 -> 31447.144 | W21: =W19-W20 -> 32076.087 | X21: =X19-X20 -> 32717.609 | Y21: =Y19-Y20 -> 33371.961 | ... AC21: =AC19-AC20 -> 36122.884 | AD21: =SUM(R21:AC21) -> 389652.06 | AE21: =IF(AD19=0,0,AD21/AD19) -> 0.52380952 | AF21: =IF($AD$49=0,0,AD21/$AD$49) -> 0.29752488
A23: ='3a-SalesForecastYear1'!B29 -> Deferred Revenue - 1 Month (20%)
A24: =Unit3&" Sold" -> 1 Sold | B24: =Unit3_Annual -> 493 | C24: ='3a-SalesForecastYear1'!N30 -> 88 | D24: =C24+C24*$C$7 -> 90.64 | E24: =D24+D24*$C$7 -> 93.3592 | F24: =E24+E24*$C$7 -> 96.159976 | G24: =F24+F24*$C$7 -> 99.044775 | H24: =G24+G24*$C$7 -> 102.01612 | I24: =H24+H24*$C$7 -> 105.0766 | J24: =I24+I24*$C$7 -> 108.2289 | K24: =J24+J24*$C$7 -> 111.47577 | ... N24: =M24+M24*$C$7 -> 121.81258 | O24: =SUM(C24:N24) -> 1248.8986 | Q24: =IF($O$46=0,0,O24/$O$46) -> 0.26268657 | R24: =N24 -> 121.81258 | S24: =R24+R24*$C$8 -> 124.24883 | T24: =S24+S24*$C$8 -> 126.73381 | U24: =T24+T24*$C$8 -> 129.26849 | V24: =U24+U24*$C$8 -> 131.85385 | W24: =V24+V24*$C$8 -> 134.49093 | X24: =W24+W24*$C$8 -> 137.18075 | Y24: =X24+X24*$C$8 -> 139.92437 | Z24: =Y24+Y24*$C$8 -> 142.72285 | ... AC24: =AB24+AB24*$C$8 -> 151.45863 | AD24: =SUM(R24:AC24) -> 1633.7613 | AF24: =IF($AD$46=0,0,AD24/$AD$46) -> 0.26268657
A25: Total Sales | B25: =Category3_Annual_Sales -> 53244 | C25: =+C24*'3a-SalesForecastYear1'!$D$11 -> 9504 | D25: =+D24*'3a-SalesForecastYear1'!$D$11 -> 9789.12 | E25: =+E24*'3a-SalesForecastYear1'!$D$11 -> 10082.794 | F25: =+F24*'3a-SalesForecastYear1'!$D$11 -> 10385.277 | G25: =+G24*'3a-SalesForecastYear1'!$D$11 -> 10696.836 | H25: =+H24*'3a-SalesForecastYear1'!$D$11 -> 11017.741 | I25: =+I24*'3a-SalesForecastYear1'!$D$11 -> 11348.273 | J25: =+J24*'3a-SalesForecastYear1'!$D$11 -> 11688.721 | ... N25: =+N24*'3a-SalesForecastYear1'!$D$11 -> 13155.759 | O25: =SUM(C25:N25) -> 134881.05 | P25: =(P26+P27) -> 1 | Q25: =IF($O$47=0,0,O25/$O$47) -> 0.087431694 | R25: =+R24*'3a-SalesForecastYear1'!$D$11 -> 13155.759 | S25: =+S24*'3a-SalesForecastYear1'!$D$11 -> 13418.874 | T25: =+T24*'3a-SalesForecastYear1'!$D$11 -> 13687.251 | U25: =+U24*'3a-SalesForecastYear1'!$D$11 -> 13960.996 | V25: =+V24*'3a-SalesForecastYear1'!$D$11 -> 14240.216 | W25: =+W24*'3a-SalesForecastYear1'!$D$11 -> 14525.021 | X25: =+X24*'3a-SalesForecastYear1'!$D$11 -> 14815.521 | Y25: =+Y24*'3a-SalesForecastYear1'!$D$11 -> 15111.831 | ... AC25: =+AC24*'3a-SalesForecastYear1'!$D$11 -> 16357.532 | AD25: =SUM(R25:AC25) -> 176446.22 | AE25: =(AE26+AE27) -> 1 | AF25: =IF($AD$47=0,0,AD25/$AD$47) -> 0.087431694
A26: Total COGS | B26: ='3a-SalesForecastYear1'!O32 -> 0 | C26: =+C24*'3a-SalesForecastYear1'!$E$11 -> 0 | D26: =+D24*'3a-SalesForecastYear1'!$E$11 -> 0 | E26: =+E24*'3a-SalesForecastYear1'!$E$11 -> 0 | F26: =+F24*'3a-SalesForecastYear1'!$E$11 -> 0 | G26: =+G24*'3a-SalesForecastYear1'!$E$11 -> 0 | H26: =+H24*'3a-SalesForecastYear1'!$E$11 -> 0 | I26: =+I24*'3a-SalesForecastYear1'!$E$11 -> 0 | J26: =+J24*'3a-SalesForecastYear1'!$E$11 -> 0 | ... N26: =+N24*'3a-SalesForecastYear1'!$E$11 -> 0 | O26: =SUM(C26:N26) -> 0 | P26: =IF(O25=0,0,O26/O25) -> 0 | Q26: =IF($O$48=0,0,O26/$O$48) -> 0 | R26: =+R24*'3a-SalesForecastYear1'!$E$11 -> 0 | S26: =+S24*'3a-SalesForecastYear1'!$E$11 -> 0 | T26: =+T24*'3a-SalesForecastYear1'!$E$11 -> 0 | U26: =+U24*'3a-SalesForecastYear1'!$E$11 -> 0 | V26: =+V24*'3a-SalesForecastYear1'!$E$11 -> 0 | W26: =+W24*'3a-SalesForecastYear1'!$E$11 -> 0 | X26: =+X24*'3a-SalesForecastYear1'!$E$11 -> 0 | Y26: =+Y24*'3a-SalesForecastYear1'!$E$11 -> 0 | ... AC26: =+AC24*'3a-SalesForecastYear1'!$E$11 -> 0 | AD26: =SUM(R26:AC26) -> 0 | AE26: =IF(AD25=0,0,AD26/AD25) -> 0 | AF26: =IF($AD$48=0,0,AD26/$AD$48) -> 0
A27: Margin | B27: ='3a-SalesForecastYear1'!O33 -> 53244 | C27: =C25-C26 -> 9504 | D27: =D25-D26 -> 9789.12 | E27: =E25-E26 -> 10082.794 | F27: =F25-F26 -> 10385.277 | G27: =G25-G26 -> 10696.836 | H27: =H25-H26 -> 11017.741 | I27: =I25-I26 -> 11348.273 | J27: =J25-J26 -> 11688.721 | ... N27: =N25-N26 -> 13155.759 | O27: =SUM(C27:N27) -> 134881.05 | P27: =IF(O25=0,0,O27/O25) -> 1 | Q27: =IF($O$49=0,0,O27/$O$49) -> 0.13472825 | R27: =R25-R26 -> 13155.759 | S27: =S25-S26 -> 13418.874 | T27: =T25-T26 -> 13687.251 | U27: =U25-U26 -> 13960.996 | V27: =V25-V26 -> 14240.216 | W27: =W25-W26 -> 14525.021 | X27: =X25-X26 -> 14815.521 | Y27: =Y25-Y26 -> 15111.831 | ... AC27: =AC25-AC26 -> 16357.532 | AD27: =SUM(R27:AC27) -> 176446.22 | AE27: =IF(AD25=0,0,AD27/AD25) -> 1 | AF27: =IF($AD$49=0,0,AD27/$AD$49) -> 0.13472825
A29: ='3a-SalesForecastYear1'!B35 -> Deferred Revenue - 6 Months (10%)
A30: =Unit4&" Sold" -> 1 Sold | B30: =Unit4_Annual -> 159 | C30: ='3a-SalesForecastYear1'!N36 -> 35 | D30: =C30+C30*$C$7 -> 36.05 | E30: =D30+D30*$C$7 -> 37.1315 | F30: =E30+E30*$C$7 -> 38.245445 | G30: =F30+F30*$C$7 -> 39.392808 | H30: =G30+G30*$C$7 -> 40.574593 | I30: =H30+H30*$C$7 -> 41.79183 | J30: =I30+I30*$C$7 -> 43.045585 | K30: =J30+J30*$C$7 -> 44.336953 | ... N30: =M30+M30*$C$7 -> 48.448185 | O30: =SUM(C30:N30) -> 496.72103 | Q30: =IF($O$46=0,0,O30/$O$46) -> 0.10447761 | R30: =N30 -> 48.448185 | S30: =R30+R30*$C$8 -> 49.417149 | T30: =S30+S30*$C$8 -> 50.405492 | U30: =T30+T30*$C$8 -> 51.413602 | V30: =U30+U30*$C$8 -> 52.441874 | W30: =V30+V30*$C$8 -> 53.490712 | X30: =W30+W30*$C$8 -> 54.560526 | Y30: =X30+X30*$C$8 -> 55.651736 | Z30: =Y30+Y30*$C$8 -> 56.764771 | ... AC30: =AB30+AB30*$C$8 -> 60.239229 | AD30: =SUM(R30:AC30) -> 649.79141 | AF30: =IF($AD$46=0,0,AD30/$AD$46) -> 0.10447761
A31: Total Sales | B31: =Category4_Annual_Sales -> 8586 | C31: =+C30*'3a-SalesForecastYear1'!$D$12 -> 1890 | D31: =+D30*'3a-SalesForecastYear1'!$D$12 -> 1946.7 | E31: =+E30*'3a-SalesForecastYear1'!$D$12 -> 2005.101 | F31: =+F30*'3a-SalesForecastYear1'!$D$12 -> 2065.254 | G31: =+G30*'3a-SalesForecastYear1'!$D$12 -> 2127.2117 | H31: =+H30*'3a-SalesForecastYear1'!$D$12 -> 2191.028 | I31: =+I30*'3a-SalesForecastYear1'!$D$12 -> 2256.7588 | J31: =+J30*'3a-SalesForecastYear1'!$D$12 -> 2324.4616 | ... N31: =+N30*'3a-SalesForecastYear1'!$D$12 -> 2616.202 | O31: =SUM(C31:N31) -> 26822.936 | P31: =(P32+P33) -> 1 | Q31: =IF($O$47=0,0,O31/$O$47) -> 0.017386985 | R31: =+R30*'3a-SalesForecastYear1'!$D$12 -> 2616.202 | S31: =+S30*'3a-SalesForecastYear1'!$D$12 -> 2668.5261 | T31: =+T30*'3a-SalesForecastYear1'!$D$12 -> 2721.8966 | U31: =+U30*'3a-SalesForecastYear1'!$D$12 -> 2776.3345 | V31: =+V30*'3a-SalesForecastYear1'!$D$12 -> 2831.8612 | W31: =+W30*'3a-SalesForecastYear1'!$D$12 -> 2888.4984 | X31: =+X30*'3a-SalesForecastYear1'!$D$12 -> 2946.2684 | Y31: =+Y30*'3a-SalesForecastYear1'!$D$12 -> 3005.1938 | ... AC31: =+AC30*'3a-SalesForecastYear1'!$D$12 -> 3252.9184 | AD31: =SUM(R31:AC31) -> 35088.736 | AE31: =(AE32+AE33) -> 1 | AF31: =IF($AD$47=0,0,AD31/$AD$47) -> 0.017386985
A32: Total COGS | B32: ='3a-SalesForecastYear1'!O38 -> 0 | C32: =+C30*'3a-SalesForecastYear1'!$E$12 -> 0 | D32: =+D30*'3a-SalesForecastYear1'!$E$12 -> 0 | E32: =+E30*'3a-SalesForecastYear1'!$E$12 -> 0 | F32: =+F30*'3a-SalesForecastYear1'!$E$12 -> 0 | G32: =+G30*'3a-SalesForecastYear1'!$E$12 -> 0 | H32: =+H30*'3a-SalesForecastYear1'!$E$12 -> 0 | I32: =+I30*'3a-SalesForecastYear1'!$E$12 -> 0 | J32: =+J30*'3a-SalesForecastYear1'!$E$12 -> 0 | ... N32: =+N30*'3a-SalesForecastYear1'!$E$12 -> 0 | O32: =SUM(C32:N32) -> 0 | P32: =IF(O31=0,0,O32/O31) -> 0 | Q32: =IF($O$48=0,0,O32/$O$48) -> 0 | R32: =+R30*'3a-SalesForecastYear1'!$E$12 -> 0 | S32: =+S30*'3a-SalesForecastYear1'!$E$12 -> 0 | T32: =+T30*'3a-SalesForecastYear1'!$E$12 -> 0 | U32: =+U30*'3a-SalesForecastYear1'!$E$12 -> 0 | V32: =+V30*'3a-SalesForecastYear1'!$E$12 -> 0 | W32: =+W30*'3a-SalesForecastYear1'!$E$12 -> 0 | X32: =+X30*'3a-SalesForecastYear1'!$E$12 -> 0 | Y32: =+Y30*'3a-SalesForecastYear1'!$E$12 -> 0 | ... AC32: =+AC30*'3a-SalesForecastYear1'!$E$12 -> 0 | AD32: =SUM(R32:AC32) -> 0 | AE32: =IF(AD31=0,0,AD32/AD31) -> 0 | AF32: =IF($AD$48=0,0,AD32/$AD$48) -> 0
A33: Margin | B33: ='3a-SalesForecastYear1'!O39 -> 8586 | C33: =C31-C32 -> 1890 | D33: =D31-D32 -> 1946.7 | E33: =E31-E32 -> 2005.101 | F33: =F31-F32 -> 2065.254 | G33: =G31-G32 -> 2127.2117 | H33: =H31-H32 -> 2191.028 | I33: =I31-I32 -> 2256.7588 | J33: =J31-J32 -> 2324.4616 | ... N33: =N31-N32 -> 2616.202 | O33: =SUM(C33:N33) -> 26822.936 | P33: =IF(O31=0,0,O33/O31) -> 1 | Q33: =IF($O$49=0,0,O33/$O$49) -> 0.026792549 | R33: =R31-R32 -> 2616.202 | S33: =S31-S32 -> 2668.5261 | T33: =T31-T32 -> 2721.8966 | U33: =U31-U32 -> 2776.3345 | V33: =V31-V32 -> 2831.8612 | W33: =W31-W32 -> 2888.4984 | X33: =X31-X32 -> 2946.2684 | Y33: =Y31-Y32 -> 3005.1938 | ... AC33: =AC31-AC32 -> 3252.9184 | AD33: =SUM(R33:AC33) -> 35088.736 | AE33: =IF(AD31=0,0,AD33/AD31) -> 1 | AF33: =IF($AD$49=0,0,AD33/$AD$49) -> 0.026792549
A35: ='3a-SalesForecastYear1'!B41 -> Product 5
A36: =Unit5&" Sold" -> Sold | B36: =Unit5_Annual -> 0 | C36: ='3a-SalesForecastYear1'!N42 -> 0 | D36: =C36+C36*$C$7 -> 0 | E36: =D36+D36*$C$7 -> 0 | F36: =E36+E36*$C$7 -> 0 | G36: =F36+F36*$C$7 -> 0 | H36: =G36+G36*$C$7 -> 0 | I36: =H36+H36*$C$7 -> 0 | J36: =I36+I36*$C$7 -> 0 | K36: =J36+J36*$C$7 -> 0 | ... N36: =M36+M36*$C$7 -> 0 | O36: =SUM(C36:N36) -> 0 | Q36: =IF($O$46=0,0,O36/$O$46) -> 0 | R36: =N36 -> 0 | S36: =R36+R36*$C$8 -> 0 | T36: =S36+S36*$C$8 -> 0 | U36: =T36+T36*$C$8 -> 0 | V36: =U36+U36*$C$8 -> 0 | W36: =V36+V36*$C$8 -> 0 | X36: =W36+W36*$C$8 -> 0 | Y36: =X36+X36*$C$8 -> 0 | Z36: =Y36+Y36*$C$8 -> 0 | ... AC36: =AB36+AB36*$C$8 -> 0 | AD36: =SUM(R36:AC36) -> 0 | AF36: =IF($AD$46=0,0,AD36/$AD$46) -> 0
A37: Total Sales | B37: =Category5_Annual_Sales -> 0 | C37: =+C36*'3a-SalesForecastYear1'!$D$13 -> 0 | D37: =+D36*'3a-SalesForecastYear1'!$D$13 -> 0 | E37: =+E36*'3a-SalesForecastYear1'!$D$13 -> 0 | F37: =+F36*'3a-SalesForecastYear1'!$D$13 -> 0 | G37: =+G36*'3a-SalesForecastYear1'!$D$13 -> 0 | H37: =+H36*'3a-SalesForecastYear1'!$D$13 -> 0 | I37: =+I36*'3a-SalesForecastYear1'!$D$13 -> 0 | J37: =+J36*'3a-SalesForecastYear1'!$D$13 -> 0 | ... N37: =+N36*'3a-SalesForecastYear1'!$D$13 -> 0 | O37: =SUM(C37:N37) -> 0 | P37: =(P38+P39) -> 0 | Q37: =IF($O$47=0,0,O37/$O$47) -> 0 | R37: =+R36*'3a-SalesForecastYear1'!$D$13 -> 0 | S37: =+S36*'3a-SalesForecastYear1'!$D$13 -> 0 | T37: =+T36*'3a-SalesForecastYear1'!$D$13 -> 0 | U37: =+U36*'3a-SalesForecastYear1'!$D$13 -> 0 | V37: =+V36*'3a-SalesForecastYear1'!$D$13 -> 0 | W37: =+W36*'3a-SalesForecastYear1'!$D$13 -> 0 | X37: =+X36*'3a-SalesForecastYear1'!$D$13 -> 0 | Y37: =+Y36*'3a-SalesForecastYear1'!$D$13 -> 0 | ... AC37: =+AC36*'3a-SalesForecastYear1'!$D$13 -> 0 | AD37: =SUM(R37:AC37) -> 0 | AE37: =(AE38+AE39) -> 0 | AF37: =IF($AD$47=0,0,AD37/$AD$47) -> 0
A38: Total COGS | B38: ='3a-SalesForecastYear1'!O44 -> 0 | C38: =+C36*'3a-SalesForecastYear1'!$E$13 -> 0 | D38: =+D36*'3a-SalesForecastYear1'!$E$13 -> 0 | E38: =+E36*'3a-SalesForecastYear1'!$E$13 -> 0 | F38: =+F36*'3a-SalesForecastYear1'!$E$13 -> 0 | G38: =+G36*'3a-SalesForecastYear1'!$E$13 -> 0 | H38: =+H36*'3a-SalesForecastYear1'!$E$13 -> 0 | I38: =+I36*'3a-SalesForecastYear1'!$E$13 -> 0 | J38: =+J36*'3a-SalesForecastYear1'!$E$13 -> 0 | ... N38: =+N36*'3a-SalesForecastYear1'!$E$13 -> 0 | O38: =SUM(C38:N38) -> 0 | P38: =IF(O37=0,0,O38/O37) -> 0 | Q38: =IF($O$48=0,0,O38/$O$48) -> 0 | R38: =+R36*'3a-SalesForecastYear1'!$E$13 -> 0 | S38: =+S36*'3a-SalesForecastYear1'!$E$13 -> 0 | T38: =+T36*'3a-SalesForecastYear1'!$E$13 -> 0 | U38: =+U36*'3a-SalesForecastYear1'!$E$13 -> 0 | V38: =+V36*'3a-SalesForecastYear1'!$E$13 -> 0 | W38: =+W36*'3a-SalesForecastYear1'!$E$13 -> 0 | X38: =+X36*'3a-SalesForecastYear1'!$E$13 -> 0 | Y38: =+Y36*'3a-SalesForecastYear1'!$E$13 -> 0 | ... AC38: =+AC36*'3a-SalesForecastYear1'!$E$13 -> 0 | AD38: =SUM(R38:AC38) -> 0 | AE38: =IF(AD37=0,0,AD38/AD37) -> 0 | AF38: =IF($AD$48=0,0,AD38/$AD$48) -> 0
A39: Margin | B39: ='3a-SalesForecastYear1'!O45 -> 0 | C39: =C37-C38 -> 0 | D39: =D37-D38 -> 0 | E39: =E37-E38 -> 0 | F39: =F37-F38 -> 0 | G39: =G37-G38 -> 0 | H39: =H37-H38 -> 0 | I39: =I37-I38 -> 0 | J39: =J37-J38 -> 0 | ... N39: =N37-N38 -> 0 | O39: =SUM(C39:N39) -> 0 | P39: =IF(O37=0,0,O39/O37) -> 0 | Q39: =IF($O$49=0,0,O39/$O$49) -> 0 | R39: =R37-R38 -> 0 | S39: =S37-S38 -> 0 | T39: =T37-T38 -> 0 | U39: =U37-U38 -> 0 | V39: =V37-V38 -> 0 | W39: =W37-W38 -> 0 | X39: =X37-X38 -> 0 | Y39: =Y37-Y38 -> 0 | ... AC39: =AC37-AC38 -> 0 | AD39: =SUM(R39:AC39) -> 0 | AE39: =IF(AD37=0,0,AD39/AD37) -> 0 | AF39: =IF($AD$49=0,0,AD39/$AD$49) -> 0
A41: ='3a-SalesForecastYear1'!B47 -> Product 6
A42: =Unit6&" Sold" -> Sold | B42: =Unit6_Annual -> 0 | C42: ='3a-SalesForecastYear1'!N48 -> 0 | D42: =C42+C42*$C$7 -> 0 | E42: =D42+D42*$C$7 -> 0 | F42: =E42+E42*$C$7 -> 0 | G42: =F42+F42*$C$7 -> 0 | H42: =G42+G42*$C$7 -> 0 | I42: =H42+H42*$C$7 -> 0 | J42: =I42+I42*$C$7 -> 0 | K42: =J42+J42*$C$7 -> 0 | ... N42: =M42+M42*$C$7 -> 0 | O42: =SUM(C42:N42) -> 0 | Q42: =IF($O$46=0,0,O42/$O$46) -> 0 | R42: =N42 -> 0 | S42: =R42+R42*$C$8 -> 0 | T42: =S42+S42*$C$8 -> 0 | U42: =T42+T42*$C$8 -> 0 | V42: =U42+U42*$C$8 -> 0 | W42: =V42+V42*$C$8 -> 0 | X42: =W42+W42*$C$8 -> 0 | Y42: =X42+X42*$C$8 -> 0 | Z42: =Y42+Y42*$C$8 -> 0 | ... AC42: =AB42+AB42*$C$8 -> 0 | AD42: =SUM(R42:AC42) -> 0 | AF42: =IF($AD$46=0,0,AD42/$AD$46) -> 0
A43: Total Sales | B43: =Category6_Annual_Sales -> 0 | C43: =+C42*'3a-SalesForecastYear1'!$D$14 -> 0 | D43: =+D42*'3a-SalesForecastYear1'!$D$14 -> 0 | E43: =+E42*'3a-SalesForecastYear1'!$D$14 -> 0 | F43: =+F42*'3a-SalesForecastYear1'!$D$14 -> 0 | G43: =+G42*'3a-SalesForecastYear1'!$D$14 -> 0 | H43: =+H42*'3a-SalesForecastYear1'!$D$14 -> 0 | I43: =+I42*'3a-SalesForecastYear1'!$D$14 -> 0 | J43: =+J42*'3a-SalesForecastYear1'!$D$14 -> 0 | ... N43: =+N42*'3a-SalesForecastYear1'!$D$14 -> 0 | O43: =SUM(C43:N43) -> 0 | P43: =(P44+P45) -> 0 | Q43: =IF($O$47=0,0,O43/$O$47) -> 0 | R43: =+R42*'3a-SalesForecastYear1'!$D$14 -> 0 | S43: =+S42*'3a-SalesForecastYear1'!$D$14 -> 0 | T43: =+T42*'3a-SalesForecastYear1'!$D$14 -> 0 | U43: =+U42*'3a-SalesForecastYear1'!$D$14 -> 0 | V43: =+V42*'3a-SalesForecastYear1'!$D$14 -> 0 | W43: =+W42*'3a-SalesForecastYear1'!$D$14 -> 0 | X43: =+X42*'3a-SalesForecastYear1'!$D$14 -> 0 | Y43: =+Y42*'3a-SalesForecastYear1'!$D$14 -> 0 | ... AC43: =+AC42*'3a-SalesForecastYear1'!$D$14 -> 0 | AD43: =SUM(R43:AC43) -> 0 | AE43: =(AE44+AE45) -> 0 | AF43: =IF($AD$47=0,0,AD43/$AD$47) -> 0
A44: Total COGS | B44: ='3a-SalesForecastYear1'!O50 -> 0 | C44: =+C42*'3a-SalesForecastYear1'!$E$14 -> 0 | D44: =+D42*'3a-SalesForecastYear1'!$E$14 -> 0 | E44: =+E42*'3a-SalesForecastYear1'!$E$14 -> 0 | F44: =+F42*'3a-SalesForecastYear1'!$E$14 -> 0 | G44: =+G42*'3a-SalesForecastYear1'!$E$14 -> 0 | H44: =+H42*'3a-SalesForecastYear1'!$E$14 -> 0 | I44: =+I42*'3a-SalesForecastYear1'!$E$14 -> 0 | J44: =+J42*'3a-SalesForecastYear1'!$E$14 -> 0 | ... N44: =+N42*'3a-SalesForecastYear1'!$E$14 -> 0 | O44: =SUM(C44:N44) -> 0 | P44: =IF(O43=0,0,O44/O43) -> 0 | Q44: =IF($O$48=0,0,O44/$O$48) -> 0 | R44: =+R42*'3a-SalesForecastYear1'!$E$14 -> 0 | S44: =+S42*'3a-SalesForecastYear1'!$E$14 -> 0 | T44: =+T42*'3a-SalesForecastYear1'!$E$14 -> 0 | U44: =+U42*'3a-SalesForecastYear1'!$E$14 -> 0 | V44: =+V42*'3a-SalesForecastYear1'!$E$14 -> 0 | W44: =+W42*'3a-SalesForecastYear1'!$E$14 -> 0 | X44: =+X42*'3a-SalesForecastYear1'!$E$14 -> 0 | Y44: =+Y42*'3a-SalesForecastYear1'!$E$14 -> 0 | ... AC44: =+AC42*'3a-SalesForecastYear1'!$E$14 -> 0 | AD44: =SUM(R44:AC44) -> 0 | AE44: =IF(AD43=0,0,AD44/AD43) -> 0 | AF44: =IF($AD$48=0,0,AD44/$AD$48) -> 0
A45: Margin | B45: ='3a-SalesForecastYear1'!O51 -> 0 | C45: =C43-C44 -> 0 | D45: =D43-D44 -> 0 | E45: =E43-E44 -> 0 | F45: =F43-F44 -> 0 | G45: =G43-G44 -> 0 | H45: =H43-H44 -> 0 | I45: =I43-I44 -> 0 | J45: =J43-J44 -> 0 | ... N45: =N43-N44 -> 0 | O45: =SUM(C45:N45) -> 0 | P45: =IF(O43=0,0,O45/O43) -> 0 | Q45: =IF($O$49=0,0,O45/$O$49) -> 0 | R45: =R43-R44 -> 0 | S45: =S43-S44 -> 0 | T45: =T43-T44 -> 0 | U45: =U43-U44 -> 0 | V45: =V43-V44 -> 0 | W45: =W43-W44 -> 0 | X45: =X43-X44 -> 0 | Y45: =Y43-Y44 -> 0 | ... AC45: =AC43-AC44 -> 0 | AD45: =SUM(R45:AC45) -> 0 | AE45: =IF(AD43=0,0,AD45/AD43) -> 0 | AF45: =IF($AD$49=0,0,AD45/$AD$49) -> 0
A46: Total Units Sold | B46: =Units_Annual_Total -> 1850 | C46: =C12+C18+C24+C30+C36+C42 -> 335 | D46: =D12+D18+D24+D30+D36+D42 -> 345.05 | E46: =E12+E18+E24+E30+E36+E42 -> 355.4015 | F46: =F12+F18+F24+F30+F36+F42 -> 366.06354 | G46: =G12+G18+G24+G30+G36+G42 -> 377.04545 | H46: =H12+H18+H24+H30+H36+H42 -> 388.35681 | I46: =I12+I18+I24+I30+I36+I42 -> 400.00752 | J46: =J12+J18+J24+J30+J36+J42 -> 412.00774 | ... N46: =N12+N18+N24+N30+N36+N42 -> 463.71835 | O46: =SUM(C46:N46) -> 4754.3299 | R46: =R12+R18+R24+R30+R36+R42 -> 463.71835 | S46: =S12+S18+S24+S30+S36+S42 -> 472.99271 | T46: =T12+T18+T24+T30+T36+T42 -> 482.45257 | U46: =U12+U18+U24+U30+U36+U42 -> 492.10162 | V46: =V12+V18+V24+V30+V36+V42 -> 501.94365 | W46: =W12+W18+W24+W30+W36+W42 -> 511.98252 | X46: =X12+X18+X24+X30+X36+X42 -> 522.22218 | Y46: =Y12+Y18+Y24+Y30+Y36+Y42 -> 532.66662 | ... AC46: =AC12+AC18+AC24+AC30+AC36+AC42 -> 576.57548 | AD46: =SUM(R46:AC46) -> 6219.4321
A47: Total Sales | B47: =Sales_Annual_Total -> 611712 | C47: =C13+C19+C25+C31+C37+C43 -> 108702 | D47: =D13+D19+D25+D31+D37+D43 -> 111963.06 | E47: =E13+E19+E25+E31+E37+E43 -> 115321.95 | F47: =F13+F19+F25+F31+F37+F43 -> 118781.61 | G47: =G13+G19+G25+G31+G37+G43 -> 122345.06 | H47: =H13+H19+H25+H31+H37+H43 -> 126015.41 | I47: =I13+I19+I25+I31+I37+I43 -> 129795.87 | J47: =J13+J19+J25+J31+J37+J43 -> 133689.75 | ... N47: =N13+N19+N25+N31+N37+N43 -> 150468.99 | O47: =SUM(C47:N47) -> 1542702 | R47: =R13+R19+R25+R31+R37+R43 -> 150468.99 | S47: =S13+S19+S25+S31+S37+S43 -> 153478.37 | T47: =T13+T19+T25+T31+T37+T43 -> 156547.94 | U47: =U13+U19+U25+U31+U37+U43 -> 159678.9 | V47: =V13+V19+V25+V31+V37+V43 -> 162872.47 | W47: =W13+W19+W25+W31+W37+W43 -> 166129.92 | X47: =X13+X19+X25+X31+X37+X43 -> 169452.52 | Y47: =Y13+Y19+Y25+Y31+Y37+Y43 -> 172841.57 | ... AC47: =AC13+AC19+AC25+AC31+AC37+AC43 -> 187089.28 | AD47: =SUM(R47:AC47) -> 2018103.6
A48: Total Cost of Goods Sold | B48: =COGS_Annual_Total -> 215640 | C48: =C14+C20+C26+C32+C38+C44 -> 38160 | D48: =D14+D20+D26+D32+D38+D44 -> 39304.8 | E48: =E14+E20+E26+E32+E38+E44 -> 40483.944 | F48: =F14+F20+F26+F32+F38+F44 -> 41698.462 | G48: =G14+G20+G26+G32+G38+G44 -> 42949.416 | H48: =H14+H20+H26+H32+H38+H44 -> 44237.899 | I48: =I14+I20+I26+I32+I38+I44 -> 45565.036 | J48: =J14+J20+J26+J32+J38+J44 -> 46931.987 | ... N48: =N14+N20+N26+N32+N38+N44 -> 52822.365 | O48: =SUM(C48:N48) -> 541567.85 | R48: =R14+R20+R26+R32+R38+R44 -> 52822.365 | S48: =S14+S20+S26+S32+S38+S44 -> 53878.812 | T48: =T14+T20+T26+T32+T38+T44 -> 54956.388 | U48: =U14+U20+U26+U32+U38+U44 -> 56055.516 | V48: =V14+V20+V26+V32+V38+V44 -> 57176.626 | W48: =W14+W20+W26+W32+W38+W44 -> 58320.159 | X48: =X14+X20+X26+X32+X38+X44 -> 59486.562 | Y48: =Y14+Y20+Y26+Y32+Y38+Y44 -> 60676.293 | ... AC48: =AC14+AC20+AC26+AC32+AC38+AC44 -> 65677.971 | AD48: =SUM(R48:AC48) -> 708458.29
A49: Total Margin | B49: =Margin_Annual_Total -> 396072 | C49: =C47-C48 -> 70542 | D49: =D47-D48 -> 72658.26 | E49: =E47-E48 -> 74838.008 | F49: =F47-F48 -> 77083.148 | G49: =G47-G48 -> 79395.642 | H49: =H47-H48 -> 81777.512 | I49: =I47-I48 -> 84230.837 | J49: =J47-J48 -> 86757.762 | ... N49: =N47-N48 -> 97646.626 | O49: =O15+O21+O27+O33+O39+O45 -> 1001134.1 | R49: =R47-R48 -> 97646.626 | S49: =S47-S48 -> 99599.558 | T49: =T47-T48 -> 101591.55 | U49: =U47-U48 -> 103623.38 | V49: =V47-V48 -> 105695.85 | W49: =W47-W48 -> 107809.76 | X49: =X47-X48 -> 109965.96 | Y49: =Y47-Y48 -> 112165.28 | ... AC49: =AC47-AC48 -> 121411.31 | AD49: =AD15+AD21+AD27+AD33+AD39+AD45 -> 1309645.3

Sheet 4-AdditionalInputs
B2: Additional Inputs
B4: Prepared By: | C4: Company Name:
B5: =IF(ISBLANK(Directions!C10),"Owner",Directions!C10) -> Owner | C5: =IF(ISBLANK(Directions!D10),"Company 1",Directions!D10) -> Company 1
B7: Accounts Receivable (A/R) Days Sales Outstanding
B8: Percent of Collections | C8: Year 1 | D8: Year 2 | E8: Year 3
B9: Paid within 30 days | C9: 1 | D9: 1 | E9: 1
B10: Paid between 30 and 60 days | C10: 0 | D10: 0 | E10: 0
B11: Paid in more than 60 days | C11: 0 | D11: 0 | E11: 0
B12: Allowance for bad debt | C12: =1-SUM(C9:C11) -> 0 | D12: =1-SUM(D9:D11) -> 0 | E12: =1-SUM(E9:E11) -> 0
B13: This should equal 100% ----> | C13: =SUM(C9:C12) -> 1 | D13: =SUM(D9:D12) -> 1 | E13: =SUM(E9:E12) -> 1
B15: Accounts Payable (A/P)
B16: Percent of Disbursements | C16: Year 1 | D16: Year 2 | E16: Year 3
B17: Paid within 30 days | C17: 1 | D17: 1 | E17: 1
B18: Paid between 30 and 60 days | C18: 0 | D18: 0 | E18: 0
B19: Paid in more than 60 days | C19: 0 | D19: 0 | E19: 0
B20: This should equal 100% ----> | C20: =SUM(C17:C19) -> 1 | D20: =SUM(D17:D19) -> 1 | E20: =SUM(E17:E19) -> 1
B23: Line of Credit Assumptions
B24: Desired Minimum Cash Balance | D24: 0
B25: Line of Credit Interest Rate | D25: 0.08
B27: Additional Fixed Assets Purchases
B28: Fixed Assets | C28: Depreciation (years) | D28: ='2a-PayrollYear1'!F7 -> Month 1 | E28: ='2a-PayrollYear1'!G7 -> Month 2 | F28: ='2a-PayrollYear1'!H7 -> Month 3 | G28: ='2a-PayrollYear1'!I7 -> Month 4 | H28: ='2a-PayrollYear1'!J7 -> Month 5 | I28: ='2a-PayrollYear1'!K7 -> Month 6 | J28: ='2a-PayrollYear1'!L7 -> Month 7 | K28: ='2a-PayrollYear1'!M7 -> Month 8 | ... O28: ='2a-PayrollYear1'!Q7 -> Month 12 | P28: Year 1 Totals | Q28: Year 2 Total | R28: Year 3 Total
B29: Real Estate | C29: 20 | D29: =Buildings -> 0 | P29: =SUM(D29:O29) -> 0
B30: Leasehold Improvements | C30: 7 | D30: =LeaseImprovements -> 0 | P30: =SUM(D30:O30) -> 0
B31: Equipment | C31: 7 | D31: =Equipment -> 0 | P31: =SUM(D31:O31) -> 0
B32: Furniture and Fixtures | C32: 5 | D32: =Furniture -> 0 | P32: =SUM(D32:O32) -> 0
B33: Vehicles | C33: 5 | D33: =Vehicles -> 0 | P33: =SUM(D33:O33) -> 0
B34: Other Fixed Assets | C34: 5 | D34: =OtherFixedAssets -> 0 | P34: =SUM(D34:O34) -> 0 | Q34: 0 | R34: 0
B35: Total Additional Fixed Assets | D35: =SUM(D29:D34) -> 0 | E35: =SUM(E29:E34) -> 0 | F35: =SUM(F29:F34) -> 0 | G35: =SUM(G29:G34) -> 0 | H35: =SUM(H29:H34) -> 0 | I35: =SUM(I29:I34) -> 0 | J35: =SUM(J29:J34) -> 0 | K35: =SUM(K29:K34) -> 0 | ... R35: =SUM(R29:R34) -> 0
B38: Income Tax Assumptions
B39: Effective Income Tax Rate - Year 1 | C39: 0
B40: Effective Income Tax Rate - Year 2 | C40: 0
B41: Effective Income Tax Rate - Year 3 | C41: 0
B43: Amortization of Start-Up Costs
B44: Amortization Period in Years | C44: 3
B46: Reehash Business Model Parameters
B48: Lead Generation & Conversion
B49: Leads per contractor per day | C49: 10
B50: Show rate (% of scheduled consultations that show) | C50: 0.4
B51: Conversion rate (% of shows that sign) | C51: 0.2
B53: Contract & Fee Structure
B54: Average contract value | C54: 18000
B55: Success fee rate | C55: 0.03
B56: Fee per closed deal | C56: =C54*C55 -> 540
B58: Revenue Recognition Timing
B59: Recognized in month of close | C59: 0.7
B60: Recognized in following month | C60: 0.2
B61: Recognized six months later | C61: 0.1
B63: Variable Costs
B64: Closer commission rate (% of contract value) | C64: 0.01
B65: Closer commission per deal | C65: =C54*C64 -> 180

Sheet 5a-OpExYear1
B2: Operating Expenses Year 1
B4: Prepared By: | C4: Company Name:
B5: =IF(ISBLANK(Directions!C10),"Owner",Directions!C10) -> Owner | C5: =IF(ISBLANK(Directions!D10),"Company 1",Directions!D10) -> Company 1
C8: ='2a-PayrollYear1'!F7 -> Month 1 | D8: ='2a-PayrollYear1'!G7 -> Month 2 | E8: ='2a-PayrollYear1'!H7 -> Month 3 | F8: ='2a-PayrollYear1'!I7 -> Month 4 | G8: ='2a-PayrollYear1'!J7 -> Month 5 | H8: ='2a-PayrollYear1'!K7 -> Month 6 | I8: ='2a-PayrollYear1'!L7 -> Month 7 | J8: ='2a-PayrollYear1'!M7 -> Month 8 | ... N8: ='2a-PayrollYear1'!Q7 -> Month 12 | O8: Annual Totals
B9: Expenses
B10: Advertising | O10: =SUM(C10:N10) -> 0
B11: Car and Truck Expenses | O11: =SUM(C11:N11) -> 0
B12: Closer Commissions (1% of contract value) | C12: 3240 | D12: 3240 | E12: 3240 | F12: 6300 | G12: 6300 | H12: 6300 | I12: 9540 | J12: 9540 | K12: 12600 | L12: 12600 | M12: 15840 | N12: 19080 | O12: =SUM(C12:N12) -> 107820
B13: Contract Labor (Not included in payroll) | O13: =SUM(C13:N13) -> 0
B14: Insurance (other than health) | O14: =SUM(C14:N14) -> 0
B15: Legal and Professional Services (Company Setup) | C15: 2000 | O15: =SUM(C15:N15) -> 2000
B16: Licenses | O16: =SUM(C16:N16) -> 0
B17: Software & Tools (CRM, dialing, calendaring) | C17: 1000 | D17: 1000 | E17: 1000 | F17: 1000 | G17: 1000 | H17: 1000 | I17: 1000 | J17: 1000 | K17: 1000 | L17: 1000 | M17: 1000 | N17: 1000 | O17: =SUM(C17:N17) -> 12000
B18: Rent or Lease -- Vehicles, Machinery, Equipment | O18: =SUM(C18:N18) -> 0
B19: Rent or Lease -- Other Business Property | O19: =SUM(C19:N19) -> 0
B20: Repairs and Maintenance | O20: =SUM(C20:N20) -> 0
B21: Supplies | O21: =SUM(C21:N21) -> 0
B22: Travel, Meals and Entertainment | O22: =SUM(C22:N22) -> 0
B23: Utilities | O23: =SUM(C23:N23) -> 0
B24: Miscellaneous | O24: =SUM(C24:N24) -> 0
B25: Total Expenses | C25: =SUM(C10:C24) -> 6240 | D25: =SUM(D10:D24) -> 4240 | E25: =SUM(E10:E24) -> 4240 | F25: =SUM(F10:F24) -> 7300 | G25: =SUM(G10:G24) -> 7300 | H25: =SUM(H10:H24) -> 7300 | I25: =SUM(I10:I24) -> 10540 | J25: =SUM(J10:J24) -> 10540 | ... N25: =SUM(N10:N24) -> 20080 | O25: =SUM(C25:N25) -> 121820
B27: Other Expenses
B28: Depreciation | C28: ='Amortization&Depreciation'!C119 -> 0 | D28: ='Amortization&Depreciation'!D119 -> 0 | E28: ='Amortization&Depreciation'!E119 -> 0 | F28: ='Amortization&Depreciation'!F119 -> 0 | G28: ='Amortization&Depreciation'!G119 -> 0 | H28: ='Amortization&Depreciation'!H119 -> 0 | I28: ='Amortization&Depreciation'!I119 -> 0 | J28: ='Amortization&Depreciation'!J119 -> 0 | ... N28: ='Amortization&Depreciation'!N119 -> 0 | O28: =SUM(C28:N28) -> 0
B29: Interest
B30: ='1-StartingPoint'!B37 -> Commercial Loan | C30: ='Amortization&Depreciation'!C15 -> 0 | D30: ='Amortization&Depreciation'!D15 -> 0 | E30: ='Amortization&Depreciation'!E15 -> 0 | F30: ='Amortization&Depreciation'!F15 -> 0 | G30: ='Amortization&Depreciation'!G15 -> 0 | H30: ='Amortization&Depreciation'!H15 -> 0 | I30: ='Amortization&Depreciation'!I15 -> 0 | J30: ='Amortization&Depreciation'!J15 -> 0 | ... N30: ='Amortization&Depreciation'!N15 -> 0 | O30: =SUM(C30:N30) -> 0
B31: ='1-StartingPoint'!B38 -> Commercial Mortgage | C31: ='Amortization&Depreciation'!C35 -> 0 | D31: ='Amortization&Depreciation'!D35 -> 0 | E31: ='Amortization&Depreciation'!E35 -> 0 | F31: ='Amortization&Depreciation'!F35 -> 0 | G31: ='Amortization&Depreciation'!G35 -> 0 | H31: ='Amortization&Depreciation'!H35 -> 0 | I31: ='Amortization&Depreciation'!I35 -> 0 | J31: ='Amortization&Depreciation'!J35 -> 0 | ... N31: ='Amortization&Depreciation'!N35 -> 0 | O31: =SUM(C31:N31) -> 0
B32: ='1-StartingPoint'!B39 -> Credit Card Debt | C32: ='Amortization&Depreciation'!C55 -> 0 | D32: ='Amortization&Depreciation'!D55 -> 0 | E32: ='Amortization&Depreciation'!E55 -> 0 | F32: ='Amortization&Depreciation'!F55 -> 0 | G32: ='Amortization&Depreciation'!G55 -> 0 | H32: ='Amortization&Depreciation'!H55 -> 0 | I32: ='Amortization&Depreciation'!I55 -> 0 | J32: ='Amortization&Depreciation'!J55 -> 0 | ... N32: ='Amortization&Depreciation'!N55 -> 0 | O32: =SUM(C32:N32) -> 0
B33: ='1-StartingPoint'!B40 -> Vehicle Loans | C33: ='Amortization&Depreciation'!C75 -> 0 | D33: ='Amortization&Depreciation'!D75 -> 0 | E33: ='Amortization&Depreciation'!E75 -> 0 | F33: ='Amortization&Depreciation'!F75 -> 0 | G33: ='Amortization&Depreciation'!G75 -> 0 | H33: ='Amortization&Depreciation'!H75 -> 0 | I33: ='Amortization&Depreciation'!I75 -> 0 | J33: ='Amortization&Depreciation'!J75 -> 0 | ... N33: ='Amortization&Depreciation'!N75 -> 0 | O33: =SUM(C33:N33) -> 0
B34: ='1-StartingPoint'!B41 -> Other Bank Debt | C34: ='Amortization&Depreciation'!C95 -> 0 | D34: ='Amortization&Depreciation'!D95 -> 0 | E34: ='Amortization&Depreciation'!E95 -> 0 | F34: ='Amortization&Depreciation'!F95 -> 0 | G34: ='Amortization&Depreciation'!G95 -> 0 | H34: ='Amortization&Depreciation'!H95 -> 0 | I34: ='Amortization&Depreciation'!I95 -> 0 | J34: ='Amortization&Depreciation'!J95 -> 0 | ... N34: ='Amortization&Depreciation'!N95 -> 0 | O34: =SUM(C34:N34) -> 0
B35: Line of Credit | C35: ='6a-CashFlowYear1'!C26 -> 0 | D35: ='6a-CashFlowYear1'!D26 -> 0 | E35: ='6a-CashFlowYear1'!E26 -> 0 | F35: ='6a-CashFlowYear1'!F26 -> 0 | G35: ='6a-CashFlowYear1'!G26 -> 0 | H35: ='6a-CashFlowYear1'!H26 -> 0 | I35: ='6a-CashFlowYear1'!I26 -> 0 | J35: ='6a-CashFlowYear1'!J26 -> 0 | ... N35: ='6a-CashFlowYear1'!N26 -> 0 | O35: =SUM(C35:N35) -> 0
B36: Bad Debt Expense | C36: =+'7a-IncomeStatementYear1'!C56 -> 0 | D36: =+'7a-IncomeStatementYear1'!D56 -> 0 | E36: =+'7a-IncomeStatementYear1'!E56 -> 0 | F36: =+'7a-IncomeStatementYear1'!F56 -> 0 | G36: =+'7a-IncomeStatementYear1'!G56 -> 0 | H36: =+'7a-IncomeStatementYear1'!H56 -> 0 | I36: =+'7a-IncomeStatementYear1'!I56 -> 0 | J36: =+'7a-IncomeStatementYear1'!J56 -> 0 | ... N36: =+'7a-IncomeStatementYear1'!N56 -> 0 | O36: =SUM(C36:N36) -> 0
B37: Total Other Expenses | C37: =SUM(C28:C36) -> 0 | D37: =SUM(D28:D36) -> 0 | E37: =SUM(E28:E36) -> 0 | F37: =SUM(F28:F36) -> 0 | G37: =SUM(G28:G36) -> 0 | H37: =SUM(H28:H36) -> 0 | I37: =SUM(I28:I36) -> 0 | J37: =SUM(J28:J36) -> 0 | ... N37: =SUM(N28:N36) -> 0 | O37: =SUM(C37:N37) -> 0
B38: Total Fixed Operating Expenses | C38: =C25+C37 -> 6240 | D38: =D25+D37 -> 4240 | E38: =E25+E37 -> 4240 | F38: =F25+F37 -> 7300 | G38: =G25+G37 -> 7300 | H38: =H25+H37 -> 7300 | I38: =I25+I37 -> 10540 | J38: =J25+J37 -> 10540 | ... N38: =N25+N37 -> 20080 | O38: =SUM(C38:N38) -> 121820

Sheet 5b-OpExYrs1-3
B2: Operating Expenses Years 1-3
B4: Prepared By: | C4: Company Name:
B5: =IF(ISBLANK(Directions!C10),"Owner",Directions!C10) -> Owner | C5: =IF(ISBLANK(Directions!D10),"Company 1",Directions!D10) -> Company 1
B7: Line Item | C7: =IF(Directions!F10>0,Directions!F10,"First Year") -> First Year | D7: Growth Rate 1 to 2 | E7: =IF(Directions!F10>0,Directions!F10+1,"Second Year") -> Second Year | F7: Growth Rate 2 to 3 | G7: =IF(Directions!F10>0,Directions!F10+2,"Third Year") -> Third Year
B8: ='5a-OpExYear1'!B10 -> Advertising | C8: ='5a-OpExYear1'!O10 -> 0 | D8: 0.03 | E8: =C8*(1+D8) -> 0 | F8: 0.03 | G8: =E8*(1+F8) -> 0
B9: ='5a-OpExYear1'!B11 -> Car and Truck Expenses | C9: ='5a-OpExYear1'!O11 -> 0 | D9: 0.03 | E9: =C9*(1+D9) -> 0 | F9: 0.03 | G9: =E9*(1+F9) -> 0
B10: ='5a-OpExYear1'!B12 -> Closer Commissions (1% of contract value) | C10: ='5a-OpExYear1'!O12 -> 107820 | D10: 0.05 | E10: =C10*(1+D10) -> 113211 | F10: 0.05 | G10: =E10*(1+F10) -> 118871.55
B11: ='5a-OpExYear1'!B13 -> Contract Labor (Not included in payroll) | C11: ='5a-OpExYear1'!O13 -> 0 | D11: 0.03 | E11: =C11*(1+D11) -> 0 | F11: 0.03 | G11: =E11*(1+F11) -> 0
B12: ='5a-OpExYear1'!B14 -> Insurance (other than health) | C12: ='5a-OpExYear1'!O14 -> 0 | D12: 0.03 | E12: =C12*(1+D12) -> 0 | F12: 0.03 | G12: =E12*(1+F12) -> 0
B13: ='5a-OpExYear1'!B15 -> Legal and Professional Services (Company Setup) | C13: ='5a-OpExYear1'!O15 -> 2000 | D13: 0.03 | E13: =C13*(1+D13) -> 2060 | F13: 0.03 | G13: =E13*(1+F13) -> 2121.8
B14: ='5a-OpExYear1'!B16 -> Licenses | C14: ='5a-OpExYear1'!O16 -> 0 | D14: 0.05 | E14: =C14*(1+D14) -> 0 | F14: 0.05 | G14: =E14*(1+F14) -> 0
B15: ='5a-OpExYear1'!B17 -> Software & Tools (CRM, dialing, calendaring) | C15: ='5a-OpExYear1'!O17 -> 12000 | D15: 0.03 | E15: =C15*(1+D15) -> 12360 | F15: 0.03 | G15: =E15*(1+F15) -> 12730.8
B16: ='5a-OpExYear1'!B18 -> Rent or Lease -- Vehicles, Machinery, Equipment | C16: ='5a-OpExYear1'!O18 -> 0 | D16: 0.03 | E16: =C16*(1+D16) -> 0 | F16: 0.03 | G16: =E16*(1+F16) -> 0
B17: ='5a-OpExYear1'!B19 -> Rent or Lease -- Other Business Property | C17: ='5a-OpExYear1'!O19 -> 0 | D17: 0.03 | E17: =C17*(1+D17) -> 0 | F17: 0.03 | G17: =E17*(1+F17) -> 0
B18: ='5a-OpExYear1'!B20 -> Repairs and Maintenance | C18: ='5a-OpExYear1'!O20 -> 0 | D18: 0.05 | E18: =C18*(1+D18) -> 0 | F18: 0.05 | G18: =E18*(1+F18) -> 0
B19: ='5a-OpExYear1'!B21 -> Supplies | C19: ='5a-OpExYear1'!O21 -> 0 | D19: 0.03 | E19: =C19*(1+D19) -> 0 | F19: 0.03 | G19: =E19*(1+F19) -> 0
... B22: ='5a-OpExYear1'!B24 -> Miscellaneous | C22: ='5a-OpExYear1'!O24 -> 0 | D22: 0.03 | E22: =C22*(1+D22) -> 0 | F22: 0.03 | G22: =E22*(1+F22) -> 0
B23: Total Expenses | C23: =SUM(C8:C22) -> 121820 | E23: =SUM(E8:E22) -> 127631 | G23: =SUM(G8:G22) -> 133724.15
B25: Other Expenses
B26: Depreciation | C26: ='5a-OpExYear1'!O28 -> 0 | E26: ='Amortization&Depreciation'!O123 -> 0 | G26: ='Amortization&Depreciation'!O127 -> 0
B27: Interest
B28: ='1-StartingPoint'!B37 -> Commercial Loan | C28: ='5a-OpExYear1'!O30 -> 0 | E28: =IF('1-StartingPoint'!$F37<36,0,'Amortization&Depreciation'!O19) -> 0 | G28: =IF('1-StartingPoint'!$F37<36,0,'Amortization&Depreciation'!O23) -> 0
B29: ='1-StartingPoint'!B38 -> Commercial Mortgage | C29: ='5a-OpExYear1'!O31 -> 0 | E29: =IF('1-StartingPoint'!$F38<36,0,'Amortization&Depreciation'!O39) -> 0 | G29: =IF('1-StartingPoint'!$F38<36,0,'Amortization&Depreciation'!O43) -> 0
B30: ='1-StartingPoint'!B39 -> Credit Card Debt | C30: ='5a-OpExYear1'!O32 -> 0 | E30: =IF('1-StartingPoint'!$F39<36,0,'Amortization&Depreciation'!O59) -> 0 | G30: =IF('1-StartingPoint'!$F39<36,0,'Amortization&Depreciation'!O63) -> 0
B31: ='1-StartingPoint'!B40 -> Vehicle Loans | C31: ='5a-OpExYear1'!O33 -> 0 | E31: =IF('1-StartingPoint'!$F40<36,0,'Amortization&Depreciation'!O79) -> 0 | G31: =IF('1-StartingPoint'!$F40<36,0,'Amortization&Depreciation'!O83) -> 0
B32: ='1-StartingPoint'!B41 -> Other Bank Debt | C32: ='5a-OpExYear1'!O34 -> 0 | E32: =IF('1-StartingPoint'!$F41<36,0,'Amortization&Depreciation'!O99) -> 0 | G32: =IF('1-StartingPoint'!$F41<36,0,'Amortization&Depreciation'!O103) -> 0
B33: Line of Credit | C33: =+'6a-CashFlowYear1'!O26 -> 0 | E33: =+'6b-CashFlowYrs1-3'!O25 -> 0 | G33: ='6b-CashFlowYrs1-3'!AB25 -> 0
B34: Bad Debt Expense | C34: =+'5a-OpExYear1'!O36 -> 0
B35: Total Other Expenses | C35: =SUM(C26:C34) -> 0 | E35: =SUM(E26:E34) -> 0 | G35: =SUM(G26:G34) -> 0
B36: Total Operating Expenses | C36: =SUM(C8:C22)+C35 -> 121820 | E36: =SUM(E8:E22)+E35 -> 127631 | G36: =SUM(G8:G22)+G35 -> 133724.15

Sheet 6a-CashFlowYear1
B2: Cash Flow Forecast Year 1
B4: Prepared By: | C4: Company Name:
B5: =IF(ISBLANK(Directions!C10),"Owner",Directions!C10) -> Owner | C5: =IF(ISBLANK(Directions!D10),"Company 1",Directions!D10) -> Company 1
C7: ='3a-SalesForecastYear1'!C16 -> Month 1 | D7: ='3a-SalesForecastYear1'!D16 -> Month 2 | E7: ='3a-SalesForecastYear1'!E16 -> Month 3 | F7: ='3a-SalesForecastYear1'!F16 -> Month 4 | G7: ='3a-SalesForecastYear1'!G16 -> Month 5 | H7: ='3a-SalesForecastYear1'!H16 -> Month 6 | I7: ='3a-SalesForecastYear1'!I16 -> Month 7 | J7: ='3a-SalesForecastYear1'!J16 -> Month 8 | ... N7: ='3a-SalesForecastYear1'!N16 -> Month 12 | O7: Totals
B8: Beginning Balance | C8: =Working_Capital -> 0 | D8: =C33 -> 3780.375 | E8: =D33 -> 11504.75 | F8: =E33 -> 19229.125 | G8: =F33 -> 30150 | H8: =G33 -> 41830.375 | I8: =H33 -> 52434.25 | J8: =I33 -> 69737.625 | K8: =J33 -> 88985 | ... N8: =M33 -> 176163.05
B9: Cash Inflows
B10: Cash Sales | C10: ='3a-SalesForecastYear1'!C53*'4-AdditionalInputs'!$C$9 -> 16524 | D10: ='3a-SalesForecastYear1'!D53*'4-AdditionalInputs'!$C$9 -> 18468 | E10: ='3a-SalesForecastYear1'!E53*'4-AdditionalInputs'!$C$9 -> 18468 | F10: ='3a-SalesForecastYear1'!F53*'4-AdditionalInputs'!$C$9 -> 34074 | G10: ='3a-SalesForecastYear1'!G53*'4-AdditionalInputs'!$C$9 -> 35910 | H10: ='3a-SalesForecastYear1'!H53*'4-AdditionalInputs'!$C$9 -> 35910 | I10: ='3a-SalesForecastYear1'!I53*'4-AdditionalInputs'!$C$9 -> 53406 | J10: ='3a-SalesForecastYear1'!J53*'4-AdditionalInputs'!$C$9 -> 55350 | ... N10: ='3a-SalesForecastYear1'!N53*'4-AdditionalInputs'!$C$9 -> 108702 | O10: =SUM(C10:N10) -> 611712
B11: Accounts Receivable | C11: 0 | D11: =('3a-SalesForecastYear1'!C53*'4-AdditionalInputs'!$C$10) -> 0 | E11: =('3a-SalesForecastYear1'!D53*'4-AdditionalInputs'!$C$10)+('3a-SalesForecastYear1'!C53*'4-AdditionalInputs'!$C$11) -> 0 | F11: =('3a-SalesForecastYear1'!E53*'4-AdditionalInputs'!$C$10)+('3a-SalesForecastYear1'!D53*'4-AdditionalInputs'!$C$11) -> 0 | G11: =('3a-SalesForecastYear1'!F53*'4-AdditionalInputs'!$C$10)+('3a-SalesForecastYear1'!E53*'4-AdditionalInputs'!$C$11) -> 0 | H11: =('3a-SalesForecastYear1'!G53*'4-AdditionalInputs'!$C$10)+('3a-SalesForecastYear1'!F53*'4-AdditionalInputs'!$C$11) -> 0 | I11: =('3a-SalesForecastYear1'!H53*'4-AdditionalInputs'!$C$10)+('3a-SalesForecastYear1'!G53*'4-AdditionalInputs'!$C$11) -> 0 | J11: =('3a-SalesForecastYear1'!I53*'4-AdditionalInputs'!$C$10)+('3a-SalesForecastYear1'!H53*'4-AdditionalInputs'!$C$11) -> 0 | K11: =('3a-SalesForecastYear1'!J53*'4-AdditionalInputs'!$C$10)+('3a-SalesForecastYear1'!I53*'4-AdditionalInputs'!$C$11) -> 0 | L11: =('3a-SalesForecastYear1'!K53*'4-AdditionalInputs'!$C$10)+('3a-SalesForecastYear1'!J53*'4-AdditionalInputs'!$C$11) -> 0 | ... N11: =('3a-SalesForecastYear1'!M53*'4-AdditionalInputs'!$C$10)+('3a-SalesForecastYear1'!L53*'4-AdditionalInputs'!$C$11) -> 0 | O11: =SUM(C11:N11) -> 0
B12: Total Cash Inflows | C12: =SUM(C10:C11) -> 16524 | D12: =SUM(D10:D11) -> 18468 | E12: =SUM(E10:E11) -> 18468 | F12: =SUM(F10:F11) -> 34074 | G12: =SUM(G10:G11) -> 35910 | H12: =SUM(H10:H11) -> 35910 | I12: =SUM(I10:I11) -> 53406 | J12: =SUM(J10:J11) -> 55350 | ... O12: =SUM(O10:O11) -> 611712
B14: Cash Outflows
B15: Investing Activities
B16: New Fixed Asset Purchases | C16: 0 | D16: ='4-AdditionalInputs'!E35 -> 0 | E16: ='4-AdditionalInputs'!F35 -> 0 | F16: ='4-AdditionalInputs'!G35 -> 0 | G16: ='4-AdditionalInputs'!H35 -> 0 | H16: ='4-AdditionalInputs'!I35 -> 0 | I16: ='4-AdditionalInputs'!J35 -> 0 | J16: ='4-AdditionalInputs'!K35 -> 0 | K16: ='4-AdditionalInputs'!L35 -> 0 | ... N16: ='4-AdditionalInputs'!O35 -> 0 | O16: =SUM(C16:N16) -> 0
B17: Additional Inventory | O17: =SUM(C17:N17) -> 0
B18: Cost of Goods Sold | C18: ='3a-SalesForecastYear1'!C54*'4-AdditionalInputs'!$C$17 -> 6480 | D18: =('3a-SalesForecastYear1'!D54*'4-AdditionalInputs'!$C$17)+('3a-SalesForecastYear1'!C54*'4-AdditionalInputs'!$C$18) -> 6480 | E18: =('3a-SalesForecastYear1'!E54*'4-AdditionalInputs'!$C$17)+('3a-SalesForecastYear1'!D54*'4-AdditionalInputs'!$C$18)+('3a-SalesForecastYear1'!C54*'4-AdditionalInputs'!$C$19) -> 6480 | F18: =('3a-SalesForecastYear1'!F54*'4-AdditionalInputs'!$C$17)+('3a-SalesForecastYear1'!E54*'4-AdditionalInputs'!$C$18)+('3a-SalesForecastYear1'!D54*'4-AdditionalInputs'!$C$19) -> 12600 | G18: =('3a-SalesForecastYear1'!G54*'4-AdditionalInputs'!$C$17)+('3a-SalesForecastYear1'!F54*'4-AdditionalInputs'!$C$18)+('3a-SalesForecastYear1'!E54*'4-AdditionalInputs'!$C$19) -> 12600 | H18: =('3a-SalesForecastYear1'!H54*'4-AdditionalInputs'!$C$17)+('3a-SalesForecastYear1'!G54*'4-AdditionalInputs'!$C$18)+('3a-SalesForecastYear1'!F54*'4-AdditionalInputs'!$C$19) -> 12600 | I18: =('3a-SalesForecastYear1'!I54*'4-AdditionalInputs'!$C$17)+('3a-SalesForecastYear1'!H54*'4-AdditionalInputs'!$C$18)+('3a-SalesForecastYear1'!G54*'4-AdditionalInputs'!$C$19) -> 19080 | J18: =('3a-SalesForecastYear1'!J54*'4-AdditionalInputs'!$C$17)+('3a-SalesForecastYear1'!I54*'4-AdditionalInputs'!$C$18)+('3a-SalesForecastYear1'!H54*'4-AdditionalInputs'!$C$19) -> 19080 | K18: =('3a-SalesForecastYear1'!K54*'4-AdditionalInputs'!$C$17)+('3a-SalesForecastYear1'!J54*'4-AdditionalInputs'!$C$18)+('3a-SalesForecastYear1'!I54*'4-AdditionalInputs'!$C$19) -> 25200 | L18: =('3a-SalesForecastYear1'!L54*'4-AdditionalInputs'!$C$17)+('3a-SalesForecastYear1'!K54*'4-AdditionalInputs'!$C$18)+('3a-SalesForecastYear1'!J54*'4-AdditionalInputs'!$C$19) -> 25200 | ... N18: =('3a-SalesForecastYear1'!N54*'4-AdditionalInputs'!$C$17)+('3a-SalesForecastYear1'!M54*'4-AdditionalInputs'!$C$18)+('3a-SalesForecastYear1'!L54*'4-AdditionalInputs'!$C$19) -> 38160 | O18: =SUM(C18:N18) -> 215640
B19: Operating Activities
B20: Operating Expenses | C20: ='5a-OpExYear1'!C25 -> 6240 | D20: ='5a-OpExYear1'!D25 -> 4240 | E20: ='5a-OpExYear1'!E25 -> 4240 | F20: ='5a-OpExYear1'!F25 -> 7300 | G20: ='5a-OpExYear1'!G25 -> 7300 | H20: ='5a-OpExYear1'!H25 -> 7300 | I20: ='5a-OpExYear1'!I25 -> 10540 | J20: ='5a-OpExYear1'!J25 -> 10540 | ... N20: ='5a-OpExYear1'!N25 -> 20080 | O20: =SUM(C20:N20) -> 121820
B21: Payroll | C21: ='2a-PayrollYear1'!F25 -> 23.625 | D21: ='2a-PayrollYear1'!G25 -> 23.625 | E21: ='2a-PayrollYear1'!H25 -> 23.625 | F21: ='2a-PayrollYear1'!I25 -> 3253.125 | G21: ='2a-PayrollYear1'!J25 -> 4329.625 | H21: ='2a-PayrollYear1'!K25 -> 5406.125 | I21: ='2a-PayrollYear1'!L25 -> 6482.625 | J21: ='2a-PayrollYear1'!M25 -> 6482.625 | ... N21: ='2a-PayrollYear1'!Q25 -> 7200.6505 | O21: =SUM(C21:N21) -> 54827.602
B22: Taxes | C22: 0 | D22: 0 | E22: =SUM('7a-IncomeStatementYear1'!C59:E59) -> 0 | F22: 0 | G22: 0 | H22: =SUM('7a-IncomeStatementYear1'!F59:H59) -> 0 | I22: 0 | J22: 0 | K22: =SUM('7a-IncomeStatementYear1'!I59:K59) -> 0 | L22: 0 | M22: 0 | N22: =SUM('7a-IncomeStatementYear1'!L59:N59) -> 0 | O22: =SUM(C22:N22) -> 0
B23: Financing Activities
B24: Loan Payments | C24: =SUM('Amortization&Depreciation'!C15:C16)+SUM('Amortization&Depreciation'!C35:C36)+SUM('Amortization&Depreciation'!C55:C56)+SUM('Amortization&Depreciation'!C75:C76)+SUM('Amortization&Depreciation'!C95:C96) -> 0 | D24: =SUM('Amortization&Depreciation'!D15:D16)+SUM('Amortization&Depreciation'!D35:D36)+SUM('Amortization&Depreciation'!D55:D56)+SUM('Amortization&Depreciation'!D75:D76)+SUM('Amortization&Depreciation'!D95:D96) -> 0 | E24: =SUM('Amortization&Depreciation'!E15:E16)+SUM('Amortization&Depreciation'!E35:E36)+SUM('Amortization&Depreciation'!E55:E56)+SUM('Amortization&Depreciation'!E75:E76)+SUM('Amortization&Depreciation'!E95:E96) -> 0 | F24: =SUM('Amortization&Depreciation'!F15:F16)+SUM('Amortization&Depreciation'!F35:F36)+SUM('Amortization&Depreciation'!F55:F56)+SUM('Amortization&Depreciation'!F75:F76)+SUM('Amortization&Depreciation'!F95:F96) -> 0 | G24: =SUM('Amortization&Depreciation'!G15:G16)+SUM('Amortization&Depreciation'!G35:G36)+SUM('Amortization&Depreciation'!G55:G56)+SUM('Amortization&Depreciation'!G75:G76)+SUM('Amortization&Depreciation'!G95:G96) -> 0 | H24: =SUM('Amortization&Depreciation'!H15:H16)+SUM('Amortization&Depreciation'!H35:H36)+SUM('Amortization&Depreciation'!H55:H56)+SUM('Amortization&Depreciation'!H75:H76)+SUM('Amortization&Depreciation'!H95:H96) -> 0 | I24: =SUM('Amortization&Depreciation'!I15:I16)+SUM('Amortization&Depreciation'!I35:I36)+SUM('Amortization&Depreciation'!I55:I56)+SUM('Amortization&Depreciation'!I75:I76)+SUM('Amortization&Depreciation'!I95:I96) -> 0 | J24: =SUM('Amortization&Depreciation'!J15:J16)+SUM('Amortization&Depreciation'!J35:J36)+SUM('Amortization&Depreciation'!J55:J56)+SUM('Amortization&Depreciation'!J75:J76)+SUM('Amortization&Depreciation'!J95:J96) -> 0 | ... N24: =SUM('Amortization&Depreciation'!N15:N16)+SUM('Amortization&Depreciation'!N35:N36)+SUM('Amortization&Depreciation'!N55:N56)+SUM('Amortization&Depreciation'!N75:N76)+SUM('Amortization&Depreciation'!N95:N96) -> 0 | O24: =SUM(C24:N24) -> 0
B25: Owners Distribution | O25: =SUM(C25:N25) -> 0
B26: Line of Credit Interest | D26: =C34*'4-AdditionalInputs'!$D$25/12 -> 0 | E26: =D34*'4-AdditionalInputs'!$D$25/12 -> 0 | F26: =E34*'4-AdditionalInputs'!$D$25/12 -> 0 | G26: =F34*'4-AdditionalInputs'!$D$25/12 -> 0 | H26: =G34*'4-AdditionalInputs'!$D$25/12 -> 0 | I26: =H34*'4-AdditionalInputs'!$D$25/12 -> 0 | J26: =I34*'4-AdditionalInputs'!$D$25/12 -> 0 | K26: =J34*'4-AdditionalInputs'!$D$25/12 -> 0 | ... N26: =M34*'4-AdditionalInputs'!$D$25/12 -> 0 | O26: =SUM(C26:N26) -> 0
B27: Line of Credit Repayments | O27: =SUM(C27:N27) -> 0
B28: Dividends Paid | O28: =SUM(C28:N28) -> 0
B29: Total Cash Outflows | C29: =SUM(C16:C28) -> 12743.625 | D29: =SUM(D16:D28) -> 10743.625 | E29: =SUM(E16:E28) -> 10743.625 | F29: =SUM(F16:F28) -> 23153.125 | G29: =SUM(G16:G28) -> 24229.625 | H29: =SUM(H16:H28) -> 25306.125 | I29: =SUM(I16:I28) -> 36102.625 | J29: =SUM(J16:J28) -> 36102.625 | ... N29: =SUM(N16:N28) -> 65440.651 | O29: =SUM(C29:N29) -> 392287.6
B30: Net Cash Flows | C30: =C12-C29 -> 3780.375 | D30: =D12-D29 -> 7724.375 | E30: =E12-E29 -> 7724.375 | F30: =F12-F29 -> 10920.875 | G30: =G12-G29 -> 11680.375 | H30: =H12-H29 -> 10603.875 | I30: =I12-I29 -> 17303.375 | J30: =J12-J29 -> 19247.375 | ... N30: =N12-N29 -> 43261.349 | O30: =SUM(C30:N30) -> 219424.4
B31: Operating Cash Balance | C31: =C8+C30 -> 3780.375 | D31: =D8+D30 -> 11504.75 | E31: =E8+E30 -> 19229.125 | F31: =F8+F30 -> 30150 | G31: =G8+G30 -> 41830.375 | H31: =H8+H30 -> 52434.25 | I31: =I8+I30 -> 69737.625 | J31: =J8+J30 -> 88985 | ... N31: =N8+N30 -> 219424.4
B32: Line of Credit Drawdown | C32: =IF(C31<'4-AdditionalInputs'!$D$24,'4-AdditionalInputs'!$D$24-C31,0) -> 0 | D32: =IF(D31<'4-AdditionalInputs'!$D$24,'4-AdditionalInputs'!$D$24-D31,0) -> 0 | E32: =IF(E31<'4-AdditionalInputs'!$D$24,'4-AdditionalInputs'!$D$24-E31,0) -> 0 | F32: =IF(F31<'4-AdditionalInputs'!$D$24,'4-AdditionalInputs'!$D$24-F31,0) -> 0 | G32: =IF(G31<'4-AdditionalInputs'!$D$24,'4-AdditionalInputs'!$D$24-G31,0) -> 0 | H32: =IF(H31<'4-AdditionalInputs'!$D$24,'4-AdditionalInputs'!$D$24-H31,0) -> 0 | I32: =IF(I31<'4-AdditionalInputs'!$D$24,'4-AdditionalInputs'!$D$24-I31,0) -> 0 | J32: =IF(J31<'4-AdditionalInputs'!$D$24,'4-AdditionalInputs'!$D$24-J31,0) -> 0 | ... N32: =IF(N31<'4-AdditionalInputs'!$D$24,'4-AdditionalInputs'!$D$24-N31,0) -> 0 | O32: =SUM(C32:N32) -> 0
B33: Ending Cash Balance | C33: =SUM(C31+C32) -> 3780.375 | D33: =SUM(D31+D32) -> 11504.75 | E33: =SUM(E31+E32) -> 19229.125 | F33: =SUM(F31+F32) -> 30150 | G33: =SUM(G31+G32) -> 41830.375 | H33: =SUM(H31+H32) -> 52434.25 | I33: =SUM(I31+I32) -> 69737.625 | J33: =SUM(J31+J32) -> 88985 | ... N33: =SUM(N31+N32) -> 219424.4
B34: Line of Credit Balance | C34: =C32-C27 -> 0 | D34: =D32+C34-D27 -> 0 | E34: =E32+D34-E27 -> 0 | F34: =F32+E34-F27 -> 0 | G34: =G32+F34-G27 -> 0 | H34: =H32+G34-H27 -> 0 | I34: =I32+H34-I27 -> 0 | J34: =J32+I34-J27 -> 0 | K34: =K32+J34-K27 -> 0 | ... N34: =N32+M34-N27 -> 0

Sheet 6b-CashFlowYrs1-3
B1: Cash Flow Forecast Years 1-3
B3: Prepared By: | C3: Company Name:
B4: =IF(ISBLANK(Directions!C10),"Owner",Directions!C10) -> Owner | C4: =IF(ISBLANK(Directions!D10),"Company 1",Directions!D10) -> Company 1
B6: Year 1 Totals | C6: ='3a-SalesForecastYear1'!C16 -> Month 1 | D6: ='3a-SalesForecastYear1'!D16 -> Month 2 | E6: ='3a-SalesForecastYear1'!E16 -> Month 3 | F6: ='3a-SalesForecastYear1'!F16 -> Month 4 | G6: ='3a-SalesForecastYear1'!G16 -> Month 5 | H6: ='3a-SalesForecastYear1'!H16 -> Month 6 | I6: ='3a-SalesForecastYear1'!I16 -> Month 7 | J6: ='3a-SalesForecastYear1'!J16 -> Month 8 | ... N6: ='3a-SalesForecastYear1'!N16 -> Month 12 | O6: Year 2 Totals | P6: =C6 -> Month 1 | Q6: =D6 -> Month 2 | R6: =E6 -> Month 3 | S6: =F6 -> Month 4 | T6: =G6 -> Month 5 | U6: =H6 -> Month 6 | V6: =I6 -> Month 7 | W6: =J6 -> Month 8 | ... AA6: =N6 -> Month 12 | AB6: Year 3 Totals
A7: Beginning Balance | C7: =Y1EndingCashBal -> 219424.4 | D7: =C32 -> 273847.72 | E7: =D32 -> 330387.3 | F7: =E32 -> 389106.64 | G7: =F32 -> 450071.11 | H7: =G32 -> 513348.07 | I7: =H32 -> 579006.91 | J7: =I32 -> 647119.07 | K7: =J32 -> 717758.15 | ... N7: =M32 -> 945606.48 | P7: =N32 -> 1027134.4 | Q7: =P32 -> 1106509.8 | R7: =Q32 -> 1187838.1 | S7: =R32 -> 1271158.4 | T7: =S32 -> 1356510.5 | U7: =T32 -> 1443935 | V7: =U32 -> 1533473.5 | W7: =V32 -> 1625168.2 | X7: =W32 -> 1719062.3 | ... AA7: =Z32 -> 2014384.5
A8: Cash Inflows
A9: Cash Sales | B9: ='6a-CashFlowYear1'!O10 -> 611712 | C9: =('3b-SalesForecastYrs1-3'!C47*'4-AdditionalInputs'!$D$9) -> 108702 | D9: =('3b-SalesForecastYrs1-3'!D47*'4-AdditionalInputs'!$D$9) -> 111963.06 | E9: =('3b-SalesForecastYrs1-3'!E47*'4-AdditionalInputs'!$D$9) -> 115321.95 | F9: =('3b-SalesForecastYrs1-3'!F47*'4-AdditionalInputs'!$D$9) -> 118781.61 | G9: =('3b-SalesForecastYrs1-3'!G47*'4-AdditionalInputs'!$D$9) -> 122345.06 | H9: =('3b-SalesForecastYrs1-3'!H47*'4-AdditionalInputs'!$D$9) -> 126015.41 | I9: =('3b-SalesForecastYrs1-3'!I47*'4-AdditionalInputs'!$D$9) -> 129795.87 | J9: =('3b-SalesForecastYrs1-3'!J47*'4-AdditionalInputs'!$D$9) -> 133689.75 | ... N9: =('3b-SalesForecastYrs1-3'!N47*'4-AdditionalInputs'!$D$9) -> 150468.99 | O9: =SUM(C9:N9) -> 1542702 | P9: =('3b-SalesForecastYrs1-3'!R47*'4-AdditionalInputs'!$E$9) -> 150468.99 | Q9: =('3b-SalesForecastYrs1-3'!S47*'4-AdditionalInputs'!$E$9) -> 153478.37 | R9: =('3b-SalesForecastYrs1-3'!T47*'4-AdditionalInputs'!$E$9) -> 156547.94 | S9: =('3b-SalesForecastYrs1-3'!U47*'4-AdditionalInputs'!$E$9) -> 159678.9 | T9: =('3b-SalesForecastYrs1-3'!V47*'4-AdditionalInputs'!$E$9) -> 162872.47 | U9: =('3b-SalesForecastYrs1-3'!W47*'4-AdditionalInputs'!$E$9) -> 166129.92 | V9: =('3b-SalesForecastYrs1-3'!X47*'4-AdditionalInputs'!$E$9) -> 169452.52 | W9: =('3b-SalesForecastYrs1-3'!Y47*'4-AdditionalInputs'!$E$9) -> 172841.57 | ... AA9: =('3b-SalesForecastYrs1-3'!AC47*'4-AdditionalInputs'!$E$9) -> 187089.28 | AB9: =SUM(P9:AA9) -> 2018103.6
A10: Accounts Receivable | B10: ='6a-CashFlowYear1'!O11 -> 0 | C10: =('3a-SalesForecastYear1'!M53*'4-AdditionalInputs'!D11)+('3a-SalesForecastYear1'!N53*'4-AdditionalInputs'!D10) -> 0 | D10: =('3a-SalesForecastYear1'!N53*'4-AdditionalInputs'!$D$11)+('3b-SalesForecastYrs1-3'!C47*'4-AdditionalInputs'!$D$10) -> 0 | E10: =('3b-SalesForecastYrs1-3'!C47*'4-AdditionalInputs'!$D$11)+('3b-SalesForecastYrs1-3'!D47*'4-AdditionalInputs'!$D$10) -> 0 | F10: =('3b-SalesForecastYrs1-3'!D47*'4-AdditionalInputs'!$D$11)+('3b-SalesForecastYrs1-3'!E47*'4-AdditionalInputs'!$D$10) -> 0 | G10: =('3b-SalesForecastYrs1-3'!E47*'4-AdditionalInputs'!$D$11)+('3b-SalesForecastYrs1-3'!F47*'4-AdditionalInputs'!$D$10) -> 0 | H10: =('3b-SalesForecastYrs1-3'!F47*'4-AdditionalInputs'!$D$11)+('3b-SalesForecastYrs1-3'!G47*'4-AdditionalInputs'!$D$10) -> 0 | I10: =('3b-SalesForecastYrs1-3'!G47*'4-AdditionalInputs'!$D$11)+('3b-SalesForecastYrs1-3'!H47*'4-AdditionalInputs'!$D$10) -> 0 | J10: =('3b-SalesForecastYrs1-3'!H47*'4-AdditionalInputs'!$D$11)+('3b-SalesForecastYrs1-3'!I47*'4-AdditionalInputs'!$D$10) -> 0 | K10: =('3b-SalesForecastYrs1-3'!I47*'4-AdditionalInputs'!$D$11)+('3b-SalesForecastYrs1-3'!J47*'4-AdditionalInputs'!$D$10) -> 0 | L10: =('3b-SalesForecastYrs1-3'!J47*'4-AdditionalInputs'!$D$11)+('3b-SalesForecastYrs1-3'!K47*'4-AdditionalInputs'!$D$10) -> 0 | ... N10: =('3b-SalesForecastYrs1-3'!L47*'4-AdditionalInputs'!$D$11)+('3b-SalesForecastYrs1-3'!M47*'4-AdditionalInputs'!$D$10) -> 0 | O10: =SUM(C10:N10) -> 0 | P10: =('3b-SalesForecastYrs1-3'!M47*'4-AdditionalInputs'!E11)+('3b-SalesForecastYrs1-3'!N47*'4-AdditionalInputs'!E10) -> 0 | Q10: =('3b-SalesForecastYrs1-3'!N47*'4-AdditionalInputs'!E11)+('3b-SalesForecastYrs1-3'!R47*'4-AdditionalInputs'!E10) -> 0 | R10: =('3b-SalesForecastYrs1-3'!R47*'4-AdditionalInputs'!$E$11)+('3b-SalesForecastYrs1-3'!S47*'4-AdditionalInputs'!$E$10) -> 0 | S10: =('3b-SalesForecastYrs1-3'!S47*'4-AdditionalInputs'!$E$11)+('3b-SalesForecastYrs1-3'!T47*'4-AdditionalInputs'!$E$10) -> 0 | T10: =('3b-SalesForecastYrs1-3'!T47*'4-AdditionalInputs'!$E$11)+('3b-SalesForecastYrs1-3'!U47*'4-AdditionalInputs'!$E$10) -> 0 | U10: =('3b-SalesForecastYrs1-3'!U47*'4-AdditionalInputs'!$E$11)+('3b-SalesForecastYrs1-3'!V47*'4-AdditionalInputs'!$E$10) -> 0 | V10: =('3b-SalesForecastYrs1-3'!V47*'4-AdditionalInputs'!$E$11)+('3b-SalesForecastYrs1-3'!W47*'4-AdditionalInputs'!$E$10) -> 0 | W10: =('3b-SalesForecastYrs1-3'!W47*'4-AdditionalInputs'!$E$11)+('3b-SalesForecastYrs1-3'!X47*'4-AdditionalInputs'!$E$10) -> 0 | X10: =('3b-SalesForecastYrs1-3'!X47*'4-AdditionalInputs'!$E$11)+('3b-SalesForecastYrs1-3'!Y47*'4-AdditionalInputs'!$E$10) -> 0 | Y10: =('3b-SalesForecastYrs1-3'!Y47*'4-AdditionalInputs'!$E$11)+('3b-SalesForecastYrs1-3'!Z47*'4-AdditionalInputs'!$E$10) -> 0 | ... AA10: =('3b-SalesForecastYrs1-3'!AA47*'4-AdditionalInputs'!$E$11)+('3b-SalesForecastYrs1-3'!AB47*'4-AdditionalInputs'!$E$10) -> 0 | AB10: =SUM(P10:AA10) -> 0
A11: Total Cash Inflows | B11: ='6a-CashFlowYear1'!O12 -> 611712 | C11: =SUM(C9:C10) -> 108702 | D11: =SUM(D9:D10) -> 111963.06 | E11: =SUM(E9:E10) -> 115321.95 | F11: =SUM(F9:F10) -> 118781.61 | G11: =SUM(G9:G10) -> 122345.06 | H11: =SUM(H9:H10) -> 126015.41 | I11: =SUM(I9:I10) -> 129795.87 | J11: =SUM(J9:J10) -> 133689.75 | ... AB11: =SUM(AB9:AB10) -> 2018103.6
A13: Cash Outflows
A14: Investing Activities
A15: New Fixed Asset Purchases | B15: ='6a-CashFlowYear1'!O16 -> 0 | C15: ='4-AdditionalInputs'!$Q$35/12 -> 0 | D15: ='4-AdditionalInputs'!$Q$35/12 -> 0 | E15: ='4-AdditionalInputs'!$Q$35/12 -> 0 | F15: ='4-AdditionalInputs'!$Q$35/12 -> 0 | G15: ='4-AdditionalInputs'!$Q$35/12 -> 0 | H15: ='4-AdditionalInputs'!$Q$35/12 -> 0 | I15: ='4-AdditionalInputs'!$Q$35/12 -> 0 | J15: ='4-AdditionalInputs'!$Q$35/12 -> 0 | ... N15: ='4-AdditionalInputs'!$Q$35/12 -> 0 | O15: =SUM(C15:N15) -> 0 | P15: ='4-AdditionalInputs'!$R$35/12 -> 0 | Q15: ='4-AdditionalInputs'!$R$35/12 -> 0 | R15: ='4-AdditionalInputs'!$R$35/12 -> 0 | S15: ='4-AdditionalInputs'!$R$35/12 -> 0 | T15: ='4-AdditionalInputs'!$R$35/12 -> 0 | U15: ='4-AdditionalInputs'!$R$35/12 -> 0 | V15: ='4-AdditionalInputs'!$R$35/12 -> 0 | W15: ='4-AdditionalInputs'!$R$35/12 -> 0 | ... AA15: ='4-AdditionalInputs'!$R$35/12 -> 0 | AB15: =SUM(P15:AA15) -> 0
A16: Additional Inventory | B16: =+'6a-CashFlowYear1'!O17 -> 0 | O16: =SUM(C16:N16) -> 0 | AB16: =SUM(P16:AA16) -> 0
A17: Cost of Goods Sold | B17: ='6a-CashFlowYear1'!O18 -> 215640 | C17: =('3b-SalesForecastYrs1-3'!C48*'4-AdditionalInputs'!$D$17)+('3a-SalesForecastYear1'!N54*'4-AdditionalInputs'!$D$18)+('3a-SalesForecastYear1'!M54*'4-AdditionalInputs'!$D$19) -> 38160 | D17: =('3b-SalesForecastYrs1-3'!D48*'4-AdditionalInputs'!$D$17)+('3b-SalesForecastYrs1-3'!C48*'4-AdditionalInputs'!$D$18)+('3a-SalesForecastYear1'!N54*'4-AdditionalInputs'!$D$19) -> 39304.8 | E17: =('3b-SalesForecastYrs1-3'!E48*'4-AdditionalInputs'!$D$17)+('3b-SalesForecastYrs1-3'!D48*'4-AdditionalInputs'!$D$18)+('3b-SalesForecastYrs1-3'!C48*'4-AdditionalInputs'!$D$19) -> 40483.944 | F17: =('3b-SalesForecastYrs1-3'!F48*'4-AdditionalInputs'!$D$17)+('3b-SalesForecastYrs1-3'!E48*'4-AdditionalInputs'!$D$18)+('3b-SalesForecastYrs1-3'!D48*'4-AdditionalInputs'!$D$19) -> 41698.462 | G17: =('3b-SalesForecastYrs1-3'!G48*'4-AdditionalInputs'!$D$17)+('3b-SalesForecastYrs1-3'!F48*'4-AdditionalInputs'!$D$18)+('3b-SalesForecastYrs1-3'!E48*'4-AdditionalInputs'!$D$19) -> 42949.416 | H17: =('3b-SalesForecastYrs1-3'!H48*'4-AdditionalInputs'!$D$17)+('3b-SalesForecastYrs1-3'!G48*'4-AdditionalInputs'!$D$18)+('3b-SalesForecastYrs1-3'!F48*'4-AdditionalInputs'!$D$19) -> 44237.899 | I17: =('3b-SalesForecastYrs1-3'!I48*'4-AdditionalInputs'!$D$17)+('3b-SalesForecastYrs1-3'!H48*'4-AdditionalInputs'!$D$18)+('3b-SalesForecastYrs1-3'!G48*'4-AdditionalInputs'!$D$19) -> 45565.036 | J17: =('3b-SalesForecastYrs1-3'!J48*'4-AdditionalInputs'!$D$17)+('3b-SalesForecastYrs1-3'!I48*'4-AdditionalInputs'!$D$18)+('3b-SalesForecastYrs1-3'!H48*'4-AdditionalInputs'!$D$19) -> 46931.987 | K17: =('3b-SalesForecastYrs1-3'!K48*'4-AdditionalInputs'!$D$17)+('3b-SalesForecastYrs1-3'!J48*'4-AdditionalInputs'!$D$18)+('3b-SalesForecastYrs1-3'!I48*'4-AdditionalInputs'!$D$19) -> 48339.946 | L17: =('3b-SalesForecastYrs1-3'!L48*'4-AdditionalInputs'!$D$17)+('3b-SalesForecastYrs1-3'!K48*'4-AdditionalInputs'!$D$18)+('3b-SalesForecastYrs1-3'!J48*'4-AdditionalInputs'!$D$19) -> 49790.145 | ... N17: =('3b-SalesForecastYrs1-3'!N48*'4-AdditionalInputs'!$D$17)+('3b-SalesForecastYrs1-3'!M48*'4-AdditionalInputs'!$D$18)+('3b-SalesForecastYrs1-3'!L48*'4-AdditionalInputs'!$D$19) -> 52822.365 | O17: =SUM(C17:N17) -> 541567.85 | P17: =('3b-SalesForecastYrs1-3'!R48*'4-AdditionalInputs'!$E$17)+('3b-SalesForecastYrs1-3'!N48*'4-AdditionalInputs'!$E$18)+('3b-SalesForecastYrs1-3'!M48*'4-AdditionalInputs'!$E$19) -> 52822.365 | Q17: =('3b-SalesForecastYrs1-3'!S48*'4-AdditionalInputs'!$E$17)+('3b-SalesForecastYrs1-3'!R48*'4-AdditionalInputs'!$E$18)+('3b-SalesForecastYrs1-3'!N48*'4-AdditionalInputs'!$E$19) -> 53878.812 | R17: =('3b-SalesForecastYrs1-3'!T48*'4-AdditionalInputs'!$E$17)+('3b-SalesForecastYrs1-3'!S48*'4-AdditionalInputs'!$E$18)+('3b-SalesForecastYrs1-3'!R48*'4-AdditionalInputs'!$E$19) -> 54956.388 | S17: =('3b-SalesForecastYrs1-3'!U48*'4-AdditionalInputs'!$E$17)+('3b-SalesForecastYrs1-3'!T48*'4-AdditionalInputs'!$E$18)+('3b-SalesForecastYrs1-3'!S48*'4-AdditionalInputs'!$E$19) -> 56055.516 | T17: =('3b-SalesForecastYrs1-3'!V48*'4-AdditionalInputs'!$E$17)+('3b-SalesForecastYrs1-3'!U48*'4-AdditionalInputs'!$E$18)+('3b-SalesForecastYrs1-3'!T48*'4-AdditionalInputs'!$E$19) -> 57176.626 | U17: =('3b-SalesForecastYrs1-3'!W48*'4-AdditionalInputs'!$E$17)+('3b-SalesForecastYrs1-3'!V48*'4-AdditionalInputs'!$E$18)+('3b-SalesForecastYrs1-3'!U48*'4-AdditionalInputs'!$E$19) -> 58320.159 | V17: =('3b-SalesForecastYrs1-3'!X48*'4-AdditionalInputs'!$E$17)+('3b-SalesForecastYrs1-3'!W48*'4-AdditionalInputs'!$E$18)+('3b-SalesForecastYrs1-3'!V48*'4-AdditionalInputs'!$E$19) -> 59486.562 | W17: =('3b-SalesForecastYrs1-3'!Y48*'4-AdditionalInputs'!$E$17)+('3b-SalesForecastYrs1-3'!X48*'4-AdditionalInputs'!$E$18)+('3b-SalesForecastYrs1-3'!W48*'4-AdditionalInputs'!$E$19) -> 60676.293 | X17: =('3b-SalesForecastYrs1-3'!Z48*'4-AdditionalInputs'!$E$17)+('3b-SalesForecastYrs1-3'!Y48*'4-AdditionalInputs'!$E$18)+('3b-SalesForecastYrs1-3'!X48*'4-AdditionalInputs'!$E$19) -> 61889.819 | Y17: =('3b-SalesForecastYrs1-3'!AA48*'4-AdditionalInputs'!$E$17)+('3b-SalesForecastYrs1-3'!Z48*'4-AdditionalInputs'!$E$18)+('3b-SalesForecastYrs1-3'!Y48*'4-AdditionalInputs'!$E$19) -> 63127.615 | ... AA17: =('3b-SalesForecastYrs1-3'!AC48*'4-AdditionalInputs'!$E$17)+('3b-SalesForecastYrs1-3'!AB48*'4-AdditionalInputs'!$E$18)+('3b-SalesForecastYrs1-3'!AA48*'4-AdditionalInputs'!$E$19) -> 65677.971 | AB17: =SUM(P17:AA17) -> 708458.29
A18: Operating Activities
A19: Operating Expenses | B19: ='6a-CashFlowYear1'!O20 -> 121820 | C19: =SUM('5b-OpExYrs1-3'!$E8:$E22)/12 -> 10635.917 | D19: =SUM('5b-OpExYrs1-3'!$E8:$E22)/12 -> 10635.917 | E19: =SUM('5b-OpExYrs1-3'!$E8:$E22)/12 -> 10635.917 | F19: =SUM('5b-OpExYrs1-3'!$E8:$E22)/12 -> 10635.917 | G19: =SUM('5b-OpExYrs1-3'!$E8:$E22)/12 -> 10635.917 | H19: =SUM('5b-OpExYrs1-3'!$E8:$E22)/12 -> 10635.917 | I19: =SUM('5b-OpExYrs1-3'!$E8:$E22)/12 -> 10635.917 | J19: =SUM('5b-OpExYrs1-3'!$E8:$E22)/12 -> 10635.917 | ... N19: =SUM('5b-OpExYrs1-3'!$E8:$E22)/12 -> 10635.917 | O19: =SUM(C19:N19) -> 127631 | P19: =SUM('5b-OpExYrs1-3'!$G8:$G22)/12 -> 11143.679 | Q19: =SUM('5b-OpExYrs1-3'!$G8:$G22)/12 -> 11143.679 | R19: =SUM('5b-OpExYrs1-3'!$G8:$G22)/12 -> 11143.679 | S19: =SUM('5b-OpExYrs1-3'!$G8:$G22)/12 -> 11143.679 | T19: =SUM('5b-OpExYrs1-3'!$G8:$G22)/12 -> 11143.679 | U19: =SUM('5b-OpExYrs1-3'!$G8:$G22)/12 -> 11143.679 | V19: =SUM('5b-OpExYrs1-3'!$G8:$G22)/12 -> 11143.679 | W19: =SUM('5b-OpExYrs1-3'!$G8:$G22)/12 -> 11143.679 | ... AA19: =SUM('5b-OpExYrs1-3'!$G8:$G22)/12 -> 11143.679 | AB19: =SUM(P19:AA19) -> 133724.15
A20: Payroll | B20: ='6a-CashFlowYear1'!O21 -> 54827.602 | C20: ='2b-PayrollYrs1-3'!$E$26/12 -> 5482.7602 | D20: ='2b-PayrollYrs1-3'!$E$26/12 -> 5482.7602 | E20: ='2b-PayrollYrs1-3'!$E$26/12 -> 5482.7602 | F20: ='2b-PayrollYrs1-3'!$E$26/12 -> 5482.7602 | G20: ='2b-PayrollYrs1-3'!$E$26/12 -> 5482.7602 | H20: ='2b-PayrollYrs1-3'!$E$26/12 -> 5482.7602 | I20: ='2b-PayrollYrs1-3'!$E$26/12 -> 5482.7602 | J20: ='2b-PayrollYrs1-3'!$E$26/12 -> 5482.7602 | ... N20: ='2b-PayrollYrs1-3'!$E$26/12 -> 5482.7602 | O20: =SUM(C20:N20) -> 65793.122 | P20: ='2b-PayrollYrs1-3'!$G$26/12 -> 7127.5883 | Q20: ='2b-PayrollYrs1-3'!$G$26/12 -> 7127.5883 | R20: ='2b-PayrollYrs1-3'!$G$26/12 -> 7127.5883 | S20: ='2b-PayrollYrs1-3'!$G$26/12 -> 7127.5883 | T20: ='2b-PayrollYrs1-3'!$G$26/12 -> 7127.5883 | U20: ='2b-PayrollYrs1-3'!$G$26/12 -> 7127.5883 | V20: ='2b-PayrollYrs1-3'!$G$26/12 -> 7127.5883 | W20: ='2b-PayrollYrs1-3'!$G$26/12 -> 7127.5883 | ... AA20: ='2b-PayrollYrs1-3'!$G$26/12 -> 7127.5883 | AB20: =SUM(P20:AA20) -> 85531.059
A21: Taxes | B21: ='6a-CashFlowYear1'!O22 -> 0 | C21: 0 | D21: 0 | E21: =SUM('7b-IncomeStatementYrs1-3'!C65:E65) -> 0 | F21: 0 | G21: 0 | H21: =SUM('7b-IncomeStatementYrs1-3'!F65:H65) -> 0 | I21: 0 | J21: 0 | K21: =SUM('7b-IncomeStatementYrs1-3'!I65:K65) -> 0 | L21: 0 | M21: 0 | N21: =SUM('7b-IncomeStatementYrs1-3'!L65:N65) -> 0 | P21: 0 | Q21: 0 | R21: =SUM('7b-IncomeStatementYrs1-3'!C69:E69) -> 0 | S21: 0 | T21: 0 | U21: =SUM('7b-IncomeStatementYrs1-3'!F69:H69) -> 0 | V21: 0 | W21: 0 | X21: =SUM('7b-IncomeStatementYrs1-3'!I69:K69) -> 0 | Y21: 0 | Z21: 0 | AA21: =SUM('7b-IncomeStatementYrs1-3'!L69:N69) -> 0 | AB21: =SUM(P21:AA21) -> 0
A22: Financing Activities
A23: Loan Payments | B23: ='6a-CashFlowYear1'!O24 -> 0 | C23: =SUM('Amortization&Depreciation'!C19:C20)+SUM('Amortization&Depreciation'!C39:C40)+SUM('Amortization&Depreciation'!C59:C60)+SUM('Amortization&Depreciation'!C79:C80)+SUM('Amortization&Depreciation'!C99:C100) -> 0 | D23: =SUM('Amortization&Depreciation'!D19:D20)+SUM('Amortization&Depreciation'!D39:D40)+SUM('Amortization&Depreciation'!D59:D60)+SUM('Amortization&Depreciation'!D79:D80)+SUM('Amortization&Depreciation'!D99:D100) -> 0 | E23: =SUM('Amortization&Depreciation'!E19:E20)+SUM('Amortization&Depreciation'!E39:E40)+SUM('Amortization&Depreciation'!E59:E60)+SUM('Amortization&Depreciation'!E79:E80)+SUM('Amortization&Depreciation'!E99:E100) -> 0 | F23: =SUM('Amortization&Depreciation'!F19:F20)+SUM('Amortization&Depreciation'!F39:F40)+SUM('Amortization&Depreciation'!F59:F60)+SUM('Amortization&Depreciation'!F79:F80)+SUM('Amortization&Depreciation'!F99:F100) -> 0 | G23: =SUM('Amortization&Depreciation'!G19:G20)+SUM('Amortization&Depreciation'!G39:G40)+SUM('Amortization&Depreciation'!G59:G60)+SUM('Amortization&Depreciation'!G79:G80)+SUM('Amortization&Depreciation'!G99:G100) -> 0 | H23: =SUM('Amortization&Depreciation'!H19:H20)+SUM('Amortization&Depreciation'!H39:H40)+SUM('Amortization&Depreciation'!H59:H60)+SUM('Amortization&Depreciation'!H79:H80)+SUM('Amortization&Depreciation'!H99:H100) -> 0 | I23: =SUM('Amortization&Depreciation'!I19:I20)+SUM('Amortization&Depreciation'!I39:I40)+SUM('Amortization&Depreciation'!I59:I60)+SUM('Amortization&Depreciation'!I79:I80)+SUM('Amortization&Depreciation'!I99:I100) -> 0 | J23: =SUM('Amortization&Depreciation'!J19:J20)+SUM('Amortization&Depreciation'!J39:J40)+SUM('Amortization&Depreciation'!J59:J60)+SUM('Amortization&Depreciation'!J79:J80)+SUM('Amortization&Depreciation'!J99:J100) -> 0 | ... N23: =SUM('Amortization&Depreciation'!N19:N20)+SUM('Amortization&Depreciation'!N39:N40)+SUM('Amortization&Depreciation'!N59:N60)+SUM('Amortization&Depreciation'!N79:N80)+SUM('Amortization&Depreciation'!N99:N100) -> 0 | O23: =SUM(C23:N23) -> 0 | P23: =SUM('Amortization&Depreciation'!C23:C24)+SUM('Amortization&Depreciation'!C43:C44)+SUM('Amortization&Depreciation'!C63:C64)+SUM('Amortization&Depreciation'!C83:C84)+SUM('Amortization&Depreciation'!C103:C104) -> 0 | Q23: =SUM('Amortization&Depreciation'!D23:D24)+SUM('Amortization&Depreciation'!D43:D44)+SUM('Amortization&Depreciation'!D63:D64)+SUM('Amortization&Depreciation'!D83:D84)+SUM('Amortization&Depreciation'!D103:D104) -> 0 | R23: =SUM('Amortization&Depreciation'!E23:E24)+SUM('Amortization&Depreciation'!E43:E44)+SUM('Amortization&Depreciation'!E63:E64)+SUM('Amortization&Depreciation'!E83:E84)+SUM('Amortization&Depreciation'!E103:E104) -> 0 | S23: =SUM('Amortization&Depreciation'!F23:F24)+SUM('Amortization&Depreciation'!F43:F44)+SUM('Amortization&Depreciation'!F63:F64)+SUM('Amortization&Depreciation'!F83:F84)+SUM('Amortization&Depreciation'!F103:F104) -> 0 | T23: =SUM('Amortization&Depreciation'!G23:G24)+SUM('Amortization&Depreciation'!G43:G44)+SUM('Amortization&Depreciation'!G63:G64)+SUM('Amortization&Depreciation'!G83:G84)+SUM('Amortization&Depreciation'!G103:G104) -> 0 | U23: =SUM('Amortization&Depreciation'!H23:H24)+SUM('Amortization&Depreciation'!H43:H44)+SUM('Amortization&Depreciation'!H63:H64)+SUM('Amortization&Depreciation'!H83:H84)+SUM('Amortization&Depreciation'!H103:H104) -> 0 | V23: =SUM('Amortization&Depreciation'!I23:I24)+SUM('Amortization&Depreciation'!I43:I44)+SUM('Amortization&Depreciation'!I63:I64)+SUM('Amortization&Depreciation'!I83:I84)+SUM('Amortization&Depreciation'!I103:I104) -> 0 | W23: =SUM('Amortization&Depreciation'!J23:J24)+SUM('Amortization&Depreciation'!J43:J44)+SUM('Amortization&Depreciation'!J63:J64)+SUM('Amortization&Depreciation'!J83:J84)+SUM('Amortization&Depreciation'!J103:J104) -> 0 | ... AA23: =SUM('Amortization&Depreciation'!N23:N24)+SUM('Amortization&Depreciation'!N43:N44)+SUM('Amortization&Depreciation'!N63:N64)+SUM('Amortization&Depreciation'!N83:N84)+SUM('Amortization&Depreciation'!N103:N104) -> 0 | AB23: =SUM(P23:AA23) -> 0
A24: Owners Distribution | B24: ='6a-CashFlowYear1'!O25 -> 0 | O24: =SUM(C24:N24) -> 0 | AB24: =SUM(P24:AA24) -> 0
A25: Line of Credit Interest | B25: ='6a-CashFlowYear1'!O26 -> 0 | C25: ='6a-CashFlowYear1'!N34*'4-AdditionalInputs'!$D$25/12 -> 0 | D25: =C33*'4-AdditionalInputs'!$D$25/12 -> 0 | E25: =D33*'4-AdditionalInputs'!$D$25/12 -> 0 | F25: =E33*'4-AdditionalInputs'!$D$25/12 -> 0 | G25: =F33*'4-AdditionalInputs'!$D$25/12 -> 0 | H25: =G33*'4-AdditionalInputs'!$D$25/12 -> 0 | I25: =H33*'4-AdditionalInputs'!$D$25/12 -> 0 | J25: =I33*'4-AdditionalInputs'!$D$25/12 -> 0 | K25: =J33*'4-AdditionalInputs'!$D$25/12 -> 0 | ... N25: =M33*'4-AdditionalInputs'!$D$25/12 -> 0 | O25: =SUM(C25:N25) -> 0 | P25: =N33*'4-AdditionalInputs'!$D$25/12 -> 0 | Q25: =P33*'4-AdditionalInputs'!$D$25/12 -> 0 | R25: =Q33*'4-AdditionalInputs'!$D$25/12 -> 0 | S25: =R33*'4-AdditionalInputs'!$D$25/12 -> 0 | T25: =S33*'4-AdditionalInputs'!$D$25/12 -> 0 | U25: =T33*'4-AdditionalInputs'!$D$25/12 -> 0 | V25: =U33*'4-AdditionalInputs'!$D$25/12 -> 0 | W25: =V33*'4-AdditionalInputs'!$D$25/12 -> 0 | X25: =W33*'4-AdditionalInputs'!$D$25/12 -> 0 | ... AA25: =Z33*'4-AdditionalInputs'!$D$25/12 -> 0 | AB25: =SUM(P25:AA25) -> 0
A26: Line of Credit Repayments | B26: ='6a-CashFlowYear1'!O27 -> 0 | O26: =SUM(C26:N26) -> 0 | AB26: =SUM(P26:AA26) -> 0
A27: Dividends Paid | B27: ='6a-CashFlowYear1'!O28 -> 0 | O27: =SUM(C27:N27) -> 0 | AB27: =SUM(P27:AA27) -> 0
A28: Total Cash Outflows | B28: ='6a-CashFlowYear1'!O29 -> 392287.6 | C28: =SUM(C15:C27) -> 54278.677 | D28: =SUM(D15:D27) -> 55423.477 | E28: =SUM(E15:E27) -> 56602.621 | F28: =SUM(F15:F27) -> 57817.139 | G28: =SUM(G15:G27) -> 59068.093 | H28: =SUM(H15:H27) -> 60356.576 | I28: =SUM(I15:I27) -> 61683.713 | J28: =SUM(J15:J27) -> 63050.664 | ... AA28: =SUM(AA15:AA27) -> 83949.238 | AB28: =SUM(P28:AA28) -> 927713.5
A29: Net Cash Flows | B29: ='6a-CashFlowYear1'!O30 -> 219424.4 | C29: =C11-C28 -> 54423.323 | D29: =D11-D28 -> 56539.583 | E29: =E11-E28 -> 58719.331 | F29: =F11-F28 -> 60964.471 | G29: =G11-G28 -> 63276.966 | H29: =H11-H28 -> 65658.835 | I29: =I11-I28 -> 68112.16 | J29: =J11-J28 -> 70639.085 | ... AA29: =AA11-AA28 -> 103140.04 | AB29: =SUM(P29:AA29) -> 1090390.1
A30: Operating Cash Balance | C30: =C7+C29 -> 273847.72 | D30: =D7+D29 -> 330387.3 | E30: =E7+E29 -> 389106.64 | F30: =F7+F29 -> 450071.11 | G30: =G7+G29 -> 513348.07 | H30: =H7+H29 -> 579006.91 | I30: =I7+I29 -> 647119.07 | J30: =J7+J29 -> 717758.15 | ... N30: =N7+N29 -> 1027134.4 | P30: =P7+P29 -> 1106509.8 | Q30: =Q7+Q29 -> 1187838.1 | R30: =R7+R29 -> 1271158.4 | S30: =S7+S29 -> 1356510.5 | T30: =T7+T29 -> 1443935 | U30: =U7+U29 -> 1533473.5 | V30: =V7+V29 -> 1625168.2 | W30: =W7+W29 -> 1719062.3 | ... AA30: =AA7+AA29 -> 2117524.5
A31: Line of Credit Drawdown | B31: ='6a-CashFlowYear1'!O32 -> 0 | C31: =IF(C30<'4-AdditionalInputs'!$D$24,'4-AdditionalInputs'!$D$24-C30,0) -> 0 | D31: =IF(D30<'4-AdditionalInputs'!$D$24,'4-AdditionalInputs'!$D$24-D30,0) -> 0 | E31: =IF(E30<'4-AdditionalInputs'!$D$24,'4-AdditionalInputs'!$D$24-E30,0) -> 0 | F31: =IF(F30<'4-AdditionalInputs'!$D$24,'4-AdditionalInputs'!$D$24-F30,0) -> 0 | G31: =IF(G30<'4-AdditionalInputs'!$D$24,'4-AdditionalInputs'!$D$24-G30,0) -> 0 | H31: =IF(H30<'4-AdditionalInputs'!$D$24,'4-AdditionalInputs'!$D$24-H30,0) -> 0 | I31: =IF(I30<'4-AdditionalInputs'!$D$24,'4-AdditionalInputs'!$D$24-I30,0) -> 0 | J31: =IF(J30<'4-AdditionalInputs'!$D$24,'4-AdditionalInputs'!$D$24-J30,0) -> 0 | ... N31: =IF(N30<'4-AdditionalInputs'!$D$24,'4-AdditionalInputs'!$D$24-N30,0) -> 0 | O31: =SUM(C31:N31) -> 0 | P31: =IF(P30<'4-AdditionalInputs'!$D$24,'4-AdditionalInputs'!$D$24-P30,0) -> 0 | Q31: =IF(Q30<'4-AdditionalInputs'!$D$24,'4-AdditionalInputs'!$D$24-Q30,0) -> 0 | R31: =IF(R30<'4-AdditionalInputs'!$D$24,'4-AdditionalInputs'!$D$24-R30,0) -> 0 | S31: =IF(S30<'4-AdditionalInputs'!$D$24,'4-AdditionalInputs'!$D$24-S30,0) -> 0 | T31: =IF(T30<'4-AdditionalInputs'!$D$24,'4-AdditionalInputs'!$D$24-T30,0) -> 0 | U31: =IF(U30<'4-AdditionalInputs'!$D$24,'4-AdditionalInputs'!$D$24-U30,0) -> 0 | V31: =IF(V30<'4-AdditionalInputs'!$D$24,'4-AdditionalInputs'!$D$24-V30,0) -> 0 | W31: =IF(W30<'4-AdditionalInputs'!$D$24,'4-AdditionalInputs'!$D$24-W30,0) -> 0 | ... AA31: =IF(AA30<'4-AdditionalInputs'!$D$24,'4-AdditionalInputs'!$D$24-AA30,0) -> 0 | AB31: =SUM(P31:AA31) -> 0
A32: Ending Cash Balance | C32: =SUM(C30+C31) -> 273847.72 | D32: =SUM(D30+D31) -> 330387.3 | E32: =SUM(E30+E31) -> 389106.64 | F32: =SUM(F30+F31) -> 450071.11 | G32: =SUM(G30+G31) -> 513348.07 | H32: =SUM(H30+H31) -> 579006.91 | I32: =SUM(I30+I31) -> 647119.07 | J32: =SUM(J30+J31) -> 717758.15 | ... N32: =SUM(N30+N31) -> 1027134.4 | P32: =SUM(P30+P31) -> 1106509.8 | Q32: =SUM(Q30+Q31) -> 1187838.1 | R32: =SUM(R30+R31) -> 1271158.4 | S32: =SUM(S30+S31) -> 1356510.5 | T32: =SUM(T30+T31) -> 1443935 | U32: =SUM(U30+U31) -> 1533473.5 | V32: =SUM(V30+V31) -> 1625168.2 | W32: =SUM(W30+W31) -> 1719062.3 | ... AA32: =SUM(AA30+AA31) -> 2117524.5
A33: Line of Credit Balance | C33: =IF(C31=0,'6a-CashFlowYear1'!N34-C26,'6a-CashFlowYear1'!N34+C31-C26) -> 0 | D33: =D31+C33-D26 -> 0 | E33: =E31+D33-E26 -> 0 | F33: =F31+E33-F26 -> 0 | G33: =G31+F33-G26 -> 0 | H33: =H31+G33-H26 -> 0 | I33: =I31+H33-I26 -> 0 | J33: =J31+I33-J26 -> 0 | K33: =K31+J33-K26 -> 0 | ... N33: =N31+M33-N26 -> 0 | P33: =IF(P31=0,N33-P26,N33+P31-P26) -> 0 | Q33: =Q31+P33-Q26 -> 0 | R33: =R31+Q33-R26 -> 0 | S33: =S31+R33-S26 -> 0 | T33: =T31+S33-T26 -> 0 | U33: =U31+T33-U26 -> 0 | V33: =V31+U33-V26 -> 0 | W33: =W31+V33-W26 -> 0 | X33: =X31+W33-X26 -> 0 | ... AA33: =AA31+Z33-AA26 -> 0

Sheet 7a-IncomeStatementYear1
B2: Income Statement Year 1
B4: Prepared By: | C4: Company Name:
B5: =IF(ISBLANK(Directions!C10),"Owner",Directions!C10) -> Owner | C5: =IF(ISBLANK(Directions!D10),"Company 1",Directions!D10) -> Company 1
C7: ='2a-PayrollYear1'!F7 -> Month 1 | D7: ='2a-PayrollYear1'!G7 -> Month 2 | E7: ='2a-PayrollYear1'!H7 -> Month 3 | F7: ='2a-PayrollYear1'!I7 -> Month 4 | G7: ='2a-PayrollYear1'!J7 -> Month 5 | H7: ='2a-PayrollYear1'!K7 -> Month 6 | I7: ='2a-PayrollYear1'!L7 -> Month 7 | J7: ='2a-PayrollYear1'!M7 -> Month 8 | ... O7: ='2a-PayrollYear1'!R7 -> Annual Totals
B8: Revenue
B9: ='3a-SalesForecastYear1'!B17 -> Number of Contractors | C9: ='3a-SalesForecastYear1'!C19 -> 9720 | D9: ='3a-SalesForecastYear1'!D19 -> 9720 | E9: ='3a-SalesForecastYear1'!E19 -> 9720 | F9: ='3a-SalesForecastYear1'!F19 -> 18900 | G9: ='3a-SalesForecastYear1'!G19 -> 18900 | H9: ='3a-SalesForecastYear1'!H19 -> 18900 | I9: ='3a-SalesForecastYear1'!I19 -> 28620 | J9: ='3a-SalesForecastYear1'!J19 -> 28620 | ... N9: ='3a-SalesForecastYear1'!N19 -> 57240 | O9: =SUM(C9:N9) -> 323460
B10: ='3a-SalesForecastYear1'!B23 -> Immediate Revenue (70%) | C10: ='3a-SalesForecastYear1'!C25 -> 6804 | D10: ='3a-SalesForecastYear1'!D25 -> 6804 | E10: ='3a-SalesForecastYear1'!E25 -> 6804 | F10: ='3a-SalesForecastYear1'!F25 -> 13230 | G10: ='3a-SalesForecastYear1'!G25 -> 13230 | H10: ='3a-SalesForecastYear1'!H25 -> 13230 | I10: ='3a-SalesForecastYear1'!I25 -> 20034 | J10: ='3a-SalesForecastYear1'!J25 -> 20034 | ... N10: ='3a-SalesForecastYear1'!N25 -> 40068 | O10: =SUM(C10:N10) -> 226422
B11: ='3a-SalesForecastYear1'!B29 -> Deferred Revenue - 1 Month (20%) | C11: ='3a-SalesForecastYear1'!C31 -> 0 | D11: ='3a-SalesForecastYear1'!D31 -> 1944 | E11: ='3a-SalesForecastYear1'!E31 -> 1944 | F11: ='3a-SalesForecastYear1'!F31 -> 1944 | G11: ='3a-SalesForecastYear1'!G31 -> 3780 | H11: ='3a-SalesForecastYear1'!H31 -> 3780 | I11: ='3a-SalesForecastYear1'!I31 -> 3780 | J11: ='3a-SalesForecastYear1'!J31 -> 5724 | ... N11: ='3a-SalesForecastYear1'!N31 -> 9504 | O11: =SUM(C11:N11) -> 53244
B12: ='3a-SalesForecastYear1'!B35 -> Deferred Revenue - 6 Months (10%) | C12: ='3a-SalesForecastYear1'!C37 -> 0 | D12: ='3a-SalesForecastYear1'!D37 -> 0 | E12: ='3a-SalesForecastYear1'!E37 -> 0 | F12: ='3a-SalesForecastYear1'!F37 -> 0 | G12: ='3a-SalesForecastYear1'!G37 -> 0 | H12: ='3a-SalesForecastYear1'!H37 -> 0 | I12: ='3a-SalesForecastYear1'!I37 -> 972 | J12: ='3a-SalesForecastYear1'!J37 -> 972 | ... N12: ='3a-SalesForecastYear1'!N37 -> 1890 | O12: =SUM(C12:N12) -> 8586
B13: ='3a-SalesForecastYear1'!B41 -> Product 5 | C13: ='3a-SalesForecastYear1'!C43 -> 0 | D13: ='3a-SalesForecastYear1'!D43 -> 0 | E13: ='3a-SalesForecastYear1'!E43 -> 0 | F13: ='3a-SalesForecastYear1'!F43 -> 0 | G13: ='3a-SalesForecastYear1'!G43 -> 0 | H13: ='3a-SalesForecastYear1'!H43 -> 0 | I13: ='3a-SalesForecastYear1'!I43 -> 0 | J13: ='3a-SalesForecastYear1'!J43 -> 0 | ... N13: ='3a-SalesForecastYear1'!N43 -> 0 | O13: =SUM(C13:N13) -> 0
B14: ='3a-SalesForecastYear1'!B47 -> Product 6 | C14: ='3a-SalesForecastYear1'!C49 -> 0 | D14: ='3a-SalesForecastYear1'!D49 -> 0 | E14: ='3a-SalesForecastYear1'!E49 -> 0 | F14: ='3a-SalesForecastYear1'!F49 -> 0 | G14: ='3a-SalesForecastYear1'!G49 -> 0 | H14: ='3a-SalesForecastYear1'!H49 -> 0 | I14: ='3a-SalesForecastYear1'!I49 -> 0 | J14: ='3a-SalesForecastYear1'!J49 -> 0 | ... N14: ='3a-SalesForecastYear1'!N49 -> 0 | O14: =SUM(C14:N14) -> 0
B15: Total Revenue | C15: =SUM(C9:C14) -> 16524 | D15: =SUM(D9:D14) -> 18468 | E15: =SUM(E9:E14) -> 18468 | F15: =SUM(F9:F14) -> 34074 | G15: =SUM(G9:G14) -> 35910 | H15: =SUM(H9:H14) -> 35910 | I15: =SUM(I9:I14) -> 53406 | J15: =SUM(J9:J14) -> 55350 | ... N15: =SUM(N9:N14) -> 108702 | O15: =SUM(C15:N15) -> 611712
B16: Cost of Goods Sold
B17: ='3a-SalesForecastYear1'!B17 -> Number of Contractors | C17: ='3a-SalesForecastYear1'!C20 -> 3240 | D17: ='3a-SalesForecastYear1'!D20 -> 3240 | E17: ='3a-SalesForecastYear1'!E20 -> 3240 | F17: ='3a-SalesForecastYear1'!F20 -> 6300 | G17: ='3a-SalesForecastYear1'!G20 -> 6300 | H17: ='3a-SalesForecastYear1'!H20 -> 6300 | I17: ='3a-SalesForecastYear1'!I20 -> 9540 | J17: ='3a-SalesForecastYear1'!J20 -> 9540 | ... N17: ='3a-SalesForecastYear1'!N20 -> 19080 | O17: =SUM(C17:N17) -> 107820
B18: ='3a-SalesForecastYear1'!B23 -> Immediate Revenue (70%) | C18: ='3a-SalesForecastYear1'!C26 -> 3240 | D18: ='3a-SalesForecastYear1'!D26 -> 3240 | E18: ='3a-SalesForecastYear1'!E26 -> 3240 | F18: ='3a-SalesForecastYear1'!F26 -> 6300 | G18: ='3a-SalesForecastYear1'!G26 -> 6300 | H18: ='3a-SalesForecastYear1'!H26 -> 6300 | I18: ='3a-SalesForecastYear1'!I26 -> 9540 | J18: ='3a-SalesForecastYear1'!J26 -> 9540 | ... N18: ='3a-SalesForecastYear1'!N26 -> 19080 | O18: =SUM(C18:N18) -> 107820
B19: ='3a-SalesForecastYear1'!B29 -> Deferred Revenue - 1 Month (20%) | C19: ='3a-SalesForecastYear1'!C32 -> 0 | D19: ='3a-SalesForecastYear1'!D32 -> 0 | E19: ='3a-SalesForecastYear1'!E32 -> 0 | F19: ='3a-SalesForecastYear1'!F32 -> 0 | G19: ='3a-SalesForecastYear1'!G32 -> 0 | H19: ='3a-SalesForecastYear1'!H32 -> 0 | I19: ='3a-SalesForecastYear1'!I32 -> 0 | J19: ='3a-SalesForecastYear1'!J32 -> 0 | ... N19: ='3a-SalesForecastYear1'!N32 -> 0 | O19: =SUM(C19:N19) -> 0
B20: ='3a-SalesForecastYear1'!B35 -> Deferred Revenue - 6 Months (10%) | C20: ='3a-SalesForecastYear1'!C38 -> 0 | D20: ='3a-SalesForecastYear1'!D38 -> 0 | E20: ='3a-SalesForecastYear1'!E38 -> 0 | F20: ='3a-SalesForecastYear1'!F38 -> 0 | G20: ='3a-SalesForecastYear1'!G38 -> 0 | H20: ='3a-SalesForecastYear1'!H38 -> 0 | I20: ='3a-SalesForecastYear1'!I38 -> 0 | J20: ='3a-SalesForecastYear1'!J38 -> 0 | ... N20: ='3a-SalesForecastYear1'!N38 -> 0 | O20: =SUM(C20:N20) -> 0
B21: ='3a-SalesForecastYear1'!B41 -> Product 5 | C21: ='3a-SalesForecastYear1'!C44 -> 0 | D21: ='3a-SalesForecastYear1'!D44 -> 0 | E21: ='3a-SalesForecastYear1'!E44 -> 0 | F21: ='3a-SalesForecastYear1'!F44 -> 0 | G21: ='3a-SalesForecastYear1'!G44 -> 0 | H21: ='3a-SalesForecastYear1'!H44 -> 0 | I21: ='3a-SalesForecastYear1'!I44 -> 0 | J21: ='3a-SalesForecastYear1'!J44 -> 0 | ... N21: ='3a-SalesForecastYear1'!N44 -> 0 | O21: =SUM(C21:N21) -> 0
B22: ='3a-SalesForecastYear1'!B47 -> Product 6 | C22: ='3a-SalesForecastYear1'!C50 -> 0 | D22: ='3a-SalesForecastYear1'!D50 -> 0 | E22: ='3a-SalesForecastYear1'!E50 -> 0 | F22: ='3a-SalesForecastYear1'!F50 -> 0 | G22: ='3a-SalesForecastYear1'!G50 -> 0 | H22: ='3a-SalesForecastYear1'!H50 -> 0 | I22: ='3a-SalesForecastYear1'!I50 -> 0 | J22: ='3a-SalesForecastYear1'!J50 -> 0 | ... N22: ='3a-SalesForecastYear1'!N50 -> 0 | O22: =SUM(C22:N22) -> 0
B23: Total Cost of Goods Sold | C23: =SUM(C17:C22) -> 6480 | D23: =SUM(D17:D22) -> 6480 | E23: =SUM(E17:E22) -> 6480 | F23: =SUM(F17:F22) -> 12600 | G23: =SUM(G17:G22) -> 12600 | H23: =SUM(H17:H22) -> 12600 | I23: =SUM(I17:I22) -> 19080 | J23: =SUM(J17:J22) -> 19080 | ... N23: =SUM(N17:N22) -> 38160 | O23: =SUM(C23:N23) -> 215640
B24: Gross Margin | C24: =C15-C23 -> 10044 | D24: =D15-D23 -> 11988 | E24: =E15-E23 -> 11988 | F24: =F15-F23 -> 21474 | G24: =G15-G23 -> 23310 | H24: =H15-H23 -> 23310 | I24: =I15-I23 -> 34326 | J24: =J15-J23 -> 36270 | ... N24: =N15-N23 -> 70542 | O24: =SUM(C24:N24) -> 396072
B25: Payroll | C25: ='2a-PayrollYear1'!F25 -> 23.625 | D25: ='2a-PayrollYear1'!G25 -> 23.625 | E25: ='2a-PayrollYear1'!H25 -> 23.625 | F25: ='2a-PayrollYear1'!I25 -> 3253.125 | G25: ='2a-PayrollYear1'!J25 -> 4329.625 | H25: ='2a-PayrollYear1'!K25 -> 5406.125 | I25: ='2a-PayrollYear1'!L25 -> 6482.625 | J25: ='2a-PayrollYear1'!M25 -> 6482.625 | ... N25: ='2a-PayrollYear1'!Q25 -> 7200.6505 | O25: =SUM(C25:N25) -> 54827.602
B26: Operating Expenses
B27: ='5a-OpExYear1'!B10 -> Advertising | C27: ='5a-OpExYear1'!C10 -> 0 | D27: ='5a-OpExYear1'!D10 -> 0 | E27: ='5a-OpExYear1'!E10 -> 0 | F27: ='5a-OpExYear1'!F10 -> 0 | G27: ='5a-OpExYear1'!G10 -> 0 | H27: ='5a-OpExYear1'!H10 -> 0 | I27: ='5a-OpExYear1'!I10 -> 0 | ... N27: ='5a-OpExYear1'!N10 -> 0 | O27: =SUM(C27:N27) -> 0
B28: ='5a-OpExYear1'!B11 -> Car and Truck Expenses | C28: ='5a-OpExYear1'!C11 -> 0 | D28: ='5a-OpExYear1'!D11 -> 0 | E28: ='5a-OpExYear1'!E11 -> 0 | F28: ='5a-OpExYear1'!F11 -> 0 | G28: ='5a-OpExYear1'!G11 -> 0 | H28: ='5a-OpExYear1'!H11 -> 0 | I28: ='5a-OpExYear1'!I11 -> 0 | ... N28: ='5a-OpExYear1'!N11 -> 0 | O28: =SUM(C28:N28) -> 0
B29: ='5a-OpExYear1'!B12 -> Closer Commissions (1% of contract value) | C29: ='5a-OpExYear1'!C12 -> 3240 | D29: ='5a-OpExYear1'!D12 -> 3240 | E29: ='5a-OpExYear1'!E12 -> 3240 | F29: ='5a-OpExYear1'!F12 -> 6300 | G29: ='5a-OpExYear1'!G12 -> 6300 | H29: ='5a-OpExYear1'!H12 -> 6300 | I29: ='5a-OpExYear1'!I12 -> 9540 | ... N29: ='5a-OpExYear1'!N12 -> 19080 | O29: =SUM(C29:N29) -> 107820
B30: ='5a-OpExYear1'!B13 -> Contract Labor (Not included in payroll) | C30: ='5a-OpExYear1'!C13 -> 0 | D30: ='5a-OpExYear1'!D13 -> 0 | E30: ='5a-OpExYear1'!E13 -> 0 | F30: ='5a-OpExYear1'!F13 -> 0 | G30: ='5a-OpExYear1'!G13 -> 0 | H30: ='5a-OpExYear1'!H13 -> 0 | I30: ='5a-OpExYear1'!I13 -> 0 | ... N30: ='5a-OpExYear1'!N13 -> 0 | O30: =SUM(C30:N30) -> 0
B31: ='5a-OpExYear1'!B14 -> Insurance (other than health) | C31: ='5a-OpExYear1'!C14 -> 0 | D31: ='5a-OpExYear1'!D14 -> 0 | E31: ='5a-OpExYear1'!E14 -> 0 | F31: ='5a-OpExYear1'!F14 -> 0 | G31: ='5a-OpExYear1'!G14 -> 0 | H31: ='5a-OpExYear1'!H14 -> 0 | I31: ='5a-OpExYear1'!I14 -> 0 | ... N31: ='5a-OpExYear1'!N14 -> 0 | O31: =SUM(C31:N31) -> 0
B32: ='5a-OpExYear1'!B15 -> Legal and Professional Services (Company Setup) | C32: ='5a-OpExYear1'!C15 -> 2000 | D32: ='5a-OpExYear1'!D15 -> 0 | E32: ='5a-OpExYear1'!E15 -> 0 | F32: ='5a-OpExYear1'!F15 -> 0 | G32: ='5a-OpExYear1'!G15 -> 0 | H32: ='5a-OpExYear1'!H15 -> 0 | I32: ='5a-OpExYear1'!I15 -> 0 | ... N32: ='5a-OpExYear1'!N15 -> 0 | O32: =SUM(C32:N32) -> 2000
B33: ='5a-OpExYear1'!B16 -> Licenses | C33: ='5a-OpExYear1'!C16 -> 0 | D33: ='5a-OpExYear1'!D16 -> 0 | E33: ='5a-OpExYear1'!E16 -> 0 | F33: ='5a-OpExYear1'!F16 -> 0 | G33: ='5a-OpExYear1'!G16 -> 0 | H33: ='5a-OpExYear1'!H16 -> 0 | I33: ='5a-OpExYear1'!I16 -> 0 | ... N33: ='5a-OpExYear1'!N16 -> 0 | O33: =SUM(C33:N33) -> 0
B34: ='5a-OpExYear1'!B17 -> Software & Tools (CRM, dialing, calendaring) | C34: ='5a-OpExYear1'!C17 -> 1000 | D34: ='5a-OpExYear1'!D17 -> 1000 | E34: ='5a-OpExYear1'!E17 -> 1000 | F34: ='5a-OpExYear1'!F17 -> 1000 | G34: ='5a-OpExYear1'!G17 -> 1000 | H34: ='5a-OpExYear1'!H17 -> 1000 | I34: ='5a-OpExYear1'!I17 -> 1000 | ... N34: ='5a-OpExYear1'!N17 -> 1000 | O34: =SUM(C34:N34) -> 12000
B35: ='5a-OpExYear1'!B18 -> Rent or Lease -- Vehicles, Machinery, Equipment | C35: ='5a-OpExYear1'!C18 -> 0 | D35: ='5a-OpExYear1'!D18 -> 0 | E35: ='5a-OpExYear1'!E18 -> 0 | F35: ='5a-OpExYear1'!F18 -> 0 | G35: ='5a-OpExYear1'!G18 -> 0 | H35: ='5a-OpExYear1'!H18 -> 0 | I35: ='5a-OpExYear1'!I18 -> 0 | ... N35: ='5a-OpExYear1'!N18 -> 0 | O35: =SUM(C35:N35) -> 0
B36: ='5a-OpExYear1'!B19 -> Rent or Lease -- Other Business Property | C36: ='5a-OpExYear1'!C19 -> 0 | D36: ='5a-OpExYear1'!D19 -> 0 | E36: ='5a-OpExYear1'!E19 -> 0 | F36: ='5a-OpExYear1'!F19 -> 0 | G36: ='5a-OpExYear1'!G19 -> 0 | H36: ='5a-OpExYear1'!H19 -> 0 | I36: ='5a-OpExYear1'!I19 -> 0 | ... N36: ='5a-OpExYear1'!N19 -> 0 | O36: =SUM(C36:N36) -> 0
B37: ='5a-OpExYear1'!B20 -> Repairs and Maintenance | C37: ='5a-OpExYear1'!C20 -> 0 | D37: ='5a-OpExYear1'!D20 -> 0 | E37: ='5a-OpExYear1'!E20 -> 0 | F37: ='5a-OpExYear1'!F20 -> 0 | G37: ='5a-OpExYear1'!G20 -> 0 | H37: ='5a-OpExYear1'!H20 -> 0 | I37: ='5a-OpExYear1'!I20 -> 0 | ... N37: ='5a-OpExYear1'!N20 -> 0 | O37: =SUM(C37:N37) -> 0
B38: ='5a-OpExYear1'!B21 -> Supplies | C38: ='5a-OpExYear1'!C21 -> 0 | D38: ='5a-OpExYear1'!D21 -> 0 | E38: ='5a-OpExYear1'!E21 -> 0 | F38: ='5a-OpExYear1'!F21 -> 0 | G38: ='5a-OpExYear1'!G21 -> 0 | H38: ='5a-OpExYear1'!H21 -> 0 | I38: ='5a-OpExYear1'!I21 -> 0 | ... N38: ='5a-OpExYear1'!N21 -> 0 | O38: =SUM(C38:N38) -> 0
... B41: ='5a-OpExYear1'!B24 -> Miscellaneous | C41: ='5a-OpExYear1'!C24 -> 0 | D41: ='5a-OpExYear1'!D24 -> 0 | E41: ='5a-OpExYear1'!E24 -> 0 | F41: ='5a-OpExYear1'!F24 -> 0 | G41: ='5a-OpExYear1'!G24 -> 0 | H41: ='5a-OpExYear1'!H24 -> 0 | I41: ='5a-OpExYear1'!I24 -> 0 | ... N41: ='5a-OpExYear1'!N24 -> 0 | O41: =SUM(C41:N41) -> 0
B42: Other Expense 1
B43: Other Expense 2
B44: Total Operating Expenses | C44: =SUM(C27:C43) -> 6240 | D44: =SUM(D27:D43) -> 4240 | E44: =SUM(E27:E43) -> 4240 | F44: =SUM(F27:F43) -> 7300 | G44: =SUM(G27:G43) -> 7300 | H44: =SUM(H27:H43) -> 7300 | I44: =SUM(I27:I43) -> 10540 | J44: =SUM(J27:J43) -> 10540 | ... N44: =SUM(N27:N43) -> 20080 | O44: =SUM(C44:N44) -> 121820
B45: Income (Before Other Expenses) | C45: =C24-C25-C44 -> 3780.375 | D45: =+D24-D25-D44 -> 7724.375 | E45: =+E24-E25-E44 -> 7724.375 | F45: =+F24-F25-F44 -> 10920.875 | G45: =+G24-G25-G44 -> 11680.375 | H45: =+H24-H25-H44 -> 10603.875 | I45: =+I24-I25-I44 -> 17303.375 | J45: =+J24-J25-J44 -> 19247.375 | K45: =+K24-K25-K44 -> 24955.35 | ... N45: =+N24-N25-N44 -> 43261.349 | O45: =SUM(C45:N45) -> 219424.4
B46: Other Expenses
B47: Amortized Start-up Expenses | C47: =+'Amortization&Depreciation'!C138+'Amortization&Depreciation'!C149 -> 0 | D47: =+'Amortization&Depreciation'!D138+'Amortization&Depreciation'!D149 -> 0 | E47: =+'Amortization&Depreciation'!E138+'Amortization&Depreciation'!E149 -> 0 | F47: =+'Amortization&Depreciation'!F138+'Amortization&Depreciation'!F149 -> 0 | G47: =+'Amortization&Depreciation'!G138+'Amortization&Depreciation'!G149 -> 0 | H47: =+'Amortization&Depreciation'!H138+'Amortization&Depreciation'!H149 -> 0 | I47: =+'Amortization&Depreciation'!I138+'Amortization&Depreciation'!I149 -> 0 | J47: =+'Amortization&Depreciation'!J138+'Amortization&Depreciation'!J149 -> 0 | ... N47: =+'Amortization&Depreciation'!N138+'Amortization&Depreciation'!N149 -> 0 | O47: =SUM(C47:N47) -> 0
B48: Depreciation | C48: ='Amortization&Depreciation'!C119 -> 0 | D48: =+'Amortization&Depreciation'!D119 -> 0 | E48: =+'Amortization&Depreciation'!E119 -> 0 | F48: =+'Amortization&Depreciation'!F119 -> 0 | G48: =+'Amortization&Depreciation'!G119 -> 0 | H48: =+'Amortization&Depreciation'!H119 -> 0 | I48: =+'Amortization&Depreciation'!I119 -> 0 | J48: =+'Amortization&Depreciation'!J119 -> 0 | K48: =+'Amortization&Depreciation'!K119 -> 0 | ... N48: =+'Amortization&Depreciation'!N119 -> 0 | O48: =SUM(C48:N48) -> 0
B49: Interest
B50: Commercial Loan | C50: =+'Amortization&Depreciation'!C15 -> 0 | D50: =+'Amortization&Depreciation'!D15 -> 0 | E50: =+'Amortization&Depreciation'!E15 -> 0 | F50: =+'Amortization&Depreciation'!F15 -> 0 | G50: =+'Amortization&Depreciation'!G15 -> 0 | H50: =+'Amortization&Depreciation'!H15 -> 0 | I50: =+'Amortization&Depreciation'!I15 -> 0 | J50: =+'Amortization&Depreciation'!J15 -> 0 | ... N50: =+'Amortization&Depreciation'!N15 -> 0 | O50: =SUM(C50:N50) -> 0
B51: Commercial Mortgage | C51: =+'Amortization&Depreciation'!C35 -> 0 | D51: =+'Amortization&Depreciation'!D35 -> 0 | E51: =+'Amortization&Depreciation'!E35 -> 0 | F51: =+'Amortization&Depreciation'!F35 -> 0 | G51: =+'Amortization&Depreciation'!G35 -> 0 | H51: =+'Amortization&Depreciation'!H35 -> 0 | I51: =+'Amortization&Depreciation'!I35 -> 0 | J51: =+'Amortization&Depreciation'!J35 -> 0 | ... N51: =+'Amortization&Depreciation'!N35 -> 0 | O51: =SUM(C51:N51) -> 0
B52: Credit Card Debt | C52: =+'Amortization&Depreciation'!C55 -> 0 | D52: =+'Amortization&Depreciation'!D55 -> 0 | E52: =+'Amortization&Depreciation'!E55 -> 0 | F52: =+'Amortization&Depreciation'!F55 -> 0 | G52: =+'Amortization&Depreciation'!G55 -> 0 | H52: =+'Amortization&Depreciation'!H55 -> 0 | I52: =+'Amortization&Depreciation'!I55 -> 0 | J52: =+'Amortization&Depreciation'!J55 -> 0 | ... N52: =+'Amortization&Depreciation'!N55 -> 0 | O52: =SUM(C52:N52) -> 0
B53: Vehicle Loans | C53: =+'Amortization&Depreciation'!C75 -> 0 | D53: =+'Amortization&Depreciation'!D75 -> 0 | E53: =+'Amortization&Depreciation'!E75 -> 0 | F53: =+'Amortization&Depreciation'!F75 -> 0 | G53: =+'Amortization&Depreciation'!G75 -> 0 | H53: =+'Amortization&Depreciation'!H75 -> 0 | I53: =+'Amortization&Depreciation'!I75 -> 0 | J53: =+'Amortization&Depreciation'!J75 -> 0 | ... N53: =+'Amortization&Depreciation'!N75 -> 0 | O53: =SUM(C53:N53) -> 0
B54: Other Bank Debt | C54: =+'Amortization&Depreciation'!C95 -> 0 | D54: =+'Amortization&Depreciation'!D95 -> 0 | E54: =+'Amortization&Depreciation'!E95 -> 0 | F54: =+'Amortization&Depreciation'!F95 -> 0 | G54: =+'Amortization&Depreciation'!G95 -> 0 | H54: =+'Amortization&Depreciation'!H95 -> 0 | I54: =+'Amortization&Depreciation'!I95 -> 0 | J54: =+'Amortization&Depreciation'!J95 -> 0 | ... N54: =+'Amortization&Depreciation'!N95 -> 0 | O54: =SUM(C54:N54) -> 0
B55: Line of Credit | C55: ='6a-CashFlowYear1'!C26 -> 0 | D55: =+'6a-CashFlowYear1'!D26 -> 0 | E55: =+'6a-CashFlowYear1'!E26 -> 0 | F55: =+'6a-CashFlowYear1'!F26 -> 0 | G55: =+'6a-CashFlowYear1'!G26 -> 0 | H55: =+'6a-CashFlowYear1'!H26 -> 0 | I55: =+'6a-CashFlowYear1'!I26 -> 0 | J55: =+'6a-CashFlowYear1'!J26 -> 0 | K55: =+'6a-CashFlowYear1'!K26 -> 0 | ... N55: =+'6a-CashFlowYear1'!N26 -> 0 | O55: =SUM(C55:N55) -> 0
B56: Bad Debt Expense | C56: =+'3a-SalesForecastYear1'!C53*'4-AdditionalInputs'!$C$12 -> 0 | D56: =+'3a-SalesForecastYear1'!D53*'4-AdditionalInputs'!$C$12 -> 0 | E56: =+'3a-SalesForecastYear1'!E53*'4-AdditionalInputs'!$C$12 -> 0 | F56: =+'3a-SalesForecastYear1'!F53*'4-AdditionalInputs'!$C$12 -> 0 | G56: =+'3a-SalesForecastYear1'!G53*'4-AdditionalInputs'!$C$12 -> 0 | H56: =+'3a-SalesForecastYear1'!H53*'4-AdditionalInputs'!$C$12 -> 0 | I56: =+'3a-SalesForecastYear1'!I53*'4-AdditionalInputs'!$C$12 -> 0 | J56: =+'3a-SalesForecastYear1'!J53*'4-AdditionalInputs'!$C$12 -> 0 | ... N56: =+'3a-SalesForecastYear1'!N53*'4-AdditionalInputs'!$C$12 -> 0 | O56: =SUM(C56:N56) -> 0
B57: Total Other Expenses | C57: =SUM(C47:C56) -> 0 | D57: =SUM(D47:D56) -> 0 | E57: =SUM(E47:E56) -> 0 | F57: =SUM(F47:F56) -> 0 | G57: =SUM(G47:G56) -> 0 | H57: =SUM(H47:H56) -> 0 | I57: =SUM(I47:I56) -> 0 | J57: =SUM(J47:J56) -> 0 | ... N57: =SUM(N47:N56) -> 0 | O57: =SUM(C57:N57) -> 0
B58: Net Income Before Income Tax | C58: =C24-C25-C44-C57 -> 3780.375 | D58: =D24-D25-D44-D57 -> 7724.375 | E58: =E24-E25-E44-E57 -> 7724.375 | F58: =F24-F25-F44-F57 -> 10920.875 | G58: =G24-G25-G44-G57 -> 11680.375 | H58: =H24-H25-H44-H57 -> 10603.875 | I58: =I24-I25-I44-I57 -> 17303.375 | J58: =J24-J25-J44-J57 -> 19247.375 | ... N58: =N24-N25-N44-N57 -> 43261.349 | O58: =SUM(C58:N58) -> 219424.4
B59: Income Tax | C59: =IF(C65>0,C64*'4-AdditionalInputs'!$C$39,0) -> 0 | D59: =+IF(D65>0,IF(C65<0,(D64-ABS(C65))*'4-AdditionalInputs'!$C$39,'7a-IncomeStatementYear1'!D64*'4-AdditionalInputs'!$C$39),IF('7a-IncomeStatementYear1'!C65>0,-'7a-IncomeStatementYear1'!C65*'4-AdditionalInputs'!$C$39,0)) -> 0 | E59: =+IF(E65>0,IF(D65<0,(E64-ABS(D65))*'4-AdditionalInputs'!$C$39,'7a-IncomeStatementYear1'!E64*'4-AdditionalInputs'!$C$39),IF('7a-IncomeStatementYear1'!D65>0,-'7a-IncomeStatementYear1'!D65*'4-AdditionalInputs'!$C$39,0)) -> 0 | F59: =+IF(F65>0,IF(E65<0,(F64-ABS(E65))*'4-AdditionalInputs'!$C$39,'7a-IncomeStatementYear1'!F64*'4-AdditionalInputs'!$C$39),IF('7a-IncomeStatementYear1'!E65>0,-'7a-IncomeStatementYear1'!E65*'4-AdditionalInputs'!$C$39,0)) -> 0 | G59: =+IF(G65>0,IF(F65<0,(G64-ABS(F65))*'4-AdditionalInputs'!$C$39,'7a-IncomeStatementYear1'!G64*'4-AdditionalInputs'!$C$39),IF('7a-IncomeStatementYear1'!F65>0,-'7a-IncomeStatementYear1'!F65*'4-AdditionalInputs'!$C$39,0)) -> 0 | H59: =+IF(H65>0,IF(G65<0,(H64-ABS(G65))*'4-AdditionalInputs'!$C$39,'7a-IncomeStatementYear1'!H64*'4-AdditionalInputs'!$C$39),IF('7a-IncomeStatementYear1'!G65>0,-'7a-IncomeStatementYear1'!G65*'4-AdditionalInputs'!$C$39,0)) -> 0 | I59: =+IF(I65>0,IF(H65<0,(I64-ABS(H65))*'4-AdditionalInputs'!$C$39,'7a-IncomeStatementYear1'!I64*'4-AdditionalInputs'!$C$39),IF('7a-IncomeStatementYear1'!H65>0,-'7a-IncomeStatementYear1'!H65*'4-AdditionalInputs'!$C$39,0)) -> 0 | J59: =+IF(J65>0,IF(I65<0,(J64-ABS(I65))*'4-AdditionalInputs'!$C$39,'7a-IncomeStatementYear1'!J64*'4-AdditionalInputs'!$C$39),IF('7a-IncomeStatementYear1'!I65>0,-'7a-IncomeStatementYear1'!I65*'4-AdditionalInputs'!$C$39,0)) -> 0 | K59: =+IF(K65>0,IF(J65<0,(K64-ABS(J65))*'4-AdditionalInputs'!$C$39,'7a-IncomeStatementYear1'!K64*'4-AdditionalInputs'!$C$39),IF('7a-IncomeStatementYear1'!J65>0,-'7a-IncomeStatementYear1'!J65*'4-AdditionalInputs'!$C$39,0)) -> 0 | ... N59: =+IF(N65>0,IF(M65<0,(N64-ABS(M65))*'4-AdditionalInputs'!$C$39,'7a-IncomeStatementYear1'!N64*'4-AdditionalInputs'!$C$39),IF('7a-IncomeStatementYear1'!M65>0,-'7a-IncomeStatementYear1'!M65*'4-AdditionalInputs'!$C$39,0)) -> 0 | O59: =SUM(C59:N59) -> 0
B60: Net Profit/Loss | C60: =C58-C59 -> 3780.375 | D60: =D58-D59 -> 7724.375 | E60: =E58-E59 -> 7724.375 | F60: =F58-F59 -> 10920.875 | G60: =G58-G59 -> 11680.375 | H60: =H58-H59 -> 10603.875 | I60: =I58-I59 -> 17303.375 | J60: =J58-J59 -> 19247.375 | ... N60: =N58-N59 -> 43261.349 | O60: =SUM(C60:N60) -> 219424.4
B63: Income Tax Calculations
B64: Monthly Taxable Income | C64: =C45-C48-C50-C51-C52-C53-C54-C55-C56 -> 3780.375 | D64: =D45-D48-D50-D51-D52-D53-D54-D55-D56 -> 7724.375 | E64: =E45-E48-E50-E51-E52-E53-E54-E55-E56 -> 7724.375 | F64: =F45-F48-F50-F51-F52-F53-F54-F55-F56 -> 10920.875 | G64: =G45-G48-G50-G51-G52-G53-G54-G55-G56 -> 11680.375 | H64: =H45-H48-H50-H51-H52-H53-H54-H55-H56 -> 10603.875 | I64: =I45-I48-I50-I51-I52-I53-I54-I55-I56 -> 17303.375 | J64: =J45-J48-J50-J51-J52-J53-J54-J55-J56 -> 19247.375 | ... N64: =N45-N48-N50-N51-N52-N53-N54-N55-N56 -> 43261.349
B65: Cumulative Taxable Income | C65: =C64 -> 3780.375 | D65: =C65+D64 -> 11504.75 | E65: =D65+E64 -> 19229.125 | F65: =E65+F64 -> 30150 | G65: =F65+G64 -> 41830.375 | H65: =+G65+H64 -> 52434.25 | I65: =+H65+I64 -> 69737.625 | J65: =+I65+J64 -> 88985 | K65: =+J65+K64 -> 113940.35 | L65: =+K65+L64 -> 141649.7 | M65: =+L65+M64 -> 176163.05 | N65: =+M65+N64 -> 219424.4

Sheet 7b-IncomeStatementYrs1-3
B2: Income Statement Years 1-3
B4: Prepared By: | C4: Company Name:
B5: =IF(ISBLANK(Directions!C10),"Owner",Directions!C10) -> Owner | C5: =IF(ISBLANK(Directions!D10),"Company 1",Directions!D10) -> Company 1
B7: Revenue | C7: =IF(Directions!F10>0,Directions!F10,"First Year") -> First Year | E7: =IF(Directions!F10>0,Directions!F10+1,"Second Year") -> Second Year | G7: =IF(Directions!F10>0,Directions!F10+2,"Third Year") -> Third Year
B8: ='3a-SalesForecastYear1'!B17 -> Number of Contractors | C8: ='3b-SalesForecastYrs1-3'!B13 -> 323460 | E8: ='3b-SalesForecastYrs1-3'!O13 -> 812351.77 | G8: ='3b-SalesForecastYrs1-3'!AD13 -> 1062687.4
B9: ='3a-SalesForecastYear1'!B23 -> Immediate Revenue (70%) | C9: ='3b-SalesForecastYrs1-3'!B19 -> 226422 | E9: ='3b-SalesForecastYrs1-3'!O19 -> 568646.24 | G9: ='3b-SalesForecastYrs1-3'!AD19 -> 743881.21
B10: ='3a-SalesForecastYear1'!B29 -> Deferred Revenue - 1 Month (20%) | C10: ='3b-SalesForecastYrs1-3'!B25 -> 53244 | E10: ='3b-SalesForecastYrs1-3'!O25 -> 134881.05 | G10: ='3b-SalesForecastYrs1-3'!AD25 -> 176446.22
B11: ='3a-SalesForecastYear1'!B35 -> Deferred Revenue - 6 Months (10%) | C11: ='3b-SalesForecastYrs1-3'!B31 -> 8586 | E11: ='3b-SalesForecastYrs1-3'!O31 -> 26822.936 | G11: ='3b-SalesForecastYrs1-3'!AD31 -> 35088.736
B12: ='3a-SalesForecastYear1'!B41 -> Product 5 | C12: ='3b-SalesForecastYrs1-3'!B37 -> 0 | E12: ='3b-SalesForecastYrs1-3'!O37 -> 0 | G12: ='3b-SalesForecastYrs1-3'!AD37 -> 0
B13: ='3a-SalesForecastYear1'!B47 -> Product 6 | C13: ='3b-SalesForecastYrs1-3'!B43 -> 0 | E13: ='3b-SalesForecastYrs1-3'!O43 -> 0 | G13: ='3b-SalesForecastYrs1-3'!AD43 -> 0
B14: Total Revenue | C14: =SUM(C8:C13) -> 611712 | D14: 1 | E14: =SUM(E8:E13) -> 1542702 | F14: 1 | G14: =SUM(G8:G13) -> 2018103.6 | H14: 1
B15: Cost of Goods Sold
B16: ='3a-SalesForecastYear1'!B17 -> Number of Contractors | C16: ='3b-SalesForecastYrs1-3'!B14 -> 107820 | E16: ='3b-SalesForecastYrs1-3'!O14 -> 270783.92 | G16: ='3b-SalesForecastYrs1-3'!AD14 -> 354229.15
B17: ='3a-SalesForecastYear1'!B23 -> Immediate Revenue (70%) | C17: ='3b-SalesForecastYrs1-3'!B20 -> 107820 | E17: ='3b-SalesForecastYrs1-3'!O20 -> 270783.92 | G17: ='3b-SalesForecastYrs1-3'!AD20 -> 354229.15
B18: ='3a-SalesForecastYear1'!B29 -> Deferred Revenue - 1 Month (20%) | C18: ='3b-SalesForecastYrs1-3'!B26 -> 0 | E18: ='3b-SalesForecastYrs1-3'!O26 -> 0 | G18: ='3b-SalesForecastYrs1-3'!AD26 -> 0
B19: ='3a-SalesForecastYear1'!B35 -> Deferred Revenue - 6 Months (10%) | C19: ='3b-SalesForecastYrs1-3'!B32 -> 0 | E19: ='3b-SalesForecastYrs1-3'!O32 -> 0 | G19: ='3b-SalesForecastYrs1-3'!AD32 -> 0
B20: ='3a-SalesForecastYear1'!B41 -> Product 5 | C20: ='3b-SalesForecastYrs1-3'!B38 -> 0 | E20: ='3b-SalesForecastYrs1-3'!O38 -> 0 | G20: ='3b-SalesForecastYrs1-3'!AD38 -> 0
B21: ='3a-SalesForecastYear1'!B47 -> Product 6 | C21: ='3b-SalesForecastYrs1-3'!B44 -> 0 | E21: ='3b-SalesForecastYrs1-3'!O44 -> 0 | G21: ='3b-SalesForecastYrs1-3'!AD44 -> 0
B22: Total Cost of Goods Sold | C22: =SUM(C16:C21) -> 215640 | D22: =IF(C14=0,0,C22/C14) -> 0.35251883 | E22: =SUM(E16:E21) -> 541567.85 | F22: =IF(E14=0,0,E22/E14) -> 0.3510515 | G22: =SUM(G16:G21) -> 708458.29 | H22: =IF(G14=0,0,G22/G14) -> 0.3510515
B23: Gross Margin | C23: =C14-C22 -> 396072 | D23: =IF(C14=0,0,C23/C14) -> 0.64748117 | E23: =E14-E22 -> 1001134.1 | F23: =IF(E14=0,0,E23/E14) -> 0.6489485 | G23: =G14-G22 -> 1309645.3 | H23: =IF(G14=0,0,G23/G14) -> 0.6489485
B24: Payroll | C24: ='2a-PayrollYear1'!R25 -> 54827.602 | E24: ='2b-PayrollYrs1-3'!E26 -> 65793.122 | G24: ='2b-PayrollYrs1-3'!G26 -> 85531.059
B25: Operating Expenses
B26: ='5a-OpExYear1'!B10 -> Advertising | C26: ='5b-OpExYrs1-3'!C8 -> 0 | E26: ='5b-OpExYrs1-3'!E8 -> 0 | G26: ='5b-OpExYrs1-3'!G8 -> 0
B27: ='5a-OpExYear1'!B11 -> Car and Truck Expenses | C27: ='5b-OpExYrs1-3'!C9 -> 0 | E27: ='5b-OpExYrs1-3'!E9 -> 0 | G27: ='5b-OpExYrs1-3'!G9 -> 0
B28: ='5a-OpExYear1'!B12 -> Closer Commissions (1% of contract value) | C28: ='5b-OpExYrs1-3'!C10 -> 107820 | E28: ='5b-OpExYrs1-3'!E10 -> 113211 | G28: ='5b-OpExYrs1-3'!G10 -> 118871.55
B29: ='5a-OpExYear1'!B13 -> Contract Labor (Not included in payroll) | C29: ='5b-OpExYrs1-3'!C11 -> 0 | E29: ='5b-OpExYrs1-3'!E11 -> 0 | G29: ='5b-OpExYrs1-3'!G11 -> 0
B30: ='5a-OpExYear1'!B14 -> Insurance (other than health) | C30: ='5b-OpExYrs1-3'!C12 -> 0 | E30: ='5b-OpExYrs1-3'!E12 -> 0 | G30: ='5b-OpExYrs1-3'!G12 -> 0
B31: ='5a-OpExYear1'!B15 -> Legal and Professional Services (Company Setup) | C31: ='5b-OpExYrs1-3'!C13 -> 2000 | E31: ='5b-OpExYrs1-3'!E13 -> 2060 | G31: ='5b-OpExYrs1-3'!G13 -> 2121.8
B32: ='5a-OpExYear1'!B16 -> Licenses | C32: ='5b-OpExYrs1-3'!C14 -> 0 | E32: ='5b-OpExYrs1-3'!E14 -> 0 | G32: ='5b-OpExYrs1-3'!G14 -> 0
B33: ='5a-OpExYear1'!B17 -> Software & Tools (CRM, dialing, calendaring) | C33: ='5b-OpExYrs1-3'!C15 -> 12000 | E33: ='5b-OpExYrs1-3'!E15 -> 12360 | G33: ='5b-OpExYrs1-3'!G15 -> 12730.8
B34: ='5a-OpExYear1'!B18 -> Rent or Lease -- Vehicles, Machinery, Equipment | C34: ='5b-OpExYrs1-3'!C16 -> 0 | E34: ='5b-OpExYrs1-3'!E16 -> 0 | G34: ='5b-OpExYrs1-3'!G16 -> 0
B35: ='5a-OpExYear1'!B19 -> Rent or Lease -- Other Business Property | C35: ='5b-OpExYrs1-3'!C17 -> 0 | E35: ='5b-OpExYrs1-3'!E17 -> 0 | G35: ='5b-OpExYrs1-3'!G17 -> 0
B36: ='5a-OpExYear1'!B20 -> Repairs and Maintenance | C36: ='5b-OpExYrs1-3'!C18 -> 0 | E36: ='5b-OpExYrs1-3'!E18 -> 0 | G36: ='5b-OpExYrs1-3'!G18 -> 0
B37: ='5a-OpExYear1'!B21 -> Supplies | C37: ='5b-OpExYrs1-3'!C19 -> 0 | E37: ='5b-OpExYrs1-3'!E19 -> 0 | G37: ='5b-OpExYrs1-3'!G19 -> 0
... B40: ='5a-OpExYear1'!B24 -> Miscellaneous | C40: ='5b-OpExYrs1-3'!C22 -> 0 | E40: ='5b-OpExYrs1-3'!E22 -> 0 | G40: ='5b-OpExYrs1-3'!G22 -> 0
B41: Other Expense 1
B42: Other Expense 2
B43: Total Operating Expenses | C43: =SUM(C26:C42) -> 121820 | D43: =IF(C14=0,0,C43/C14) -> 0.199146 | E43: =SUM(E26:E42) -> 127631 | F43: =IF(E14=0,0,E43/E14) -> 0.082732116 | G43: =SUM(G26:G42) -> 133724.15 | H43: =IF(G14=0,0,G43/G14) -> 0.066262282
B44: Income (Before Other Expenses) | C44: =C23-C24-C43 -> 219424.4 | D44: =IF(C14=0,0,C44/C14) -> 0.3587054 | E44: =E23-E24-E43 -> 807710.03 | F44: =IF(E14=0,0,E44/E14) -> 0.52356841 | G44: =G23-G24-G43 -> 1090390.1 | H44: =IF(G14=0,0,G44/G14) -> 0.54030432
B45: Other Expenses
B46: Amortized Start-up Expenses | C46: =+'Amortization&Depreciation'!O138+'Amortization&Depreciation'!O149 -> 0 | E46: =+'Amortization&Depreciation'!O141+'Amortization&Depreciation'!O152 -> 0 | G46: =+'Amortization&Depreciation'!O144+'Amortization&Depreciation'!O155 -> 0
B47: Depreciation | C47: =+'Amortization&Depreciation'!O119 -> 0 | E47: =+'Amortization&Depreciation'!O123 -> 0 | G47: =+'Amortization&Depreciation'!O127 -> 0
B48: Interest
B49: Commercial Loan | C49: ='5b-OpExYrs1-3'!C28 -> 0 | E49: ='5b-OpExYrs1-3'!E28 -> 0 | G49: ='5b-OpExYrs1-3'!G28 -> 0
B50: Commercial Mortgage | C50: ='5b-OpExYrs1-3'!C29 -> 0 | E50: ='5b-OpExYrs1-3'!E29 -> 0 | G50: ='5b-OpExYrs1-3'!G29 -> 0
B51: Credit Card Debt | C51: ='5b-OpExYrs1-3'!C30 -> 0 | E51: ='5b-OpExYrs1-3'!E30 -> 0 | G51: ='5b-OpExYrs1-3'!G30 -> 0
B52: Vehicle Loans | C52: ='5b-OpExYrs1-3'!C31 -> 0 | E52: ='5b-OpExYrs1-3'!E31 -> 0 | G52: ='5b-OpExYrs1-3'!G31 -> 0
B53: Other Bank Debt | C53: ='5b-OpExYrs1-3'!C32 -> 0 | E53: ='5b-OpExYrs1-3'!E32 -> 0 | G53: ='5b-OpExYrs1-3'!G32 -> 0
B54: Line of Credit | C54: =+'6a-CashFlowYear1'!O26 -> 0 | E54: ='6b-CashFlowYrs1-3'!O25 -> 0 | G54: =+'6b-CashFlowYrs1-3'!AB25 -> 0
B55: Bad Debt Expense | C55: =+'3a-SalesForecastYear1'!O53*'4-AdditionalInputs'!$C$12 -> 0 | E55: ='3b-SalesForecastYrs1-3'!O47*'4-AdditionalInputs'!$D$12 -> 0 | G55: ='3b-SalesForecastYrs1-3'!AD47*'4-AdditionalInputs'!$E$12 -> 0
B56: Total Other Expenses | C56: =SUM(C46:C55) -> 0 | D56: =IF(C14=0,0,C56/C14) -> 0 | E56: =SUM(E46:E55) -> 0 | F56: =IF(E14=0,0,E56/E14) -> 0 | G56: =SUM(G46:G55) -> 0 | H56: =IF(G14=0,0,G56/G14) -> 0
B57: Net Income Before Income Tax | C57: =C23-C24-C43-C56 -> 219424.4 | D57: =IF(C14=0,0,C57/C14) -> 0.3587054 | E57: =E23-E24-E43-E56 -> 807710.03 | F57: =IF(E14=0,0,E57/E14) -> 0.52356841 | G57: =G23-G24-G43-G56 -> 1090390.1 | H57: =IF(G14=0,0,G57/G14) -> 0.54030432
B58: Income Tax | C58: =+'7a-IncomeStatementYear1'!O59 -> 0 | E58: =O65 -> 0 | G58: =O69 -> 0
B59: Net Income/Loss | C59: =C57-C58 -> 219424.4 | D59: =IF(C14=0,0,C59/C14) -> 0.3587054 | E59: =E57-E58 -> 807710.03 | F59: =IF(E14=0,0,E59/E14) -> 0.52356841 | G59: =G57-G58 -> 1090390.1 | H59: =IF(G14=0,0,G59/G14) -> 0.54030432
B62: Income Tax Calculations | C62: Month 1 | D62: Month 2 | E62: Month 3 | F62: Month 4 | G62: Month 5 | H62: Month 6 | I62: Month 7 | J62: Month 8 | K62: Month 9 | L62: Month 10 | M62: Month 11 | N62: Month 12 | O62: Total
B63: Taxable Amount Year 2 | C63: ='3b-SalesForecastYrs1-3'!C49-('2b-PayrollYrs1-3'!$E$26/12)-'6b-CashFlowYrs1-3'!C19-'Amortization&Depreciation'!C123-'Amortization&Depreciation'!C19-'Amortization&Depreciation'!C39-'Amortization&Depreciation'!C59-'Amortization&Depreciation'!C79-'Amortization&Depreciation'!C99-'6b-CashFlowYrs1-3'!C25-$E$55/12 -> 54423.323 | D63: ='3b-SalesForecastYrs1-3'!D49-('2b-PayrollYrs1-3'!$E$26/12)-'6b-CashFlowYrs1-3'!D19-'Amortization&Depreciation'!D123-'Amortization&Depreciation'!D19-'Amortization&Depreciation'!D39-'Amortization&Depreciation'!D59-'Amortization&Depreciation'!D79-'Amortization&Depreciation'!D99-'6b-CashFlowYrs1-3'!D25-$E$55/12 -> 56539.583 | E63: ='3b-SalesForecastYrs1-3'!E49-('2b-PayrollYrs1-3'!$E$26/12)-'6b-CashFlowYrs1-3'!E19-'Amortization&Depreciation'!E123-'Amortization&Depreciation'!E19-'Amortization&Depreciation'!E39-'Amortization&Depreciation'!E59-'Amortization&Depreciation'!E79-'Amortization&Depreciation'!E99-'6b-CashFlowYrs1-3'!E25-$E$55/12 -> 58719.331 | F63: ='3b-SalesForecastYrs1-3'!F49-('2b-PayrollYrs1-3'!$E$26/12)-'6b-CashFlowYrs1-3'!F19-'Amortization&Depreciation'!F123-'Amortization&Depreciation'!F19-'Amortization&Depreciation'!F39-'Amortization&Depreciation'!F59-'Amortization&Depreciation'!F79-'Amortization&Depreciation'!F99-'6b-CashFlowYrs1-3'!F25-$E$55/12 -> 60964.471 | G63: ='3b-SalesForecastYrs1-3'!G49-('2b-PayrollYrs1-3'!$E$26/12)-'6b-CashFlowYrs1-3'!G19-'Amortization&Depreciation'!G123-'Amortization&Depreciation'!G19-'Amortization&Depreciation'!G39-'Amortization&Depreciation'!G59-'Amortization&Depreciation'!G79-'Amortization&Depreciation'!G99-'6b-CashFlowYrs1-3'!G25-$E$55/12 -> 63276.966 | H63: ='3b-SalesForecastYrs1-3'!H49-('2b-PayrollYrs1-3'!$E$26/12)-'6b-CashFlowYrs1-3'!H19-'Amortization&Depreciation'!H123-'Amortization&Depreciation'!H19-'Amortization&Depreciation'!H39-'Amortization&Depreciation'!H59-'Amortization&Depreciation'!H79-'Amortization&Depreciation'!H99-'6b-CashFlowYrs1-3'!H25-$E$55/12 -> 65658.835 | I63: ='3b-SalesForecastYrs1-3'!I49-('2b-PayrollYrs1-3'!$E$26/12)-'6b-CashFlowYrs1-3'!I19-'Amortization&Depreciation'!I123-'Amortization&Depreciation'!I19-'Amortization&Depreciation'!I39-'Amortization&Depreciation'!I59-'Amortization&Depreciation'!I79-'Amortization&Depreciation'!I99-'6b-CashFlowYrs1-3'!I25-$E$55/12 -> 68112.16 | J63: ='3b-SalesForecastYrs1-3'!J49-('2b-PayrollYrs1-3'!$E$26/12)-'6b-CashFlowYrs1-3'!J19-'Amortization&Depreciation'!J123-'Amortization&Depreciation'!J19-'Amortization&Depreciation'!J39-'Amortization&Depreciation'!J59-'Amortization&Depreciation'!J79-'Amortization&Depreciation'!J99-'6b-CashFlowYrs1-3'!J25-$E$55/12 -> 70639.085 | ... N63: ='3b-SalesForecastYrs1-3'!N49-('2b-PayrollYrs1-3'!$E$26/12)-'6b-CashFlowYrs1-3'!N19-'Amortization&Depreciation'!N123-'Amortization&Depreciation'!N19-'Amortization&Depreciation'!N39-'Amortization&Depreciation'!N59-'Amortization&Depreciation'!N79-'Amortization&Depreciation'!N99-'6b-CashFlowYrs1-3'!N25-$E$55/12 -> 81527.949 | O63: =SUM(C63:N63) -> 807710.03
B64: Total | C64: =C63 -> 54423.323 | D64: =D63+C64 -> 110962.91 | E64: =E63+D64 -> 169682.24 | F64: =F63+E64 -> 230646.71 | G64: =G63+F64 -> 293923.67 | H64: =H63+G64 -> 359582.51 | I64: =I63+H64 -> 427694.67 | J64: =J63+I64 -> 498333.75 | K64: =K63+J64 -> 571575.57 | ... N64: =N63+M64 -> 807710.03 | O64: =SUM(C64:N64) -> 4898215.7
B65: Income Taxes | C65: =IF(C64>0,C63*'4-AdditionalInputs'!$C$40,0) -> 0 | D65: =IF(D64>0,IF(C64<0,(D63-ABS(C64))*'4-AdditionalInputs'!$C$40,D63*'4-AdditionalInputs'!$C$40),IF(C64>0,-(C64*'4-AdditionalInputs'!$C$40),0)) -> 0 | E65: =IF(E64>0,IF(D64<0,(E63-ABS(D64))*'4-AdditionalInputs'!$C$40,E63*'4-AdditionalInputs'!$C$40),IF(D64>0,-(D64*'4-AdditionalInputs'!$C$40),0)) -> 0 | F65: =IF(F64>0,IF(E64<0,(F63-ABS(E64))*'4-AdditionalInputs'!$C$40,F63*'4-AdditionalInputs'!$C$40),IF(E64>0,-(E64*'4-AdditionalInputs'!$C$40),0)) -> 0 | G65: =IF(G64>0,IF(F64<0,(G63-ABS(F64))*'4-AdditionalInputs'!$C$40,G63*'4-AdditionalInputs'!$C$40),IF(F64>0,-(F64*'4-AdditionalInputs'!$C$40),0)) -> 0 | H65: =IF(H64>0,IF(G64<0,(H63-ABS(G64))*'4-AdditionalInputs'!$C$40,H63*'4-AdditionalInputs'!$C$40),IF(G64>0,-(G64*'4-AdditionalInputs'!$C$40),0)) -> 0 | I65: =IF(I64>0,IF(H64<0,(I63-ABS(H64))*'4-AdditionalInputs'!$C$40,I63*'4-AdditionalInputs'!$C$40),IF(H64>0,-(H64*'4-AdditionalInputs'!$C$40),0)) -> 0 | J65: =IF(J64>0,IF(I64<0,(J63-ABS(I64))*'4-AdditionalInputs'!$C$40,J63*'4-AdditionalInputs'!$C$40),IF(I64>0,-(I64*'4-AdditionalInputs'!$C$40),0)) -> 0 | K65: =IF(K64>0,IF(J64<0,(K63-ABS(J64))*'4-AdditionalInputs'!$C$40,K63*'4-AdditionalInputs'!$C$40),IF(J64>0,-(J64*'4-AdditionalInputs'!$C$40),0)) -> 0 | ... N65: =IF(N64>0,IF(M64<0,(N63-ABS(M64))*'4-AdditionalInputs'!$C$40,N63*'4-AdditionalInputs'!$C$40),IF(M64>0,-(M64*'4-AdditionalInputs'!$C$40),0)) -> 0 | O65: =SUM(C65:N65) -> 0
B67: Taxable Amount Year 3 | C67: =('3b-SalesForecastYrs1-3'!R49-('2b-PayrollYrs1-3'!$G$26/12)-'6b-CashFlowYrs1-3'!P19)-'Amortization&Depreciation'!C127-'Amortization&Depreciation'!C23-'Amortization&Depreciation'!C43-'Amortization&Depreciation'!C63-'Amortization&Depreciation'!C83-'Amortization&Depreciation'!C103-'6b-CashFlowYrs1-3'!P25-$G$55/12 -> 79375.358 | D67: =('3b-SalesForecastYrs1-3'!S49-('2b-PayrollYrs1-3'!$G$26/12)-'6b-CashFlowYrs1-3'!Q19)-'Amortization&Depreciation'!D127-'Amortization&Depreciation'!D23-'Amortization&Depreciation'!D43-'Amortization&Depreciation'!D63-'Amortization&Depreciation'!D83-'Amortization&Depreciation'!D103-'6b-CashFlowYrs1-3'!Q25-$G$55/12 -> 81328.291 | E67: =('3b-SalesForecastYrs1-3'!T49-('2b-PayrollYrs1-3'!$G$26/12)-'6b-CashFlowYrs1-3'!R19)-'Amortization&Depreciation'!E127-'Amortization&Depreciation'!E23-'Amortization&Depreciation'!E43-'Amortization&Depreciation'!E63-'Amortization&Depreciation'!E83-'Amortization&Depreciation'!E103-'6b-CashFlowYrs1-3'!R25-$G$55/12 -> 83320.282 | F67: =('3b-SalesForecastYrs1-3'!U49-('2b-PayrollYrs1-3'!$G$26/12)-'6b-CashFlowYrs1-3'!S19)-'Amortization&Depreciation'!F127-'Amortization&Depreciation'!F23-'Amortization&Depreciation'!F43-'Amortization&Depreciation'!F63-'Amortization&Depreciation'!F83-'Amortization&Depreciation'!F103-'6b-CashFlowYrs1-3'!S25-$G$55/12 -> 85352.113 | G67: =('3b-SalesForecastYrs1-3'!V49-('2b-PayrollYrs1-3'!$G$26/12)-'6b-CashFlowYrs1-3'!T19)-'Amortization&Depreciation'!G127-'Amortization&Depreciation'!G23-'Amortization&Depreciation'!G43-'Amortization&Depreciation'!G63-'Amortization&Depreciation'!G83-'Amortization&Depreciation'!G103-'6b-CashFlowYrs1-3'!T25-$G$55/12 -> 87424.581 | H67: =('3b-SalesForecastYrs1-3'!W49-('2b-PayrollYrs1-3'!$G$26/12)-'6b-CashFlowYrs1-3'!U19)-'Amortization&Depreciation'!H127-'Amortization&Depreciation'!H23-'Amortization&Depreciation'!H43-'Amortization&Depreciation'!H63-'Amortization&Depreciation'!H83-'Amortization&Depreciation'!H103-'6b-CashFlowYrs1-3'!U25-$G$55/12 -> 89538.498 | I67: =('3b-SalesForecastYrs1-3'!X49-('2b-PayrollYrs1-3'!$G$26/12)-'6b-CashFlowYrs1-3'!V19)-'Amortization&Depreciation'!I127-'Amortization&Depreciation'!I23-'Amortization&Depreciation'!I43-'Amortization&Depreciation'!I63-'Amortization&Depreciation'!I83-'Amortization&Depreciation'!I103-'6b-CashFlowYrs1-3'!V25-$G$55/12 -> 91694.693 | J67: =('3b-SalesForecastYrs1-3'!Y49-('2b-PayrollYrs1-3'!$G$26/12)-'6b-CashFlowYrs1-3'!W19)-'Amortization&Depreciation'!J127-'Amortization&Depreciation'!J23-'Amortization&Depreciation'!J43-'Amortization&Depreciation'!J63-'Amortization&Depreciation'!J83-'Amortization&Depreciation'!J103-'6b-CashFlowYrs1-3'!W25-$G$55/12 -> 93894.012 | ... N67: =('3b-SalesForecastYrs1-3'!AC49-('2b-PayrollYrs1-3'!$G$26/12)-'6b-CashFlowYrs1-3'!AA19)-'Amortization&Depreciation'!N127-'Amortization&Depreciation'!N23-'Amortization&Depreciation'!N43-'Amortization&Depreciation'!N63-'Amortization&Depreciation'!N83-'Amortization&Depreciation'!N103-'6b-CashFlowYrs1-3'!AA25-$G$55/12 -> 103140.04 | O67: =SUM(C67:N67) -> 1090390.1
B68: Total | C68: =C67 -> 79375.358 | D68: =D67+C68 -> 160703.65 | E68: =E67+D68 -> 244023.93 | F68: =F67+E68 -> 329376.04 | G68: =G67+F68 -> 416800.62 | H68: =H67+G68 -> 506339.12 | I68: =I67+H68 -> 598033.81 | J68: =J67+I68 -> 691927.83 | K68: =K67+J68 -> 788065.14 | ... N68: =N67+M68 -> 1090390.1 | O68: =SUM(C68:N68) -> 6778776.3
B69: Income Taxes | C69: =IF(C68>0,C67*'4-AdditionalInputs'!$C$41,0) -> 0 | D69: =IF(D68>0,IF(C68<0,(D67-ABS(C68))*'4-AdditionalInputs'!$C$41,D67*'4-AdditionalInputs'!$C$41),IF(C68>0,C68*'4-AdditionalInputs'!$C$41,0)) -> 0 | E69: =IF(E68>0,IF(D68<0,(E67-ABS(D68))*'4-AdditionalInputs'!$C$41,E67*'4-AdditionalInputs'!$C$41),IF(D68>0,D68*'4-AdditionalInputs'!$C$41,0)) -> 0 | F69: =IF(F68>0,IF(E68<0,(F67-ABS(E68))*'4-AdditionalInputs'!$C$41,F67*'4-AdditionalInputs'!$C$41),IF(E68>0,E68*'4-AdditionalInputs'!$C$41,0)) -> 0 | G69: =IF(G68>0,IF(F68<0,(G67-ABS(F68))*'4-AdditionalInputs'!$C$41,G67*'4-AdditionalInputs'!$C$41),IF(F68>0,F68*'4-AdditionalInputs'!$C$41,0)) -> 0 | H69: =IF(H68>0,IF(G68<0,(H67-ABS(G68))*'4-AdditionalInputs'!$C$41,H67*'4-AdditionalInputs'!$C$41),IF(G68>0,G68*'4-AdditionalInputs'!$C$41,0)) -> 0 | I69: =IF(I68>0,IF(H68<0,(I67-ABS(H68))*'4-AdditionalInputs'!$C$41,I67*'4-AdditionalInputs'!$C$41),IF(H68>0,H68*'4-AdditionalInputs'!$C$41,0)) -> 0 | J69: =IF(J68>0,IF(I68<0,(J67-ABS(I68))*'4-AdditionalInputs'!$C$41,J67*'4-AdditionalInputs'!$C$41),IF(I68>0,I68*'4-AdditionalInputs'!$C$41,0)) -> 0 | K69: =IF(K68>0,IF(J68<0,(K67-ABS(J68))*'4-AdditionalInputs'!$C$41,K67*'4-AdditionalInputs'!$C$41),IF(J68>0,J68*'4-AdditionalInputs'!$C$41,0)) -> 0 | ... N69: =IF(N68>0,IF(M68<0,(N67-ABS(M68))*'4-AdditionalInputs'!$C$41,N67*'4-AdditionalInputs'!$C$41),IF(M68>0,M68*'4-AdditionalInputs'!$C$41,0)) -> 0 | O69: =SUM(C69:N69) -> 0

Sheet 8-BalanceSheet
C2: Balance Sheet Years 1-3
C4: Prepared By: | D4: Company Name:
C5: =IF(ISBLANK(Directions!C10),"Owner",Directions!C10) -> Owner | D5: =IF(ISBLANK(Directions!D10),"Company 1",Directions!D10) -> Company 1
C7: ASSETS | D7: =IF(Directions!F10>0,Directions!F10,"First Year") -> First Year | E7: =IF(Directions!F10>0,Directions!F10+1,"Second Year") -> Second Year | F7: =IF(Directions!F10>0,Directions!F10+2,"Third Year") -> Third Year
C8: Current Assets
C9: Cash | D9: =Y1EndingCashBal -> 219424.4 | E9: ='6b-CashFlowYrs1-3'!N32 -> 1027134.4 | F9: ='6b-CashFlowYrs1-3'!AA32 -> 2117524.5
C10: Accounts Receivable | D10: =+'7a-IncomeStatementYear1'!O15-'6a-CashFlowYear1'!O12-'7a-IncomeStatementYear1'!O56 -> 0 | E10: =+D10+'7b-IncomeStatementYrs1-3'!E14-'6b-CashFlowYrs1-3'!O11-'7b-IncomeStatementYrs1-3'!E55 -> -1.0011718e-08 | F10: =+E10+'7b-IncomeStatementYrs1-3'!G14-'6b-CashFlowYrs1-3'!AB11-'7b-IncomeStatementYrs1-3'!G55 -> -1.0011718e-08
C11: Inventory | D11: =+Inventory+'6a-CashFlowYear1'!O17 -> 0 | E11: =+D11+'6b-CashFlowYrs1-3'!O16 -> 0 | F11: =+E11+'6b-CashFlowYrs1-3'!AB16 -> 0
C12: Prepaid Expenses | D12: =+'Amortization&Depreciation'!C132-'Amortization&Depreciation'!C133 -> 0 | E12: =+D12-'Amortization&Depreciation'!C133 -> 0 | F12: =+E12-'Amortization&Depreciation'!C133 -> 0
C13: Other Initial Costs | D13: =+OtherStartUp-'Amortization&Depreciation'!C135 -> 0 | E13: =+D13-'Amortization&Depreciation'!C135 -> 0 | F13: =+E13-'Amortization&Depreciation'!C135 -> 0
C14: Total Current Assets | D14: =SUM(D9:D13) -> 219424.4 | E14: =SUM(E9:E13) -> 1027134.4 | F14: =SUM(F9:F13) -> 2117524.5
C16: Fixed Assets
C17: Real Estate -- Land | D17: =Land -> 0 | E17: =Land -> 0 | F17: =Land -> 0
C18: Real Estate -- Buildings | D18: =+'4-AdditionalInputs'!P29 -> 0 | E18: =+'4-AdditionalInputs'!P29+'4-AdditionalInputs'!Q29 -> 0 | F18: =+'4-AdditionalInputs'!P29+'4-AdditionalInputs'!Q29+'4-AdditionalInputs'!R29 -> 0
C19: Leasehold Improvements | D19: =+'4-AdditionalInputs'!P30 -> 0 | E19: =+'4-AdditionalInputs'!P30+'4-AdditionalInputs'!Q30 -> 0 | F19: =+'4-AdditionalInputs'!P30+'4-AdditionalInputs'!Q30+'4-AdditionalInputs'!R30 -> 0
C20: Equipment | D20: =+'4-AdditionalInputs'!P31 -> 0 | E20: =+'4-AdditionalInputs'!P31+'4-AdditionalInputs'!Q31 -> 0 | F20: =+'4-AdditionalInputs'!P31+'4-AdditionalInputs'!Q31+'4-AdditionalInputs'!R31 -> 0
C21: Furniture and Fixtures | D21: =+'4-AdditionalInputs'!P32 -> 0 | E21: =+'4-AdditionalInputs'!P32+'4-AdditionalInputs'!Q32 -> 0 | F21: =+'4-AdditionalInputs'!P32+'4-AdditionalInputs'!Q32+'4-AdditionalInputs'!R32 -> 0
C22: Vehicles | D22: =+'4-AdditionalInputs'!P33 -> 0 | E22: =+'4-AdditionalInputs'!P33+'4-AdditionalInputs'!Q33 -> 0 | F22: =+'4-AdditionalInputs'!P33+'4-AdditionalInputs'!Q33+'4-AdditionalInputs'!R33 -> 0
C23: Other | D23: =+'4-AdditionalInputs'!P34 -> 0 | E23: =+'4-AdditionalInputs'!P34+'4-AdditionalInputs'!Q34 -> 0 | F23: =+'4-AdditionalInputs'!P34+'4-AdditionalInputs'!Q34+'4-AdditionalInputs'!R34 -> 0
C24: Total Fixed Assets | D24: =SUM(D17:D23) -> 0 | E24: =SUM(E17:E23) -> 0 | F24: =SUM(F17:F23) -> 0
C25: (Less Accumulated Depreciation) | D25: ='Amortization&Depreciation'!O119 -> 0 | E25: =+D25+'Amortization&Depreciation'!O123 -> 0 | F25: =E25+'Amortization&Depreciation'!O127 -> 0
C26: Total Assets | D26: =INT(D24+D14-D25) -> 219424 | E26: =INT(E24+E14-E25) -> 1027134 | F26: =INT(F24+F14-F25) -> 2117524
C28: LIABILITIES & EQUITY
C29: Liabilities
C30: Accounts Payable | D30: =+'7a-IncomeStatementYear1'!O23-'6a-CashFlowYear1'!O18 -> 0 | E30: =+D30+'7b-IncomeStatementYrs1-3'!E22-'6b-CashFlowYrs1-3'!O17 -> 0 | F30: =+E30+'7b-IncomeStatementYrs1-3'!G22-'6b-CashFlowYrs1-3'!AB17 -> 0
C31: Commercial Loan Balance | D31: =+'Amortization&Depreciation'!N17 -> 0 | E31: =+'Amortization&Depreciation'!N21 -> 0 | F31: =+'Amortization&Depreciation'!N25 -> 0
C32: Commercial Mortgage Balance | D32: =+'Amortization&Depreciation'!N37 -> 0 | E32: =+'Amortization&Depreciation'!N41 -> 0 | F32: =+'Amortization&Depreciation'!N45 -> 0
C33: Credit Card Debt Balance | D33: =+'Amortization&Depreciation'!N57 -> 0 | E33: =+'Amortization&Depreciation'!N61 -> 0 | F33: =+'Amortization&Depreciation'!N65 -> 0
C34: Vehicle Loans Balance | D34: =+'Amortization&Depreciation'!N77 -> 0 | E34: =+'Amortization&Depreciation'!N81 -> 0 | F34: =+'Amortization&Depreciation'!N85 -> 0
C35: Other Bank Debt Balance | D35: =+'Amortization&Depreciation'!N97 -> 0 | E35: =+'Amortization&Depreciation'!N101 -> 0 | F35: =+'Amortization&Depreciation'!N105 -> 0
C36: Line of Credit Balance | D36: =+'6a-CashFlowYear1'!N34 -> 0 | E36: =+'6b-CashFlowYrs1-3'!N33 -> 0 | F36: =+'6b-CashFlowYrs1-3'!AA33 -> 0
C37: Total Liabilities | D37: =SUM(D30:D36) -> 0 | E37: =SUM(E30:E36) -> 0 | F37: =SUM(F30:F36) -> 0
C38: Equity
C39: Common Stock | D39: =OwnerEquity+OutsideInvest -> 0 | E39: =OwnerEquity+OutsideInvest -> 0 | F39: =OwnerEquity+OutsideInvest -> 0
C40: Retained Earnings | D40: ='7b-IncomeStatementYrs1-3'!C59 -> 219424.4 | E40: =D40+NetIncomeY2 -> 1027134.4 | F40: =E40+NetIncomeY3 -> 2117524.5
C41: Dividends Dispersed/Owners Draw | D41: ='6a-CashFlowYear1'!O28+'6a-CashFlowYear1'!O25 -> 0 | E41: =+D41+'6b-CashFlowYrs1-3'!O27+'6b-CashFlowYrs1-3'!O24 -> 0 | F41: =+E41+'6b-CashFlowYrs1-3'!AB27+'6b-CashFlowYrs1-3'!AB24 -> 0
C42: Total Equity | D42: =+D39+D40-D41 -> 219424.4 | E42: =+E39+E40-E41 -> 1027134.4 | F42: =+F39+F40-F41 -> 2117524.5
C43: Total Liabilities and Equity | D43: =INT(D37+D42) -> 219424 | E43: =INT(E37+E42) -> 1027134 | F43: =INT(F37+F42) -> 2117524
C45: Balance sheet in or out of balance? | D45: =D26-D43 -> 0 | E45: =E26-E43 -> 0 | F45: =F26-F43 -> 0
D46: =IF(D45=0,"Balanced!","Warning: Not Balanced") -> Balanced! | E46: =IF(E45=0,"Balanced!","Warning: Not Balanced") -> Balanced! | F46: =IF(F45=0,"Balanced!","Warning: Not Balanced") -> Balanced!

Sheet BreakevenAnalysis
B2: Breakeven Analysis Year 1
B4: Prepared By: | C4: Company Name:
B5: =IF(ISBLANK(Directions!C10),"Owner",Directions!C10) -> Owner | C5: =IF(ISBLANK(Directions!D10),"Company 1",Directions!D10) -> Company 1
B8: Gross Margin % of Sales
B9: Gross Margin | C9: ='7b-IncomeStatementYrs1-3'!C23 -> 396072
B10: Total Sales | C10: ='7b-IncomeStatementYrs1-3'!C14 -> 611712
B11: Gross Margin/Total Sales | C11: =IF(C10>0,C9/C10,0) -> 0.64748117
B12: Total Fixed Expenses
B13: Payroll | C13: ='2a-PayrollYear1'!R25 -> 54827.602
B14: Operating Expenses | C14: ='5a-OpExYear1'!O38 -> 121820
B15: Operating + Payroll | C15: =SUM(C13:C14) -> 176647.6
B16: Breakeven Sales in Dollars (Annual)
B17: Gross Margin % of Sales | C17: =C11 -> 0.64748117
B18: Total Fixed Expenses | C18: =C15 -> 176647.6
B19: Yearly Breakeven Amount | C19: =IF(C11=0,0,C15/C11) -> 272822.76
B20: Monthly Breakeven Amount | C20: =C19/12 -> 22735.23

Sheet FinancialRatios
B2: Financial Ratios - Year 1
B4: Prepared By: | C4: Company Name:
B5: =IF(ISBLANK(Directions!C10),"Owner",Directions!C10) -> Owner | C5: =IF(ISBLANK(Directions!D10),"Company 1",Directions!D10) -> Company 1
B7: Ratios | C7: Year One | D7: Year Two | E7: Year Three | F7: Industry Norms | G7: Notes
B8: Liquidity
B9: Current Ratio | C9: =IF('8-BalanceSheet'!D37=0,0,'8-BalanceSheet'!D14/'8-BalanceSheet'!D37) -> 0 | D9: =IF('8-BalanceSheet'!E37=0,0,'8-BalanceSheet'!E14/'8-BalanceSheet'!E37) -> 0 | E9: =IF('8-BalanceSheet'!F37=0,0,'8-BalanceSheet'!F14/'8-BalanceSheet'!F37) -> 0
B10: Quick Ratio | C10: =IF('8-BalanceSheet'!D37=0,0,('8-BalanceSheet'!D9+'8-BalanceSheet'!D10)/'8-BalanceSheet'!D37) -> 0 | D10: =IF('8-BalanceSheet'!E37=0,0,('8-BalanceSheet'!E9+'8-BalanceSheet'!E10)/'8-BalanceSheet'!E37) -> 0 | E10: =IF('8-BalanceSheet'!F37=0,0,('8-BalanceSheet'!F9+'8-BalanceSheet'!F10)/'8-BalanceSheet'!F37) -> 0
B11: Safety
B12: Debt to Equity Ratio | C12: =IF('8-BalanceSheet'!D42=0,0,'8-BalanceSheet'!D37/'8-BalanceSheet'!D42) -> 0 | D12: =IF('8-BalanceSheet'!E42=0,0,'8-BalanceSheet'!E37/'8-BalanceSheet'!E42) -> 0 | E12: =IF('8-BalanceSheet'!F42=0,0,'8-BalanceSheet'!F37/'8-BalanceSheet'!F42) -> 0
B13: Debt-Service Coverage Ratio - DSCR | C13: =IF('8-BalanceSheet'!D37=0,0,('7a-IncomeStatementYear1'!O60+'7a-IncomeStatementYear1'!O48)/'8-BalanceSheet'!D37) -> 0 | D13: =IF('8-BalanceSheet'!E37=0,0,('7b-IncomeStatementYrs1-3'!E47+NetIncomeY2)/'8-BalanceSheet'!E37) -> 0 | E13: =IF('8-BalanceSheet'!F37=0,0,('7b-IncomeStatementYrs1-3'!G47+NetIncomeY3)/'8-BalanceSheet'!F37) -> 0
B14: Profitability
B15: Sales Growth | C15: 0 | D15: =IF('7b-IncomeStatementYrs1-3'!C14=0,0,('7b-IncomeStatementYrs1-3'!E14-'7b-IncomeStatementYrs1-3'!C14)/'7b-IncomeStatementYrs1-3'!C14) -> 1.5219417 | E15: =IF('7b-IncomeStatementYrs1-3'!E14=0,0,('7b-IncomeStatementYrs1-3'!G14-'7b-IncomeStatementYrs1-3'!E14)/'7b-IncomeStatementYrs1-3'!E14) -> 0.30816165
B16: COGS to Sales | C16: =IF('7b-IncomeStatementYrs1-3'!C14=0,0,'7b-IncomeStatementYrs1-3'!C22/'7b-IncomeStatementYrs1-3'!C14) -> 0.35251883 | D16: =IF('7b-IncomeStatementYrs1-3'!E14=0,0,'7b-IncomeStatementYrs1-3'!E22/'7b-IncomeStatementYrs1-3'!E14) -> 0.3510515 | E16: =IF('7b-IncomeStatementYrs1-3'!G14=0,0,'7b-IncomeStatementYrs1-3'!G22/'7b-IncomeStatementYrs1-3'!G14) -> 0.3510515
B17: Gross Profit Margin | C17: =BreakevenAnalysis!C11 -> 0.64748117 | D17: =IF('7b-IncomeStatementYrs1-3'!E14=0,0,'7b-IncomeStatementYrs1-3'!E23/'7b-IncomeStatementYrs1-3'!E14) -> 0.6489485 | E17: =IF('7b-IncomeStatementYrs1-3'!G14=0,0,'7b-IncomeStatementYrs1-3'!G23/'7b-IncomeStatementYrs1-3'!G14) -> 0.6489485
B18: SG&A to Sales | C18: =IF('7a-IncomeStatementYear1'!O15=0,0,('7a-IncomeStatementYear1'!O25+'7a-IncomeStatementYear1'!O44)/'7a-IncomeStatementYear1'!O15) -> 0.28877577 | D18: =IF('7b-IncomeStatementYrs1-3'!E14=0,0,('7b-IncomeStatementYrs1-3'!E24+'7b-IncomeStatementYrs1-3'!E43)/'7b-IncomeStatementYrs1-3'!E14) -> 0.12538009 | E18: =IF('7b-IncomeStatementYrs1-3'!G14=0,0,('7b-IncomeStatementYrs1-3'!G24+'7b-IncomeStatementYrs1-3'!G43)/'7b-IncomeStatementYrs1-3'!G14) -> 0.10864418
B19: Net Profit Margin | C19: =IF('7b-IncomeStatementYrs1-3'!C14=0,0,NetIncomeY1/'7b-IncomeStatementYrs1-3'!C14) -> 0.3587054 | D19: =IF('7b-IncomeStatementYrs1-3'!E14=0,0,NetIncomeY2/'7b-IncomeStatementYrs1-3'!E14) -> 0.52356841 | E19: =IF('7b-IncomeStatementYrs1-3'!G14=0,0,NetIncomeY3/'7b-IncomeStatementYrs1-3'!G14) -> 0.54030432
B20: Return on Equity (ROE) | C20: =IF('8-BalanceSheet'!D42=0,0,NetIncomeY1/'8-BalanceSheet'!D42) -> 1 | D20: =IF('8-BalanceSheet'!E42=0,0,NetIncomeY2/'8-BalanceSheet'!E42) -> 0.78637227 | E20: =IF('8-BalanceSheet'!F42=0,0,NetIncomeY3/'8-BalanceSheet'!F42) -> 0.51493623
B21: Return on Assets | C21: =IF('8-BalanceSheet'!D26=0,0,NetIncomeY1/'8-BalanceSheet'!D26) -> 1.0000018 | D21: =IF('8-BalanceSheet'!E26=0,0,NetIncomeY2/'8-BalanceSheet'!E26) -> 0.78637259 | E21: =IF('8-BalanceSheet'!F26=0,0,NetIncomeY3/'8-BalanceSheet'!F26) -> 0.51493636
B22: Owner's Compensation to Sales | C22: =IF('7b-IncomeStatementYrs1-3'!C14=0,0,'2b-PayrollYrs1-3'!C9/'7b-IncomeStatementYrs1-3'!C14) -> 0.082829828 | D22: =IF('7b-IncomeStatementYrs1-3'!E14=0,0,'2b-PayrollYrs1-3'!E9/'7b-IncomeStatementYrs1-3'!E14) -> 0.039412408 | E22: =IF('7b-IncomeStatementYrs1-3'!G14=0,0,'2b-PayrollYrs1-3'!G9/'7b-IncomeStatementYrs1-3'!G14) -> 0.039166513
B23: Efficiency
B24: Days in Receivables | C24: =IF('7b-IncomeStatementYrs1-3'!C14=0,0,'8-BalanceSheet'!D10/'7b-IncomeStatementYrs1-3'!C14*360) -> 0 | D24: =IF('7b-IncomeStatementYrs1-3'!E14=0,0,'8-BalanceSheet'!E10/'7b-IncomeStatementYrs1-3'!E14)*360 -> -2.3363024e-12 | E24: =IF('7b-IncomeStatementYrs1-3'!G14=0,0,'8-BalanceSheet'!F10/'7b-IncomeStatementYrs1-3'!G14*360) -> -1.7859432e-12
B25: Accounts Receivable Turnover | C25: =IF('8-BalanceSheet'!D10=0,0,'7b-IncomeStatementYrs1-3'!C14/'8-BalanceSheet'!D10) -> 0 | D25: =IF('8-BalanceSheet'!E10=0,0,'7b-IncomeStatementYrs1-3'!E14/'8-BalanceSheet'!E10) -> -154089642472097 | E25: =IF('8-BalanceSheet'!F10=0,0,'7b-IncomeStatementYrs1-3'!G14/'8-BalanceSheet'!F10) -> -201574161712889
B26: Days in Inventory | C26: =IF('7b-IncomeStatementYrs1-3'!C22=0,0,'8-BalanceSheet'!D11/'7b-IncomeStatementYrs1-3'!C22*360) -> 0 | D26: =IF('7b-IncomeStatementYrs1-3'!E22=0,0,'8-BalanceSheet'!E11/'7b-IncomeStatementYrs1-3'!E22*365) -> 0 | E26: =IF('7b-IncomeStatementYrs1-3'!G22=0,0,'8-BalanceSheet'!F11/'7b-IncomeStatementYrs1-3'!G22*365) -> 0
B27: Inventory Turnover | C27: =IF('8-BalanceSheet'!D11=0,0,'7b-IncomeStatementYrs1-3'!C22/'8-BalanceSheet'!D11) -> 0 | D27: =IF('8-BalanceSheet'!E11=0,0,'7b-IncomeStatementYrs1-3'!E22/'8-BalanceSheet'!E11) -> 0 | E27: =IF('8-BalanceSheet'!F11=0,0,'7b-IncomeStatementYrs1-3'!G22/'8-BalanceSheet'!F11) -> 0
B28: Sales to Total Assets | C28: =IF('8-BalanceSheet'!D26=0,0,'7b-IncomeStatementYrs1-3'!C14/'8-BalanceSheet'!D26) -> 2.7878081 | D28: =IF('8-BalanceSheet'!E26=0,0,'7b-IncomeStatementYrs1-3'!E14/'8-BalanceSheet'!E26) -> 1.5019481 | E28: =IF('8-BalanceSheet'!F26=0,0,'7b-IncomeStatementYrs1-3'!G14/'8-BalanceSheet'!F26) -> 0.95304875

Sheet DiagnosticTools
B2: Diagnostic Tools - Year 1
B4: Prepared By: | C4: Company Name:
B5: =IF(ISBLANK(Directions!C10),"Owner",Directions!C10) -> Owner | C5: =IF(ISBLANK(Directions!D10),"Company 1",Directions!D10) -> Company 1
B7: General Financing Assumptions | C7: Value | D7: Findings
B8: Owner's Cash Injection into the Business | C8: =IF('1-StartingPoint'!D42=0,0,'1-StartingPoint'!D34/'1-StartingPoint'!C31) -> 0 | D8: =IF(C8>0.2,"Owner's injection is reasonable","Owner's injection might be too low in relation to the amount of money needed") -> Owner's injection might be too low in relation to the amount of money needed
B9: Cash Request as percent of Total Required Funds | C9: =IF('1-StartingPoint'!C31=0,0,'1-StartingPoint'!C29/'1-StartingPoint'!C31) -> 0 | D9: =IF(C9<0.2,"Cash request seems reasonable with respect to total request","Cash request exceeds 20% which might be too high") -> Cash request seems reasonable with respect to total request
B11: Loan Assumptions | C11: Value | D11: Findings
B12: Commercial Loan Interest rate | C12: ='1-StartingPoint'!E37 -> 0.09 | D12: =IF(C12<0.06,"Interest rate may be too low for the type of loan requested","Interest rate seems reasonable") -> Interest rate seems reasonable
B13: Commercial Loan Term in Months | C13: ='1-StartingPoint'!F37 -> 84 | D13: =IF(C13>120,"Loan term may be too high for this type of loan","Loan term seems within range for this type of loan") -> Loan term seems within range for this type of loan
B14: Commercial Mortgage Interest rate | C14: ='1-StartingPoint'!E38 -> 0.09 | D14: =IF(C14<0.06,"Interest rate may be too low for type of loan requested","Interest rate seems reasonable") -> Interest rate seems reasonable
B15: Commercial Mortgage Term in Months | C15: ='1-StartingPoint'!F38 -> 240 | D15: =IF(C15>240,"Loan term may be too high for this type of loan","Loan term seems within range for this type of loan") -> Loan term seems within range for this type of loan
B16: Debt-Service Coverage | C16: =FinancialRatios!C13 -> 0 | D16: =IF(C16>1,"Calculated loan payments relative to operating proft may be too high","Calculated loan payments relative to operating profit seem reasonable") -> Calculated loan payments relative to operating profit seem reasonable
B18: Income Statement | C18: Value | D18: Findings
B19: Gross Margin as a Percent of Sales | C19: =BreakevenAnalysis!C11 -> 0.64748117 | D19: =IF(C19<0.2,"Gross margin percentage seems very low","Gross margin percentage seems reasonable") -> Gross margin percentage seems reasonable
B20: Owner's Compensation Lower Limit Check | C20: ='2a-PayrollYear1'!R8 -> 50668 | D20: =IF(C20>0,"An owner's compensation amount has been established","An owner's compensation amount has not been established") -> An owner's compensation amount has been established
B21: Owner's Compensation Upper Limit Check | C21: =IF(NetIncomeY1=0,0,'2a-PayrollYear1'!R8/NetIncomeY1) -> 0.23091325 | D21: =IF(C21>1,"Owner's compensation may be too high relative to profitability of business","Owner's compensation seems reasonable") -> Owner's compensation seems reasonable
B22: Advertising Expense Levels as a Percent of Sales | C22: =IF('7b-IncomeStatementYrs1-3'!C14=0,0,'7b-IncomeStatementYrs1-3'!C26/'7b-IncomeStatementYrs1-3'!C14) -> 0 | D22: =IF(C22<0.02,"Advertising as a percent of sales may be too low","Advertising as a percent of sales seems reasonable") -> Advertising as a percent of sales may be too low
B23: Profitability Levels | C23: =NetIncomeY1 -> 219424.4 | D23: =IF(C23<=0,"The business is not showing a profit","The business is showing a profit") -> The business is showing a profit
B24: Profitability as a Percent of Sales | C24: =IF('7b-IncomeStatementYrs1-3'!C14=0,0,NetIncomeY1/'7b-IncomeStatementYrs1-3'!C14) -> 0.3587054 | D24: =IF(C24>0.2,"The projection may be too aggressive in stating profitability","The projection does not seem highly unreasonable") -> The projection may be too aggressive in stating profitability
B26: Cash Flow Statement | C26: Value | D26: Findings
B27: Desired Operating cash Flow Levels | C27: ='6a-CashFlowYear1'!O32 -> 0 | D27: =IF(C27<0,"The financial projection does not provide the desired level of cash flow","The financial projection provides the desired level of cash flow") -> The financial projection provides the desired level of cash flow
B28: Line of Credit Drawdowns | C28: =+C27 -> 0 | D28: =IF(C28>0,"The business will need at least this level of a line of credit","The business doesn't seem to require a line of credit") -> The business doesn't seem to require a line of credit
B29: Accounts Receivable Ratio to Sales | C29: =IF('7b-IncomeStatementYrs1-3'!C14=0,0,'8-BalanceSheet'!D10/'7b-IncomeStatementYrs1-3'!C14) -> 0 | D29: =IF(C29>0.3,"Accounts receivable amounts seem high","Accounts receivable amount as a percent of sales seems reasonable") -> Accounts receivable amount as a percent of sales seems reasonable
B31: Balance Sheet | C31: Value | D31: Findings
B32: Does the Year 1 Balance Sheet Balance? | C32: ='8-BalanceSheet'!D45 -> 0 | D32: =IF(C32<>0,"The balance sheet is not in balance","The balance sheet does balance") -> The balance sheet does balance
B33: Debt to Equity Ratio | C33: =FinancialRatios!C12 -> 0 | D33: =IF(C33<=2,"Very comfortable",IF(C33<=3,"Reasonable",IF(C33<=4,"Getting debt heavy","Debt heavy"))) -> Very comfortable
B35: Breakeven Analysis | C35: Value | D35: Findings
B36: Do Sales Exceed the Breakeven Level? | C36: ='7b-IncomeStatementYrs1-3'!C14-BreakevenAnalysis!C19 -> 338889.24 | D36: =IF(C36>0,"The sales projection exceeds the projected break-even sales level","The sales projection is less than the break-even amount") -> The sales projection exceeds the projected break-even sales level

Sheet COGS Calculator
B2: COGS Calculator
B4: Prepared By: | C4: Company Name:
B5: =IF(ISBLANK(Directions!C10),"Owner",Directions!C10) -> Owner | C5: =IF(ISBLANK(Directions!D10),"Company 1",Directions!D10) -> Company 1
B7: Variable Costs of Products
B8: Timeframe: | C8: Month
B9: Product Line: | C9: Widget
B10: Raw materials
B11: Labor used to produce product
B12: Costs associated with shipping and storing raw materials
B13: Production facility expenses (use fraction of total if facility is used for other items)
B14: Total Product Expenses | C14: =SUM(C10:C13) -> 0
B15: Number Units Sold in timeframe used
B16: Cost of Goods Sold Per Unit | C16: =IF(C15>0,C14/C15,"Please enter all information.") -> Please enter all information.
B18: Variable Costs of Services
B19: Timeframe: | C19: Month
B20: Product Line: | C20: Project
B21: Amount spent on labor during timeframe
B22: Amount spent on materials during this timeframe
B23: List any other variable costs associated with the delivery of your service during this timeframe.
B24: Total Service Expenses | C24: =SUM(C21:C23) -> 0
B25: Number Units Sold During Timeframe
B26: Cost of Goods Sold Per Unit | C26: =IF(C25>0,C24/C25,"Please enter all information.") -> Please enter all information.
C29: Return to Sales Forecast Year 1

Sheet Amortization&Depreciation
B2: Amortization & Depreciation Schedule
B4: Prepared By: | C4: Company Name: | E4: Return to Starting Point
B5: =IF(ISBLANK(Directions!C10),"Owner",Directions!C10) -> Owner | C5: =IF(ISBLANK(Directions!D10),"Company 1",Directions!D10) -> Company 1
B8: Commercial Loan
B9: Principal Amount | C9: =CommLoan -> 0
B10: Interest Rate | C10: ='1-StartingPoint'!E37 -> 0.09
B11: Loan Term in Months | C11: ='1-StartingPoint'!F37 -> 84
B12: Monthly Payment Amount | C12: =ABS(PMT(C10/12,C11,C9)) -> 0
C13: ='3a-SalesForecastYear1'!$C$16 -> Month 1 | D13: ='3a-SalesForecastYear1'!$D$16 -> Month 2 | E13: ='3a-SalesForecastYear1'!$E$16 -> Month 3 | F13: ='3a-SalesForecastYear1'!$F$16 -> Month 4 | G13: ='3a-SalesForecastYear1'!$G$16 -> Month 5 | H13: ='3a-SalesForecastYear1'!$H$16 -> Month 6 | I13: ='3a-SalesForecastYear1'!$I$16 -> Month 7 | J13: ='3a-SalesForecastYear1'!$J$16 -> Month 8 | K13: ='3a-SalesForecastYear1'!$K$16 -> Month 9 | L13: ='3a-SalesForecastYear1'!$L$16 -> Month 10 | M13: ='3a-SalesForecastYear1'!$M$16 -> Month 11 | N13: ='3a-SalesForecastYear1'!$N$16 -> Month 12 | O13: Totals
B14: Year One
B15: Interest | C15: =IF($C$11<1,0,ABS(IPMT($C$10/12,1,$C$11,$C$9))) -> 0 | D15: =IF($C$11<2,0,ABS(IPMT($C$10/12,2,$C$11,$C$9))) -> 0 | E15: =IF($C$11<3,0,ABS(IPMT($C$10/12,3,$C$11,$C$9))) -> 0 | F15: =IF($C$11<4,0,ABS(IPMT($C$10/12,4,$C$11,$C$9))) -> 0 | G15: =IF($C$11<5,0,ABS(IPMT($C$10/12,5,$C$11,$C$9))) -> 0 | H15: =IF($C$11<6,0,ABS(IPMT($C$10/12,6,$C$11,$C$9))) -> 0 | I15: =IF($C$11<7,0,ABS(IPMT($C$10/12,7,$C$11,$C$9))) -> 0 | J15: =IF($C$11<8,0,ABS(IPMT($C$10/12,8,$C$11,$C$9))) -> 0 | K15: =IF($C$11<9,0,ABS(IPMT($C$10/12,9,$C$11,$C$9))) -> 0 | L15: =IF($C$11<10,0,ABS(IPMT($C$10/12,10,$C$11,$C$9))) -> 0 | M15: =IF($C$11<11,0,ABS(IPMT($C$10/12,11,$C$11,$C$9))) -> 0 | N15: =IF($C$11<12,0,ABS(IPMT($C$10/12,12,$C$11,$C$9))) -> 0 | O15: =SUM(C15:N15) -> 0
B16: Principal | C16: =IF($C$11<1,0,ABS(PPMT($C$10/12,1,$C$11,$C$9))) -> 0 | D16: =IF($C$11<2,0,ABS(PPMT($C$10/12,2,$C$11,$C$9))) -> 0 | E16: =IF($C$11<3,0,ABS(PPMT($C$10/12,3,$C$11,$C$9))) -> 0 | F16: =IF($C$11<4,0,ABS(PPMT($C$10/12,4,$C$11,$C$9))) -> 0 | G16: =IF($C$11<5,0,ABS(PPMT($C$10/12,5,$C$11,$C$9))) -> 0 | H16: =IF($C$11<6,0,ABS(PPMT($C$10/12,6,$C$11,$C$9))) -> 0 | I16: =IF($C$11<7,0,ABS(PPMT($C$10/12,7,$C$11,$C$9))) -> 0 | J16: =IF($C$11<8,0,ABS(PPMT($C$10/12,8,$C$11,$C$9))) -> 0 | K16: =IF($C$11<9,0,ABS(PPMT($C$10/12,9,$C$11,$C$9))) -> 0 | L16: =IF($C$11<10,0,ABS(PPMT($C$10/12,10,$C$11,$C$9))) -> 0 | M16: =IF($C$11<11,0,ABS(PPMT($C$10/12,11,$C$11,$C$9))) -> 0 | N16: =IF($C$11<12,0,ABS(PPMT($C$10/12,12,$C$11,$C$9))) -> 0 | O16: =SUM(C16:N16) -> 0
B17: Loan Balance | C17: =$C$9-C16 -> 0 | D17: =C17-D16 -> 0 | E17: =D17-E16 -> 0 | F17: =E17-F16 -> 0 | G17: =F17-G16 -> 0 | H17: =G17-H16 -> 0 | I17: =H17-I16 -> 0 | J17: =I17-J16 -> 0 | K17: =J17-K16 -> 0 | ... N17: =M17-N16 -> 0
B18: Year Two
B19: Interest | C19: =IF($C$11<13,0,ABS(IPMT($C$10/12,13,$C$11,$C$9))) -> 0 | D19: =IF($C$11<14,0,ABS(IPMT($C$10/12,14,$C$11,$C$9))) -> 0 | E19: =IF($C$11<15,0,ABS(IPMT($C$10/12,15,$C$11,$C$9))) -> 0 | F19: =IF($C$11<16,0,ABS(IPMT($C$10/12,16,$C$11,$C$9))) -> 0 | G19: =IF($C$11<17,0,ABS(IPMT($C$10/12,17,$C$11,$C$9))) -> 0 | H19: =IF($C$11<18,0,ABS(IPMT($C$10/12,18,$C$11,$C$9))) -> 0 | I19: =IF($C$11<19,0,ABS(IPMT($C$10/12,19,$C$11,$C$9))) -> 0 | J19: =IF($C$11<20,0,ABS(IPMT($C$10/12,20,$C$11,$C$9))) -> 0 | K19: =IF($C$11<21,0,ABS(IPMT($C$10/12,21,$C$11,$C$9))) -> 0 | L19: =IF($C$11<22,0,ABS(IPMT($C$10/12,22,$C$11,$C$9))) -> 0 | M19: =IF($C$11<23,0,ABS(IPMT($C$10/12,23,$C$11,$C$9))) -> 0 | N19: =IF($C$11<24,0,ABS(IPMT($C$10/12,24,$C$11,$C$9))) -> 0 | O19: =SUM(C19:N19) -> 0
B20: Principal | C20: =IF($C$11<13,0,ABS(PPMT($C$10/12,13,$C$11,$C$9))) -> 0 | D20: =IF($C$11<14,0,ABS(PPMT($C$10/12,14,$C$11,$C$9))) -> 0 | E20: =IF($C$11<15,0,ABS(PPMT($C$10/12,15,$C$11,$C$9))) -> 0 | F20: =IF($C$11<16,0,ABS(PPMT($C$10/12,16,$C$11,$C$9))) -> 0 | G20: =IF($C$11<17,0,ABS(PPMT($C$10/12,17,$C$11,$C$9))) -> 0 | H20: =IF($C$11<18,0,ABS(PPMT($C$10/12,18,$C$11,$C$9))) -> 0 | I20: =IF($C$11<19,0,ABS(PPMT($C$10/12,19,$C$11,$C$9))) -> 0 | J20: =IF($C$11<20,0,ABS(PPMT($C$10/12,20,$C$11,$C$9))) -> 0 | K20: =IF($C$11<21,0,ABS(PPMT($C$10/12,21,$C$11,$C$9))) -> 0 | L20: =IF($C$11<22,0,ABS(PPMT($C$10/12,22,$C$11,$C$9))) -> 0 | M20: =IF($C$11<23,0,ABS(PPMT($C$10/12,23,$C$11,$C$9))) -> 0 | N20: =IF($C$11<24,0,ABS(PPMT($C$10/12,24,$C$11,$C$9))) -> 0 | O20: =SUM(C20:N20) -> 0
B21: Loan Balance | C21: =N17-C20 -> 0 | D21: =C21-D20 -> 0 | E21: =D21-E20 -> 0 | F21: =E21-F20 -> 0 | G21: =F21-G20 -> 0 | H21: =G21-H20 -> 0 | I21: =H21-I20 -> 0 | J21: =I21-J20 -> 0 | K21: =J21-K20 -> 0 | ... N21: =M21-N20 -> 0
B22: Year Three
B23: Interest | C23: =IF($C$11<25,0,ABS(IPMT($C$10/12,25,$C$11,$C$9))) -> 0 | D23: =IF($C$11<26,0,ABS(IPMT($C$10/12,26,$C$11,$C$9))) -> 0 | E23: =IF($C$11<27,0,ABS(IPMT($C$10/12,27,$C$11,$C$9))) -> 0 | F23: =IF($C$11<28,0,ABS(IPMT($C$10/12,28,$C$11,$C$9))) -> 0 | G23: =IF($C$11<29,0,ABS(IPMT($C$10/12,29,$C$11,$C$9))) -> 0 | H23: =IF($C$11<30,0,ABS(IPMT($C$10/12,30,$C$11,$C$9))) -> 0 | I23: =IF($C$11<31,0,ABS(IPMT($C$10/12,31,$C$11,$C$9))) -> 0 | J23: =IF($C$11<32,0,ABS(IPMT($C$10/12,32,$C$11,$C$9))) -> 0 | K23: =IF($C$11<33,0,ABS(IPMT($C$10/12,33,$C$11,$C$9))) -> 0 | L23: =IF($C$11<34,0,ABS(IPMT($C$10/12,34,$C$11,$C$9))) -> 0 | M23: =IF($C$11<35,0,ABS(IPMT($C$10/12,35,$C$11,$C$9))) -> 0 | N23: =IF($C$11<36,0,ABS(IPMT($C$10/12,36,$C$11,$C$9))) -> 0 | O23: =SUM(C23:N23) -> 0
B24: Principal | C24: =IF($C$11<25,0,ABS(PPMT($C$10/12,25,$C$11,$C$9))) -> 0 | D24: =IF($C$11<26,0,ABS(PPMT($C$10/12,26,$C$11,$C$9))) -> 0 | E24: =IF($C$11<27,0,ABS(PPMT($C$10/12,27,$C$11,$C$9))) -> 0 | F24: =IF($C$11<28,0,ABS(PPMT($C$10/12,28,$C$11,$C$9))) -> 0 | G24: =IF($C$11<29,0,ABS(PPMT($C$10/12,29,$C$11,$C$9))) -> 0 | H24: =IF($C$11<30,0,ABS(PPMT($C$10/12,30,$C$11,$C$9))) -> 0 | I24: =IF($C$11<31,0,ABS(PPMT($C$10/12,31,$C$11,$C$9))) -> 0 | J24: =IF($C$11<32,0,ABS(PPMT($C$10/12,32,$C$11,$C$9))) -> 0 | K24: =IF($C$11<33,0,ABS(PPMT($C$10/12,33,$C$11,$C$9))) -> 0 | L24: =IF($C$11<34,0,ABS(PPMT($C$10/12,34,$C$11,$C$9))) -> 0 | M24: =IF($C$11<35,0,ABS(PPMT($C$10/12,35,$C$11,$C$9))) -> 0 | N24: =IF($C$11<36,0,ABS(PPMT($C$10/12,36,$C$11,$C$9))) -> 0 | O24: =SUM(C24:N24) -> 0
B25: Loan Balance | C25: =N21-C24 -> 0 | D25: =C25-D24 -> 0 | E25: =D25-E24 -> 0 | F25: =E25-F24 -> 0 | G25: =F25-G24 -> 0 | H25: =G25-H24 -> 0 | I25: =H25-I24 -> 0 | J25: =I25-J24 -> 0 | K25: =J25-K24 -> 0 | ... N25: =M25-N24 -> 0
B28: Commercial Mortgage
B29: Principal Amount | C29: =CommMortgage -> 0
B30: Interest Rate | C30: ='1-StartingPoint'!E38 -> 0.09
B31: Loan Term in Months | C31: ='1-StartingPoint'!F38 -> 240
B32: Monthly Payment Amount | C32: =ABS(PMT(C30/12,C31,C29)) -> 0
C33: ='3a-SalesForecastYear1'!$C$16 -> Month 1 | D33: ='3a-SalesForecastYear1'!$D$16 -> Month 2 | E33: ='3a-SalesForecastYear1'!$E$16 -> Month 3 | F33: ='3a-SalesForecastYear1'!$F$16 -> Month 4 | G33: ='3a-SalesForecastYear1'!$G$16 -> Month 5 | H33: ='3a-SalesForecastYear1'!$H$16 -> Month 6 | I33: ='3a-SalesForecastYear1'!$I$16 -> Month 7 | J33: ='3a-SalesForecastYear1'!$J$16 -> Month 8 | K33: ='3a-SalesForecastYear1'!$K$16 -> Month 9 | L33: ='3a-SalesForecastYear1'!$L$16 -> Month 10 | M33: ='3a-SalesForecastYear1'!$M$16 -> Month 11 | N33: ='3a-SalesForecastYear1'!$N$16 -> Month 12 | O33: Totals
B34: Year One
B35: Interest | C35: =ABS(IPMT($C$30/12,1,$C$31,$C$29)) -> 0 | D35: =ABS(IPMT($C$30/12,2,$C$31,$C$29)) -> 0 | E35: =ABS(IPMT($C$30/12,3,$C$31,$C$29)) -> 0 | F35: =ABS(IPMT($C$30/12,4,$C$31,$C$29)) -> 0 | G35: =ABS(IPMT($C$30/12,5,$C$31,$C$29)) -> 0 | H35: =ABS(IPMT($C$30/12,6,$C$31,$C$29)) -> 0 | I35: =ABS(IPMT($C$30/12,7,$C$31,$C$29)) -> 0 | J35: =ABS(IPMT($C$30/12,8,$C$31,$C$29)) -> 0 | K35: =ABS(IPMT($C$30/12,9,$C$31,$C$29)) -> 0 | L35: =ABS(IPMT($C$30/12,10,$C$31,$C$29)) -> 0 | M35: =ABS(IPMT($C$30/12,11,$C$31,$C$29)) -> 0 | N35: =ABS(IPMT($C$30/12,12,$C$31,$C$29)) -> 0 | O35: =SUM(C35:N35) -> 0
B36: Principal | C36: =ABS(PPMT($C$30/12,1,$C$31,$C$29)) -> 0 | D36: =ABS(PPMT($C$30/12,2,$C$31,$C$29)) -> 0 | E36: =ABS(PPMT($C$30/12,3,$C$31,$C$29)) -> 0 | F36: =ABS(PPMT($C$30/12,4,$C$31,$C$29)) -> 0 | G36: =ABS(PPMT($C$30/12,5,$C$31,$C$29)) -> 0 | H36: =ABS(PPMT($C$30/12,6,$C$31,$C$29)) -> 0 | I36: =ABS(PPMT($C$30/12,7,$C$31,$C$29)) -> 0 | J36: =ABS(PPMT($C$30/12,8,$C$31,$C$29)) -> 0 | K36: =ABS(PPMT($C$30/12,9,$C$31,$C$29)) -> 0 | L36: =ABS(PPMT($C$30/12,10,$C$31,$C$29)) -> 0 | M36: =ABS(PPMT($C$30/12,11,$C$31,$C$29)) -> 0 | N36: =ABS(PPMT($C$30/12,12,$C$31,$C$29)) -> 0 | O36: =SUM(C36:N36) -> 0
B37: Loan Balance | C37: =$C$29-C36 -> 0 | D37: =C37-D36 -> 0 | E37: =D37-E36 -> 0 | F37: =E37-F36 -> 0 | G37: =F37-G36 -> 0 | H37: =G37-H36 -> 0 | I37: =H37-I36 -> 0 | J37: =I37-J36 -> 0 | K37: =J37-K36 -> 0 | ... N37: =M37-N36 -> 0
B38: Year Two
B39: Interest | C39: =IF($C$31<13,0,ABS(IPMT($C$30/12,13,$C$31,$C$29))) -> 0 | D39: =IF($C$31<14,0,ABS(IPMT($C$30/12,14,$C$31,$C$29))) -> 0 | E39: =IF($C$31<15,0,ABS(IPMT($C$30/12,15,$C$31,$C$29))) -> 0 | F39: =IF($C$31<16,0,ABS(IPMT($C$30/12,16,$C$31,$C$29))) -> 0 | G39: =IF($C$31<17,0,ABS(IPMT($C$30/12,17,$C$31,$C$29))) -> 0 | H39: =IF($C$31<18,0,ABS(IPMT($C$30/12,18,$C$31,$C$29))) -> 0 | I39: =IF($C$31<19,0,ABS(IPMT($C$30/12,19,$C$31,$C$29))) -> 0 | J39: =IF($C$31<20,0,ABS(IPMT($C$30/12,20,$C$31,$C$29))) -> 0 | K39: =IF($C$31<21,0,ABS(IPMT($C$30/12,21,$C$31,$C$29))) -> 0 | L39: =IF($C$31<22,0,ABS(IPMT($C$30/12,22,$C$31,$C$29))) -> 0 | M39: =IF($C$31<23,0,ABS(IPMT($C$30/12,23,$C$31,$C$29))) -> 0 | N39: =IF($C$31<24,0,ABS(IPMT($C$30/12,24,$C$31,$C$29))) -> 0 | O39: =SUM(C39:N39) -> 0
B40: Principal | C40: =IF($C$31<13,0,ABS(PPMT($C$30/12,13,$C$31,$C$29))) -> 0 | D40: =IF($C$31<14,0,ABS(PPMT($C$30/12,14,$C$31,$C$29))) -> 0 | E40: =IF($C$31<13,0,ABS(PPMT($C$30/12,15,$C$31,$C$29))) -> 0 | F40: =IF($C$31<16,0,ABS(PPMT($C$30/12,16,$C$31,$C$29))) -> 0 | G40: =IF($C$31<17,0,ABS(PPMT($C$30/12,17,$C$31,$C$29))) -> 0 | H40: =IF($C$31<18,0,ABS(PPMT($C$30/12,18,$C$31,$C$29))) -> 0 | I40: =IF($C$31<19,0,ABS(PPMT($C$30/12,19,$C$31,$C$29))) -> 0 | J40: =IF($C$31<20,0,ABS(PPMT($C$30/12,20,$C$31,$C$29))) -> 0 | K40: =IF($C$31<21,0,ABS(PPMT($C$30/12,21,$C$31,$C$29))) -> 0 | L40: =IF($C$31<22,0,ABS(PPMT($C$30/12,22,$C$31,$C$29))) -> 0 | M40: =IF($C$31<23,0,ABS(PPMT($C$30/12,23,$C$31,$C$29))) -> 0 | N40: =IF($C$31<24,0,ABS(PPMT($C$30/12,24,$C$31,$C$29))) -> 0 | O40: =SUM(C40:N40) -> 0
B41: Loan Balance | C41: =N37-C40 -> 0 | D41: =C41-D40 -> 0 | E41: =D41-E40 -> 0 | F41: =E41-F40 -> 0 | G41: =F41-G40 -> 0 | H41: =G41-H40 -> 0 | I41: =H41-I40 -> 0 | J41: =I41-J40 -> 0 | K41: =J41-K40 -> 0 | ... N41: =M41-N40 -> 0
B42: Year Three
B43: Interest | C43: =IF($C$31<25,0,ABS(IPMT($C$30/12,25,$C$31,$C$29))) -> 0 | D43: =IF($C$31<26,0,ABS(IPMT($C$30/12,26,$C$31,$C$29))) -> 0 | E43: =IF($C$31<27,0,ABS(IPMT($C$30/12,27,$C$31,$C$29))) -> 0 | F43: =IF($C$31<28,0,ABS(IPMT($C$30/12,28,$C$31,$C$29))) -> 0 | G43: =IF($C$31<29,0,ABS(IPMT($C$30/12,29,$C$31,$C$29))) -> 0 | H43: =IF($C$31<29,0,ABS(IPMT($C$30/12,30,$C$31,$C$29))) -> 0 | I43: =IF($C$31<30,0,ABS(IPMT($C$30/12,31,$C$31,$C$29))) -> 0 | J43: =IF($C$31<31,0,ABS(IPMT($C$30/12,32,$C$31,$C$29))) -> 0 | K43: =IF($C$31<32,0,ABS(IPMT($C$30/12,33,$C$31,$C$29))) -> 0 | L43: =IF($C$31<33,0,ABS(IPMT($C$30/12,34,$C$31,$C$29))) -> 0 | M43: =IF($C$31<34,0,ABS(IPMT($C$30/12,35,$C$31,$C$29))) -> 0 | N43: =IF($C$31<35,0,ABS(IPMT($C$30/12,36,$C$31,$C$29))) -> 0 | O43: =SUM(C43:N43) -> 0
B44: Principal | C44: =IF($C$31<25,0,ABS(PPMT($C$30/12,25,$C$31,$C$29))) -> 0 | D44: =IF($C$31<26,0,ABS(PPMT($C$30/12,26,$C$31,$C$29))) -> 0 | E44: =IF($C$31<27,0,ABS(PPMT($C$30/12,27,$C$31,$C$29))) -> 0 | F44: =IF($C$31<28,0,ABS(PPMT($C$30/12,28,$C$31,$C$29))) -> 0 | G44: =IF($C$31<28,0,ABS(PPMT($C$30/12,29,$C$31,$C$29))) -> 0 | H44: =IF($C$31<29,0,ABS(PPMT($C$30/12,30,$C$31,$C$29))) -> 0 | I44: =IF($C$31<30,0,ABS(PPMT($C$30/12,31,$C$31,$C$29))) -> 0 | J44: =IF($C$31<31,0,ABS(PPMT($C$30/12,32,$C$31,$C$29))) -> 0 | K44: =IF($C$31<32,0,ABS(PPMT($C$30/12,33,$C$31,$C$29))) -> 0 | L44: =IF($C$31<33,0,ABS(PPMT($C$30/12,34,$C$31,$C$29))) -> 0 | M44: =IF($C$31<34,0,ABS(PPMT($C$30/12,35,$C$31,$C$29))) -> 0 | N44: =IF($C$31<35,0,ABS(PPMT($C$30/12,36,$C$31,$C$29))) -> 0 | O44: =SUM(C44:N44) -> 0
B45: Loan Balance | C45: =N41-C44 -> 0 | D45: =C45-D44 -> 0 | E45: =D45-E44 -> 0 | F45: =E45-F44 -> 0 | G45: =F45-G44 -> 0 | H45: =G45-H44 -> 0 | I45: =H45-I44 -> 0 | J45: =I45-J44 -> 0 | K45: =J45-K44 -> 0 | ... N45: =M45-N44 -> 0
B48: Credit Card Debt
B49: Principal Amount | C49: =CCDebt -> 0
B50: Interest Rate | C50: ='1-StartingPoint'!E39 -> 0.07
B51: Loan Term in Months | C51: ='1-StartingPoint'!F39 -> 60
B52: Monthly Payment Amount | C52: =ABS(PMT(C50/12,C51,C49)) -> 0
C53: ='3a-SalesForecastYear1'!$C$16 -> Month 1 | D53: ='3a-SalesForecastYear1'!$D$16 -> Month 2 | E53: ='3a-SalesForecastYear1'!$E$16 -> Month 3 | F53: ='3a-SalesForecastYear1'!$F$16 -> Month 4 | G53: ='3a-SalesForecastYear1'!$G$16 -> Month 5 | H53: ='3a-SalesForecastYear1'!$H$16 -> Month 6 | I53: ='3a-SalesForecastYear1'!$I$16 -> Month 7 | J53: ='3a-SalesForecastYear1'!$J$16 -> Month 8 | K53: ='3a-SalesForecastYear1'!$K$16 -> Month 9 | L53: ='3a-SalesForecastYear1'!$L$16 -> Month 10 | M53: ='3a-SalesForecastYear1'!$M$16 -> Month 11 | N53: ='3a-SalesForecastYear1'!$N$16 -> Month 12 | O53: Totals
B54: Year One
B55: Interest | C55: =ABS(IPMT($C$50/12,1,$C$51,$C$49)) -> 0 | D55: =ABS(IPMT($C$50/12,2,$C$51,$C$49)) -> 0 | E55: =ABS(IPMT($C$50/12,3,$C$51,$C$49)) -> 0 | F55: =ABS(IPMT($C$50/12,4,$C$51,$C$49)) -> 0 | G55: =ABS(IPMT($C$50/12,5,$C$51,$C$49)) -> 0 | H55: =ABS(IPMT($C$50/12,6,$C$51,$C$49)) -> 0 | I55: =ABS(IPMT($C$50/12,7,$C$51,$C$49)) -> 0 | J55: =ABS(IPMT($C$50/12,8,$C$51,$C$49)) -> 0 | K55: =ABS(IPMT($C$50/12,9,$C$51,$C$49)) -> 0 | L55: =ABS(IPMT($C$50/12,10,$C$51,$C$49)) -> 0 | M55: =ABS(IPMT($C$50/12,11,$C$51,$C$49)) -> 0 | N55: =ABS(IPMT($C$50/12,12,$C$51,$C$49)) -> 0 | O55: =SUM(C55:N55) -> 0
B56: Principal | C56: =ABS(PPMT($C$50/12,1,$C$51,$C$49)) -> 0 | D56: =ABS(PPMT($C$50/12,2,$C$51,$C$49)) -> 0 | E56: =ABS(PPMT($C$50/12,3,$C$51,$C$49)) -> 0 | F56: =ABS(PPMT($C$50/12,4,$C$51,$C$49)) -> 0 | G56: =ABS(PPMT($C$50/12,5,$C$51,$C$49)) -> 0 | H56: =ABS(PPMT($C$50/12,6,$C$51,$C$49)) -> 0 | I56: =ABS(PPMT($C$50/12,7,$C$51,$C$49)) -> 0 | J56: =ABS(PPMT($C$50/12,8,$C$51,$C$49)) -> 0 | K56: =ABS(PPMT($C$50/12,9,$C$51,$C$49)) -> 0 | L56: =ABS(PPMT($C$50/12,10,$C$51,$C$49)) -> 0 | M56: =ABS(PPMT($C$50/12,11,$C$51,$C$49)) -> 0 | N56: =ABS(PPMT($C$50/12,12,$C$51,$C$49)) -> 0 | O56: =SUM(C56:N56) -> 0
B57: Loan Balance | C57: =$C$49-C56 -> 0 | D57: =C57-D56 -> 0 | E57: =D57-E56 -> 0 | F57: =E57-F56 -> 0 | G57: =F57-G56 -> 0 | H57: =G57-H56 -> 0 | I57: =H57-I56 -> 0 | J57: =I57-J56 -> 0 | K57: =J57-K56 -> 0 | ... N57: =M57-N56 -> 0
B58: Year Two
B59: Interest | C59: =IF($C$51<13,0,ABS(IPMT($C$50/12,13,$C$51,$C$49))) -> 0 | D59: =IF($C$51<14,0,ABS(IPMT($C$50/12,14,$C$51,$C$49))) -> 0 | E59: =IF($C$51<15,0,ABS(IPMT($C$50/12,15,$C$51,$C$49))) -> 0 | F59: =IF($C$51<16,0,ABS(IPMT($C$50/12,16,$C$51,$C$49))) -> 0 | G59: =IF($C$51<17,0,ABS(IPMT($C$50/12,17,$C$51,$C$49))) -> 0 | H59: =IF($C$51<18,0,ABS(IPMT($C$50/12,18,$C$51,$C$49))) -> 0 | I59: =IF($C$51<19,0,ABS(IPMT($C$50/12,19,$C$51,$C$49))) -> 0 | J59: =IF($C$51<20,0,ABS(IPMT($C$50/12,20,$C$51,$C$49))) -> 0 | K59: =IF($C$51<21,0,ABS(IPMT($C$50/12,21,$C$51,$C$49))) -> 0 | L59: =IF($C$51<22,0,ABS(IPMT($C$50/12,22,$C$51,$C$49))) -> 0 | M59: =IF($C$51<23,0,ABS(IPMT($C$50/23,11,$C$51,$C$49))) -> 0 | N59: =IF($C$51<24,0,ABS(IPMT($C$50/12,24,$C$51,$C$49))) -> 0 | O59: =SUM(C59:N59) -> 0
B60: Principal | C60: =IF($C$51<13,0,ABS(PPMT($C$50/12,13,$C$51,$C$49))) -> 0 | D60: =IF($C$51<14,0,ABS(PPMT($C$50/12,14,$C$51,$C$49))) -> 0 | E60: =IF($C$51<15,0,ABS(PPMT($C$50/12,15,$C$51,$C$49))) -> 0 | F60: =IF($C$51<16,0,ABS(PPMT($C$50/12,16,$C$51,$C$49))) -> 0 | G60: =IF($C$51<17,0,ABS(PPMT($C$50/12,17,$C$51,$C$49))) -> 0 | H60: =IF($C$51<18,0,ABS(PPMT($C$50/12,18,$C$51,$C$49))) -> 0 | I60: =IF($C$51<19,0,ABS(PPMT($C$50/12,19,$C$51,$C$49))) -> 0 | J60: =IF($C$51<20,0,ABS(PPMT($C$50/12,20,$C$51,$C$49))) -> 0 | K60: =IF($C$51<21,0,ABS(PPMT($C$50/12,21,$C$51,$C$49))) -> 0 | L60: =IF($C$51<22,0,ABS(PPMT($C$50/12,22,$C$51,$C$49))) -> 0 | M60: =IF($C$51<23,0,ABS(PPMT($C$50/12,23,$C$51,$C$49))) -> 0 | N60: =IF($C$51<24,0,ABS(PPMT($C$50/12,24,$C$51,$C$49))) -> 0 | O60: =SUM(C60:N60) -> 0
B61: Loan Balance | C61: =N57-C60 -> 0 | D61: =C61-D60 -> 0 | E61: =D61-E60 -> 0 | F61: =E61-F60 -> 0 | G61: =F61-G60 -> 0 | H61: =G61-H60 -> 0 | I61: =H61-I60 -> 0 | J61: =I61-J60 -> 0 | K61: =J61-K60 -> 0 | ... N61: =M61-N60 -> 0
B62: Year Three
B63: Interest | C63: =IF($C$51<25,0,ABS(IPMT($C$50/12,25,$C$51,$C$49))) -> 0 | D63: =IF($C$51<26,0,ABS(IPMT($C$50/12,26,$C$51,$C$49))) -> 0 | E63: =IF($C$51<27,0,ABS(IPMT($C$50/12,27,$C$51,$C$49))) -> 0 | F63: =IF($C$51<28,0,ABS(IPMT($C$50/12,28,$C$51,$C$49))) -> 0 | G63: =IF($C$51<29,0,ABS(IPMT($C$50/12,29,$C$51,$C$49))) -> 0 | H63: =IF($C$51<30,0,ABS(IPMT($C$50/12,30,$C$51,$C$49))) -> 0 | I63: =IF($C$51<31,0,ABS(IPMT($C$50/12,31,$C$51,$C$49))) -> 0 | J63: =IF($C$51<32,0,ABS(IPMT($C$50/12,32,$C$51,$C$49))) -> 0 | K63: =IF($C$51<33,0,ABS(IPMT($C$50/12,33,$C$51,$C$49))) -> 0 | L63: =IF($C$51<34,0,ABS(IPMT($C$50/12,34,$C$51,$C$49))) -> 0 | M63: =IF($C$51<35,0,ABS(IPMT($C$50/12,35,$C$51,$C$49))) -> 0 | N63: =IF($C$51<36,0,ABS(IPMT($C$50/12,36,$C$51,$C$49))) -> 0 | O63: =SUM(C63:N63) -> 0
B64: Principal | C64: =IF($C$51<25,0,ABS(PPMT($C$50/12,25,$C$51,$C$49))) -> 0 | D64: =IF($C$51<26,0,ABS(PPMT($C$50/12,26,$C$51,$C$49))) -> 0 | E64: =IF($C$51<27,0,ABS(PPMT($C$50/12,27,$C$51,$C$49))) -> 0 | F64: =IF($C$51<28,0,ABS(PPMT($C$50/12,28,$C$51,$C$49))) -> 0 | G64: =IF($C$51<29,0,ABS(PPMT($C$50/12,29,$C$51,$C$49))) -> 0 | H64: =IF($C$51<30,0,ABS(PPMT($C$50/12,30,$C$51,$C$49))) -> 0 | I64: =IF($C$51<31,0,ABS(PPMT($C$50/12,31,$C$51,$C$49))) -> 0 | J64: =IF($C$51<32,0,ABS(PPMT($C$50/12,32,$C$51,$C$49))) -> 0 | K64: =IF($C$51<33,0,ABS(PPMT($C$50/12,33,$C$51,$C$49))) -> 0 | L64: =IF($C$51<34,0,ABS(PPMT($C$50/12,34,$C$51,$C$49))) -> 0 | M64: =IF($C$51<35,0,ABS(PPMT($C$50/12,35,$C$51,$C$49))) -> 0 | N64: =IF($C$51<36,0,ABS(PPMT($C$50/12,36,$C$51,$C$49))) -> 0 | O64: =SUM(C64:N64) -> 0
B65: Loan Balance | C65: =N61-C64 -> 0 | D65: =C65-D64 -> 0 | E65: =D65-E64 -> 0 | F65: =E65-F64 -> 0 | G65: =F65-G64 -> 0 | H65: =G65-H64 -> 0 | I65: =H65-I64 -> 0 | J65: =I65-J64 -> 0 | K65: =J65-K64 -> 0 | ... N65: =M65-N64 -> 0
B68: Vehicle Loans
B69: Principal Amount | C69: =VehicleLoan -> 0
B70: Interest Rate | C70: ='1-StartingPoint'!E40 -> 0.06
B71: Loan Term in Months | C71: ='1-StartingPoint'!F40 -> 48
B72: Monthly Payment Amount | C72: =ABS(PMT(C70/12,C71,C69)) -> 0
C73: ='3a-SalesForecastYear1'!$C$16 -> Month 1 | D73: ='3a-SalesForecastYear1'!$D$16 -> Month 2 | E73: ='3a-SalesForecastYear1'!$E$16 -> Month 3 | F73: ='3a-SalesForecastYear1'!$F$16 -> Month 4 | G73: ='3a-SalesForecastYear1'!$G$16 -> Month 5 | H73: ='3a-SalesForecastYear1'!$H$16 -> Month 6 | I73: ='3a-SalesForecastYear1'!$I$16 -> Month 7 | J73: ='3a-SalesForecastYear1'!$J$16 -> Month 8 | K73: ='3a-SalesForecastYear1'!$K$16 -> Month 9 | L73: ='3a-SalesForecastYear1'!$L$16 -> Month 10 | M73: ='3a-SalesForecastYear1'!$M$16 -> Month 11 | N73: ='3a-SalesForecastYear1'!$N$16 -> Month 12 | O73: Totals
B74: Year One
B75: Interest | C75: =ABS(IPMT($C$70/12,1,$C$71,$C$69)) -> 0 | D75: =ABS(IPMT($C$70/12,2,$C$71,$C$69)) -> 0 | E75: =ABS(IPMT($C$70/12,3,$C$71,$C$69)) -> 0 | F75: =ABS(IPMT($C$70/12,4,$C$71,$C$69)) -> 0 | G75: =ABS(IPMT($C$70/12,5,$C$71,$C$69)) -> 0 | H75: =ABS(IPMT($C$70/12,6,$C$71,$C$69)) -> 0 | I75: =ABS(IPMT($C$70/12,7,$C$71,$C$69)) -> 0 | J75: =ABS(IPMT($C$70/12,8,$C$71,$C$69)) -> 0 | K75: =ABS(IPMT($C$70/12,9,$C$71,$C$69)) -> 0 | L75: =ABS(IPMT($C$70/12,10,$C$71,$C$69)) -> 0 | M75: =ABS(IPMT($C$70/12,11,$C$71,$C$69)) -> 0 | N75: =ABS(IPMT($C$70/12,12,$C$71,$C$69)) -> 0 | O75: =SUM(C75:N75) -> 0
B76: Principal | C76: =ABS(PPMT($C$70/12,1,$C$71,$C$69)) -> 0 | D76: =ABS(PPMT($C$70/12,2,$C$71,$C$69)) -> 0 | E76: =ABS(PPMT($C$70/12,3,$C$71,$C$69)) -> 0 | F76: =ABS(PPMT($C$70/12,4,$C$71,$C$69)) -> 0 | G76: =ABS(PPMT($C$70/12,5,$C$71,$C$69)) -> 0 | H76: =ABS(PPMT($C$70/12,6,$C$71,$C$69)) -> 0 | I76: =ABS(PPMT($C$70/12,7,$C$71,$C$69)) -> 0 | J76: =ABS(PPMT($C$70/12,8,$C$71,$C$69)) -> 0 | K76: =ABS(PPMT($C$70/12,9,$C$71,$C$69)) -> 0 | L76: =ABS(PPMT($C$70/12,10,$C$71,$C$69)) -> 0 | M76: =ABS(PPMT($C$70/12,11,$C$71,$C$69)) -> 0 | N76: =ABS(PPMT($C$70/12,12,$C$71,$C$69)) -> 0 | O76: =SUM(C76:N76) -> 0
B77: Loan Balance | C77: =$C$69-C76 -> 0 | D77: =C77-D76 -> 0 | E77: =D77-E76 -> 0 | F77: =E77-F76 -> 0 | G77: =F77-G76 -> 0 | H77: =G77-H76 -> 0 | I77: =H77-I76 -> 0 | J77: =I77-J76 -> 0 | K77: =J77-K76 -> 0 | ... N77: =M77-N76 -> 0
B78: Year Two
B79: Interest | C79: =IF($C$71<13,0,ABS(IPMT($C$70/12,13,$C$71,$C$69))) -> 0 | D79: =IF($C$71<14,0,ABS(IPMT($C$70/12,14,$C$71,$C$69))) -> 0 | E79: =IF($C$71<15,0,ABS(IPMT($C$70/12,15,$C$71,$C$69))) -> 0 | F79: =IF($C$71<16,0,ABS(IPMT($C$70/12,16,$C$71,$C$69))) -> 0 | G79: =IF($C$71<17,0,ABS(IPMT($C$70/12,17,$C$71,$C$69))) -> 0 | H79: =IF($C$71<18,0,ABS(IPMT($C$70/12,18,$C$71,$C$69))) -> 0 | I79: =IF($C$71<19,0,ABS(IPMT($C$70/12,19,$C$71,$C$69))) -> 0 | J79: =IF($C$71<20,0,ABS(IPMT($C$70/12,20,$C$71,$C$69))) -> 0 | K79: =IF($C$71<21,0,ABS(IPMT($C$70/12,21,$C$71,$C$69))) -> 0 | L79: =IF($C$71<22,0,ABS(IPMT($C$70/12,22,$C$71,$C$69))) -> 0 | M79: =IF($C$71<23,0,ABS(IPMT($C$70/12,23,$C$71,$C$69))) -> 0 | N79: =IF($C$71<24,0,ABS(IPMT($C$70/12,24,$C$71,$C$69))) -> 0 | O79: =SUM(C79:N79) -> 0
B80: Principal | C80: =IF($C$71<13,0,ABS(PPMT($C$70/12,13,$C$71,$C$69))) -> 0 | D80: =IF($C$71<14,0,ABS(PPMT($C$70/12,14,$C$71,$C$69))) -> 0 | E80: =IF($C$71<15,0,ABS(PPMT($C$70/12,15,$C$71,$C$69))) -> 0 | F80: =IF($C$71<16,0,ABS(PPMT($C$70/12,16,$C$71,$C$69))) -> 0 | G80: =IF($C$71<17,0,ABS(PPMT($C$70/12,17,$C$71,$C$69))) -> 0 | H80: =IF($C$71<18,0,ABS(PPMT($C$70/12,18,$C$71,$C$69))) -> 0 | I80: =IF($C$71<19,0,ABS(PPMT($C$70/12,19,$C$71,$C$69))) -> 0 | J80: =IF($C$71<20,0,ABS(PPMT($C$70/12,20,$C$71,$C$69))) -> 0 | K80: =IF($C$71<21,0,ABS(PPMT($C$70/12,21,$C$71,$C$69))) -> 0 | L80: =IF($C$71<22,0,ABS(PPMT($C$70/12,22,$C$71,$C$69))) -> 0 | M80: =IF($C$71<23,0,ABS(PPMT($C$70/12,23,$C$71,$C$69))) -> 0 | N80: =IF($C$71<24,0,ABS(PPMT($C$70/12,24,$C$71,$C$69))) -> 0 | O80: =SUM(C80:N80) -> 0
B81: Loan Balance | C81: =N77-C80 -> 0 | D81: =C81-D80 -> 0 | E81: =D81-E80 -> 0 | F81: =E81-F80 -> 0 | G81: =F81-G80 -> 0 | H81: =G81-H80 -> 0 | I81: =H81-I80 -> 0 | J81: =I81-J80 -> 0 | K81: =J81-K80 -> 0 | ... N81: =M81-N80 -> 0
B82: Year Three
B83: Interest | C83: =IF($C$71<25,0,ABS(IPMT($C$70/12,25,$C$71,$C$69))) -> 0 | D83: =IF($C$71<26,0,ABS(IPMT($C$70/12,26,$C$71,$C$69))) -> 0 | E83: =IF($C$71<27,0,ABS(IPMT($C$70/12,27,$C$71,$C$69))) -> 0 | F83: =IF($C$71<28,0,ABS(IPMT($C$70/12,28,$C$71,$C$69))) -> 0 | G83: =IF($C$71<29,0,ABS(IPMT($C$70/12,29,$C$71,$C$69))) -> 0 | H83: =IF($C$71<30,0,ABS(IPMT($C$70/12,30,$C$71,$C$69))) -> 0 | I83: =IF($C$71<31,0,ABS(IPMT($C$70/12,31,$C$71,$C$69))) -> 0 | J83: =IF($C$71<32,0,ABS(IPMT($C$70/12,32,$C$71,$C$69))) -> 0 | K83: =IF($C$71<33,0,ABS(IPMT($C$70/12,33,$C$71,$C$69))) -> 0 | L83: =IF($C$71<34,0,ABS(IPMT($C$70/12,34,$C$71,$C$69))) -> 0 | M83: =IF($C$71<34,0,ABS(IPMT($C$70/12,35,$C$71,$C$69))) -> 0 | N83: =IF($C$71<36,0,ABS(IPMT($C$70/12,36,$C$71,$C$69))) -> 0 | O83: =SUM(C83:N83) -> 0
B84: Principal | C84: =IF($C$71<25,0,ABS(PPMT($C$70/12,25,$C$71,$C$69))) -> 0 | D84: =IF($C$71<26,0,ABS(PPMT($C$70/12,26,$C$71,$C$69))) -> 0 | E84: =IF($C$71<27,0,ABS(PPMT($C$70/12,27,$C$71,$C$69))) -> 0 | F84: =IF($C$71<28,0,ABS(PPMT($C$70/12,28,$C$71,$C$69))) -> 0 | G84: =IF($C$71<29,0,ABS(PPMT($C$70/12,29,$C$71,$C$69))) -> 0 | H84: =IF($C$71<30,0,ABS(PPMT($C$70/12,30,$C$71,$C$69))) -> 0 | I84: =IF($C$71<31,0,ABS(PPMT($C$70/12,31,$C$71,$C$69))) -> 0 | J84: =IF($C$71<32,0,ABS(PPMT($C$70/12,32,$C$71,$C$69))) -> 0 | K84: =IF($C$71<33,0,ABS(PPMT($C$70/12,33,$C$71,$C$69))) -> 0 | L84: =IF($C$71<34,0,ABS(PPMT($C$70/12,34,$C$71,$C$69))) -> 0 | M84: =ABS(PPMT($C$70/12,35,$C$71,$C$69)) -> 0 | N84: =IF($C$71<36,0,ABS(PPMT($C$70/12,36,$C$71,$C$69))) -> 0 | O84: =SUM(C84:N84) -> 0
B85: Loan Balance | C85: =N81-C84 -> 0 | D85: =C85-D84 -> 0 | E85: =D85-E84 -> 0 | F85: =E85-F84 -> 0 | G85: =F85-G84 -> 0 | H85: =G85-H84 -> 0 | I85: =H85-I84 -> 0 | J85: =I85-J84 -> 0 | K85: =J85-K84 -> 0 | ... N85: =M85-N84 -> 0
B88: Other Bank Debt
B89: Principal Amount | C89: =OtherBankDebt -> 0
B90: Interest Rate | C90: ='1-StartingPoint'!E41 -> 0.05
B91: Loan Term in Months | C91: ='1-StartingPoint'!F41 -> 36
B92: Monthly Payment Amount | C92: =ABS(PMT(C90/12,C91,C89)) -> 0
C93: ='3a-SalesForecastYear1'!$C$16 -> Month 1 | D93: ='3a-SalesForecastYear1'!$D$16 -> Month 2 | E93: ='3a-SalesForecastYear1'!$E$16 -> Month 3 | F93: ='3a-SalesForecastYear1'!$F$16 -> Month 4 | G93: ='3a-SalesForecastYear1'!$G$16 -> Month 5 | H93: ='3a-SalesForecastYear1'!$H$16 -> Month 6 | I93: ='3a-SalesForecastYear1'!$I$16 -> Month 7 | J93: ='3a-SalesForecastYear1'!$J$16 -> Month 8 | K93: ='3a-SalesForecastYear1'!$K$16 -> Month 9 | L93: ='3a-SalesForecastYear1'!$L$16 -> Month 10 | M93: ='3a-SalesForecastYear1'!$M$16 -> Month 11 | N93: ='3a-SalesForecastYear1'!$N$16 -> Month 12 | O93: Totals
B94: Year One
B95: Interest | C95: =ABS(IPMT($C$90/12,1,$C$91,$C$89)) -> 0 | D95: =ABS(IPMT($C$90/12,2,$C$91,$C$89)) -> 0 | E95: =ABS(IPMT($C$90/12,3,$C$91,$C$89)) -> 0 | F95: =ABS(IPMT($C$90/12,4,$C$91,$C$89)) -> 0 | G95: =ABS(IPMT($C$90/12,5,$C$91,$C$89)) -> 0 | H95: =ABS(IPMT($C$90/12,6,$C$91,$C$89)) -> 0 | I95: =ABS(IPMT($C$90/12,7,$C$91,$C$89)) -> 0 | J95: =ABS(IPMT($C$90/12,8,$C$91,$C$89)) -> 0 | K95: =ABS(IPMT($C$90/12,9,$C$91,$C$89)) -> 0 | L95: =ABS(IPMT($C$90/12,10,$C$91,$C$89)) -> 0 | M95: =ABS(IPMT($C$90/12,11,$C$91,$C$89)) -> 0 | N95: =ABS(IPMT($C$90/12,12,$C$91,$C$89)) -> 0 | O95: =SUM(C95:N95) -> 0
B96: Principal | C96: =ABS(PPMT($C$90/12,1,$C$91,$C$89)) -> 0 | D96: =ABS(PPMT($C$90/12,2,$C$91,$C$89)) -> 0 | E96: =ABS(PPMT($C$90/12,3,$C$91,$C$89)) -> 0 | F96: =ABS(PPMT($C$90/12,4,$C$91,$C$89)) -> 0 | G96: =ABS(PPMT($C$90/12,5,$C$91,$C$89)) -> 0 | H96: =ABS(PPMT($C$90/12,6,$C$91,$C$89)) -> 0 | I96: =ABS(PPMT($C$90/12,7,$C$91,$C$89)) -> 0 | J96: =ABS(PPMT($C$90/12,8,$C$91,$C$89)) -> 0 | K96: =ABS(PPMT($C$90/12,9,$C$91,$C$89)) -> 0 | L96: =ABS(PPMT($C$90/12,10,$C$91,$C$89)) -> 0 | M96: =ABS(PPMT($C$90/12,11,$C$91,$C$89)) -> 0 | N96: =ABS(PPMT($C$90/12,12,$C$91,$C$89)) -> 0 | O96: =SUM(C96:N96) -> 0
B97: Loan Balance | C97: =$C$89-C96 -> 0 | D97: =C97-D96 -> 0 | E97: =D97-E96 -> 0 | F97: =E97-F96 -> 0 | G97: =F97-G96 -> 0 | H97: =G97-H96 -> 0 | I97: =H97-I96 -> 0 | J97: =I97-J96 -> 0 | K97: =J97-K96 -> 0 | ... N97: =M97-N96 -> 0
B98: Year Two
B99: Interest | C99: =IF($C$91<13,0,ABS(IPMT($C$90/12,13,$C$91,$C$89))) -> 0 | D99: =IF($C$91<14,0,ABS(IPMT($C$90/12,14,$C$91,$C$89))) -> 0 | E99: =IF($C$91<15,0,ABS(IPMT($C$90/12,15,$C$91,$C$89))) -> 0 | F99: =IF($C$91<16,0,ABS(IPMT($C$90/12,16,$C$91,$C$89))) -> 0 | G99: =IF($C$91<17,0,ABS(IPMT($C$90/12,17,$C$91,$C$89))) -> 0 | H99: =IF($C$91<18,0,ABS(IPMT($C$90/12,18,$C$91,$C$89))) -> 0 | I99: =IF($C$91<19,0,ABS(IPMT($C$90/12,19,$C$91,$C$89))) -> 0 | J99: =IF($C$91<20,0,ABS(IPMT($C$90/12,20,$C$91,$C$89))) -> 0 | K99: =IF($C$91<21,0,ABS(IPMT($C$90/12,21,$C$91,$C$89))) -> 0 | L99: =IF($C$91<22,0,ABS(IPMT($C$90/12,22,$C$91,$C$89))) -> 0 | M99: =IF($C$91<23,0,ABS(IPMT($C$90/23,11,$C$91,$C$89))) -> 0 | N99: =IF($C$91<24,0,ABS(IPMT($C$90/12,24,$C$91,$C$89))) -> 0 | O99: =SUM(C99:N99) -> 0
B100: Principal | C100: =IF($C$91<13,0,ABS(PPMT($C$90/12,13,$C$91,$C$89))) -> 0 | D100: =IF($C$91<14,0,ABS(PPMT($C$90/12,14,$C$91,$C$89))) -> 0 | E100: =IF($C$91<15,0,ABS(PPMT($C$90/12,15,$C$91,$C$89))) -> 0 | F100: =IF($C$91<16,0,ABS(PPMT($C$90/12,16,$C$91,$C$89))) -> 0 | G100: =IF($C$91<17,0,ABS(PPMT($C$90/12,17,$C$91,$C$89))) -> 0 | H100: =IF($C$91<18,0,ABS(PPMT($C$90/12,18,$C$91,$C$89))) -> 0 | I100: =IF($C$91<19,0,ABS(PPMT($C$90/12,19,$C$91,$C$89))) -> 0 | J100: =IF($C$91<20,0,ABS(PPMT($C$90/12,20,$C$91,$C$89))) -> 0 | K100: =IF($C$91<21,0,ABS(PPMT($C$90/12,21,$C$91,$C$89))) -> 0 | L100: =IF($C$91<22,0,ABS(PPMT($C$90/12,22,$C$91,$C$89))) -> 0 | M100: =IF($C$91<23,0,ABS(PPMT($C$90/12,23,$C$91,$C$89))) -> 0 | N100: =IF($C$91<24,0,ABS(PPMT($C$90/12,24,$C$91,$C$89))) -> 0 | O100: =SUM(C100:N100) -> 0
B101: Loan Balance | C101: =N97-C100 -> 0 | D101: =C101-D100 -> 0 | E101: =D101-E100 -> 0 | F101: =E101-F100 -> 0 | G101: =F101-G100 -> 0 | H101: =G101-H100 -> 0 | I101: =H101-I100 -> 0 | J101: =I101-J100 -> 0 | K101: =J101-K100 -> 0 | ... N101: =M101-N100 -> 0
B102: Year Three
B103: Interest | C103: =IF($C$91<25,0,ABS(IPMT($C$90/12,25,$C$91,$C$89))) -> 0 | D103: =IF($C$91<26,0,ABS(IPMT($C$90/12,26,$C$91,$C$89))) -> 0 | E103: =IF($C$91<27,0,ABS(IPMT($C$90/12,27,$C$91,$C$89))) -> 0 | F103: =IF($C$91<28,0,ABS(IPMT($C$90/12,28,$C$91,$C$89))) -> 0 | G103: =IF($C$91<29,0,ABS(IPMT($C$90/12,29,$C$91,$C$89))) -> 0 | H103: =IF($C$91<30,0,ABS(IPMT($C$90/12,30,$C$91,$C$89))) -> 0 | I103: =IF($C$91<31,0,ABS(IPMT($C$90/12,31,$C$91,$C$89))) -> 0 | J103: =IF($C$91<32,0,ABS(IPMT($C$90/12,32,$C$91,$C$89))) -> 0 | K103: =IF($C$91<33,0,ABS(IPMT($C$90/12,33,$C$91,$C$89))) -> 0 | L103: =IF($C$91<34,0,ABS(IPMT($C$90/12,34,$C$91,$C$89))) -> 0 | M103: =IF($C$91<35,0,ABS(IPMT($C$90/12,35,$C$91,$C$89))) -> 0 | N103: =IF($C$91<36,0,ABS(IPMT($C$90/12,36,$C$91,$C$89))) -> 0 | O103: =SUM(C103:N103) -> 0
B104: Principal | C104: =IF($C$91<25,0,ABS(PPMT($C$90/12,25,$C$91,$C$89))) -> 0 | D104: =IF($C$91<26,0,ABS(PPMT($C$90/12,26,$C$91,$C$89))) -> 0 | E104: =IF($C$91<27,0,ABS(PPMT($C$90/12,27,$C$91,$C$89))) -> 0 | F104: =IF($C$91<28,0,ABS(PPMT($C$90/12,28,$C$91,$C$89))) -> 0 | G104: =IF($C$91<29,0,ABS(PPMT($C$90/12,29,$C$91,$C$89))) -> 0 | H104: =IF($C$91<30,0,ABS(PPMT($C$90/12,30,$C$91,$C$89))) -> 0 | I104: =IF($C$91<31,0,ABS(PPMT($C$90/12,31,$C$91,$C$89))) -> 0 | J104: =IF($C$91<32,0,ABS(PPMT($C$90/12,32,$C$91,$C$89))) -> 0 | K104: =IF($C$91<33,0,ABS(PPMT($C$90/12,33,$C$91,$C$89))) -> 0 | L104: =IF($C$91<34,0,ABS(PPMT($C$90/12,34,$C$91,$C$89))) -> 0 | M104: =IF($C$91<35,0,ABS(PPMT($C$90/12,35,$C$91,$C$89))) -> 0 | N104: =IF($C$91<36,0,ABS(PPMT($C$90/12,36,$C$91,$C$89))) -> 0 | O104: =SUM(C104:N104) -> 0
